Workbook

Sheet reference
A1: Order created at | B1: Order description | C1: Recipient name | D1: Recipient address | E1: Recipient phone | F1: proft | G1: Collected amount | H1: Total fee | I1: Order status | J1: Order status 2
A2: 45916.191 | B2: Martin 2 sole half | C2: Amit Magar | D2: Dharan, bhanu chowk | E2: 9849401180 | F2: 350 | G2: 1350 | H2: 162.38 | I2: Delivered | J2: 45918.315
A3: 45916.19 | B3: N and red 37 and 40 | C3: Prabin karki | D3: Solukhumbu tingla | E3: 9749215487 | F3: 450 | G3: 2550 | H3: 215.38 | I3: Delivered | J3: 45919.617
A4: 45895.495 | B4: Martin 1 sole 42 | C4: Smriti and Smaran store (Smriti And Smaran Store) | D4: Jorpati, Sano bazaar shop no. 25, Kathmandu,27.721747093899435, 85.37363752197368 | E4: 9847465097 | F4: 0 | G4: 0 | H4: 144.5 | I4: Returned To Merchant | J4: 45898.212
A5: 45895.34 | B5: Red Nike 40 | C5: Smriti and Smaran store (Smriti And Smaran Store) | D5: Jorpati, Sano bazaar shop no. 25, Kathmandu,27.721747093899435, 85.37363752197368 | E5: 9847465097 | F5: 0 | G5: 0 | H5: 144.5 | I5: Returned To Merchant | J5: 45898.212
A6: 45894.197 | B6: Martin 1 sole 36 | C6: Manoj | D6: Sundarijal, ktm dobato chowk | E6: 9768966994 | F6: 300 | G6: 1100 | H6: 101.75 | I6: Delivered | J6: 45894.442
A7: 45893.181 | B7: Martin 3 sole 41 | C7: Manish Bishwokarma | D7: Tanahun, dulegauda | E7: 9815193182 | F7: 650 | G7: 1650 | H7: 183.13 | I7: Delivered | J7: 45894.315
A8: 45893.179 | B8: Blue Nike 39 | C8: Rajdip Chudal | D8: Haldibari 4, magalbare jhapa | E8: 9815936372 | F8: 350 | G8: 1350 | H8: 182.38 | I8: Delivered | J8: 45895.446
A9: 45893.178 | B9: Martin 3 sole size 39 39 38 | C9: Laxmi Rai | D9: Shree antu, baral bhanjyang | E9: 9769723304 | F9: 1300 | G9: 4650 | H9: 220.63 | I9: Delivered | J9: 45898.377
A10: 45892.286 | B10: Nike 11 red and Martin 2 sole 42 and 43 | C10: Dipak Shah | D10: Tinkune, the new summit college | E10: 9826881955 | F10: 800 | G10: 2600 | H10: 105.5 | I10: Delivered | J10: 45893.253
A11: 45892.233 | B11: Red Nike 40 | C11: Bishwas | D11: Chitwan, tandi | E11: 9708251241 | F11: 0 | G11: 0 | H11: 0 | I11: Return | J11: 45895.334
A12: 45892.231 | B12: Martin 1 sole 42 | C12: Rishav Shah | D12: Birgunj, murlibagaicha | E12: 9805639259 | F12: 0 | G12: 0 | H12: 0 | I12: Return | J12: 45895.247
A13: 45892.228 | B13: Martin 1 sole 43 | C13: Chandra Bohara | D13: Dadeldhura, bagbazzar tufandadko check najik police bit | E13: 9865629618 | F13: 450 | G13: 1350 | H13: 182.38 | I13: Delivered | J13: 45895.355
... A45: 45865.178 | B45: Dark brown 40 | C45: Govinda Khatiwada | D45: Salleri bazar, solukhumbu | E45: 9869667233 | F45: 320 | G45: 1320 | H45: 212.3 | I45: Delivered | J45: 45867.602
A46: 45864.496 | C46: Smriti and Smaran store (Smriti And Smaran Store) | D46: Jorpati, Sano bazaar shop no. 25, Kathmandu,27.721747093899435, 85.37363752197368 | E46: 9847465097 | F46: 0 | G46: 0 | H46: 161.5 | I46: Returned To Merchant | J46: 45869.275
A47: 45864.205 | B47: Size 39 Martin 3 sole | C47: Rohan | D47: Manakamana suit hotel, gogechaur, banepa | E47: 9701538165 | F47: 600 | G47: 1600 | H47: 163 | I47: Delivered | J47: 45865.527
A48: 45864.204 | B48: Single sole Martin 43 | C48: Ankit Rajbanshi | D48: Mechinagar-10, dhulabari, jhapa | E48: 9827940827 | F48: 350 | G48: 1350 | H48: 182.38 | I48: Delivered | J48: 45866.45
A49: 45864.198 | B49: Martin 3 sole size 39 | C49: Kevin Tamang | D49: Chitwan, pokhara buspark | E49: 9701268575 | F49: 0 | G49: 0 | H49: 0 | I49: Return | J49: 45868.457
A50: 45864.192 | B50: Brown 40 | C50: Toshu Sah | D50: Chyasal, lalitpur | E50: 9700310751 | F50: 300 | G50: 1300 | H50: 102.25 | I50: Delivered | J50: 45865.18
A51: 45863.478 | B51: Vans 40 | C51: Smriti and Smaran store (Smriti And Smaran Store) | D51: Jorpati, Sano bazaar shop no. 25, Kathmandu,27.721747093899435, 85.37363752197368 | E51: 9847465097 | F51: 0 | G51: 0 | H51: 204 | I51: Returned To Merchant | J51: 45868.957
A52: 45863.225 | B52: Martin half double sole | C52: Abhishek rokaya | D52: Durbarmarg , yakyeti marg Jane bato | E52: 9822767923 | F52: 400 | G52: 1300 | H52: 102.25 | I52: Delivered | J52: 45863.423
A53: 45863.223 | B53: Sky blue Nike size 42 | C53: Rohan Grg Prajoo | D53: Tersapatti 3 pokhara | E53: 9705554376 | F53: 350 | G53: 1350 | H53: 162.38 | I53: Delivered | J53: 45866.33
A54: 45863.203 | B54: Red Nike 43 | C54: Sagar | D54: Dhangadhi bhakat chowk, ward no. 9 | E54: 9814660801 | F54: 350 | G54: 1350 | H54: 182.38 | I54: Delivered | J54: 45865.279
A55: 45863.202 | B55: Nike white and vans 41 | C55: Manoj Parsai | D55: Nayabazar 10, pokhara, kaski | E55: 9816148089 | F55: 950 | G55: 2550 | H55: 165.38 | I55: Delivered | J55: 45864.416
A56: 45862.197 | B56: Sr sports and vans 42 | C56: Abhishek Shrestha | D56: Tokha, kathmandu | E56: 9803226972 | F56: 900 | G56: 2500 | H56: 105.25 | I56: Delivered | J56: 45863.314
A57: 45862.195 | B57: Dark brown 42 | C57: Suraj Gyawali | D57: Parsyang pokhara | E57: 9847307560 | F57: 350 | G57: 1350 | H57: 162.38 | I57: Delivered | J57: 45863.42
A58: 45862.188 | B58: Vans 42 | C58: Bhuwan Dev | D58: Soil management dictorate harihar bhawan, lalitpur | E58: 9766381427 | F58: 700 | G58: 1300 | H58: 102.25 | I58: Delivered | J58: 45863.283
A59: 45861.205 | C59: Srawon Magar | D59: Sindhuli bazzar, kabiram | E59: 9844184404 | F59: 0 | G59: 0 | H59: 0 | I59: Return | J59: 45864.38
A60: 45861.201 | B60: Dunk Low pro 39 | C60: Arpan Neupane | D60: Kharaney path, leknath kaski | E60: 9846952971 | F60: 350 | G60: 1350 | H60: 162.38 | I60: Delivered | J60: 45862.362
A61: 45861.199 | B61: Vans 41 | C61: Menal Shrestha | D61: Steel Tower, jawalakhel | E61: 9818994553 | F61: 700 | G61: 1300 | H61: 102.25 | I61: Delivered | J61: 45861.444
A62: 45860.993 | B62: Vans size 40 | C62: Arjun | D62: Simara, iccha hotel | E62: 9824283470 | F62: 0 | G62: 0 | H62: 182.38 | I62: Pickup Cancel | J62: 45863.422
A63: 45860.511 | B63: Sr delta size 39 | C63: Sanjit Tamang | D63: Sirutar, bhaktapur | E63: 9826764749 | F63: 300 | G63: 1300 | H63: 102.25 | I63: Delivered | J63: 45862.395
A64: 45860.138 | B64: Sr delta size 39 | C64: Smriti and Smaran store (Smriti And Smaran Store) | D64: Jorpati, Sano bazaar shop no. 25, Kathmandu,27.721747093899435, 85.37363752197368 | E64: 9847465097 | F64: 0 | G64: 0 | H64: 42.5 | I64: Returned To Merchant | J64: 45863.213
A65: 45859.484 | B65: Vans 41 | C65: Smriti and Smaran store (Smriti And Smaran Store) | D65: Jorpati, Sano bazaar shop no. 25, Kathmandu,27.721747093899435, 85.37363752197368 | E65: 9847465097 | F65: 0 | G65: 0 | H65: 204 | I65: Returned To Merchant | J65: 45873.684
A66: 45858.192 | B66: Sr delta size 39 | C66: Sanjit Tamang | D66: Sirutar, bhaktapur | E66: 9826764749 | F66: 0 | G66: 0 | H66: 0 | I66: Return | J66: 45860.135
A67: 45857.228 | B67: Vans 43 | C67: Newar Shyam | D67: Pakhapani, dang | E67: 9843713594 | F67: 750 | G67: 1350 | H67: 232.38 | I67: Delivered | J67: 45860.518
A68: 45857.209 | B68: Gray 42 | C68: Diwash | D68: Morang pathari | E68: 9746898035 | F68: 450 | G68: 1450 | H68: 232.63 | I68: Delivered | J68: 45862.316
A69: 45857.207 | B69: Vans 40 | C69: Arjun | D69: Simara, iccha hotel | E69: 9824283470 | F69: 0 | G69: 0 | H69: 0 | I69: Return | J69: 45863.394
A70: 45857.206 | B70: Nike White and gray 43 | C70: Nishan sigdel | D70: Sunsari, ramdhuni bhasi, lalpur | E70: 9829369398 | F70: 450 | G70: 2450 | H70: 215.13 | I70: Delivered | J70: 45860.334
A71: 45857.199 | B71: Brown 39 nike | C71: Samir Khadka | D71: Mullani, manakamana mandir | E71: 9803441330 | F71: 300 | G71: 1300 | H71: 152.25 | I71: Delivered | J71: 45858.386
... A113: 45806.446 | B113: Lofer black size 39 | C113: MD noore nabi | D113: Butwal, pharsatikar 4 | E113: 9704729700 | F113: 500 | G113: 1300 | H113: 82.25 | I113: Delivered | J113: 45809.488
A114: 45806.441 | C114: Bibek rai | D114: Lalitpur, purna Chandi mandir | E114: 9810065122 | F114: 260 | G114: 1260 | H114: 3.15 | I114: Delivered | J114: 45807.219
A115: 45806.435 | B115: Brown Nike size 41 | C115: Nisan or jibika tamang | D115: Dhulabari | E115: 9764470296 | F115: 300 | G115: 1300 | H115: 82.25 | I115: Delivered | J115: 45809.376
A116: 45806.43 | B116: Brown Nike of size 36 | C116: Salin | D116: Dilli bazzar, ktm | E116: 9847148778 | F116: 300 | G116: 1300 | H116: 3.25 | I116: Delivered | J116: 45807.3
A117: 45806.194 | B117: White shoes size 42 | C117: Sohail | D117: Binam kasmetik and gift shop, kalanki | E117: 9761875124 | F117: 0 | G117: 0 | H117: 0 | I117: Return | J117: 45807.389
A118: 45806.189 | B118: Vans shoes size 37 | C118: Bikash chaulagain | D118: Kalikot tadi | E118: 9765455610 | F118: 0 | G118: 1300 | H118: 82.25 | I118: Delivered | J118: 45809.596
A119: 45806.185 | B119: White shoes size 43 | C119: Nabin | D119: Bhaktapur duwakot near kmc hospital | E119: 9849083465 | F119: 300 | G119: 1300 | H119: 3.25 | I119: Delivered | J119: 45806.491
A120: 45806.183 | B120: Sr shoes size 39 | C120: Siddharth | D120: PepsiCola kapur garden, ktm | E120: 9865111985 | F120: 260 | G120: 1260 | H120: 3.15 | I120: Delivered | J120: 45806.514
A121: 45806.179 | B121: Samba shoes size 37 | C121: Jenny kumal | D121: Kushma parbat | E121: 9805122929 | F121: 300 | G121: 1300 | H121: 82.25 | I121: Delivered | J121: 45813.317
A122: 45806.176 | B122: Dr. Martin single sole size 41 | C122: Ram karki | D122: Bhojpur | E122: 9864549595 | F122: 300 | G122: 1300 | H122: 82.25 | I122: Delivered | J122: 45809.596
A123: 45806.173 | B123: Sport shoes Nike waterproof size 42 | C123: Dil Bahadur pariyar | D123: Pokhara 18, besitol near baglung buspark | E123: 9805885012 | F123: 300 | G123: 1300 | H123: 82.25 | I123: Delivered | J123: 45807.333
A124: 45785.089 | B124: Red jordan | C124: Aditya mukhiya bin | D124: Mmc college road, manakamana chowk, hetauda | E124: 9704578101 | F124: 200 | G124: 1200 | H124: 3 | I124: Delivered | J124: 45786.363
A125: 45785.088 | B125: Maroon full Jordan of size 42 | C125: Dany | D125: Katari, udayapur | E125: 9708876627 | F125: 200 | G125: 1200 | H125: 3 | I125: Delivered | J125: 45790.401
A126: 45782.226 | B126: Red full Jordan and white Nike of size 41 costing RS. 1200 each | C126: Arman Kapar | D126: Gyanseshwor Chowk opposite of German embassy | E126: 9813149928 | F126: 400 | G126: 2400 | H126: 6 | I126: Delivered | J126: 45783.219
... A160: 45761.513 | B160: Shoes cost | C160: Aashish basnet | D160: Pm general store | E160: 9749878703 | F160: 500 | G160: 1500 | H160: 3.75 | I160: Delivered | J160: 45763.319
A161: ='return order'!A2 -> 45894.195 | B161: ='return order'!B2 -> Brown Nike 40 | C161: ='return order'!C2 -> Aashish Thakuri | D161: ='return order'!D2 -> Dang, lamahi bazzar | E161: ='return order'!E2 -> 9749766969 | F161: 0 | G161: {=XLOOKUP(C161, 'return order'!$C$2:$C$29, 'return order'!$F$2:$F$29, 0)} -> 1350 | H161: ='return order'!G2 -> 161.5 | I161: ='return order'!I2 -> Return | J161: ='return order'!K2 -> 45898.349
A162: ='return order'!A3 -> 45893.184 | B162: ='return order'!B3 -> Utsav 41 | C162: ='return order'!C3 -> Janak Karki | D162: ='return order'!D3 -> Dailekh, dullu nagarpalika ward 4, bhandari ghau | E162: ='return order'!E3 -> 9803727667 | F162: 0 | G162: {=XLOOKUP(C162, 'return order'!$C$2:$C$29, 'return order'!$F$2:$F$29, 0)} -> 1350 | H162: ='return order'!G3 -> 187 | I162: ='return order'!I3 -> Return | J162: ='return order'!K3 -> 45900.385
A163: ='return order'!A4 -> 45893.182 | B163: ='return order'!B4 -> White Nike 42 | C163: ='return order'!C4 -> Sushi Yogi | D163: ='return order'!D4 -> Tokha, chandeswari | E163: ='return order'!E4 -> 9829685117 | F163: 0 | G163: {=XLOOKUP(C163, 'return order'!$C$2:$C$29, 'return order'!$F$2:$F$29, 0)} -> 1300 | H163: ='return order'!G4 -> 30 | I163: ='return order'!I4 -> Return | J163: ='return order'!K4 -> 45895.512
A164: ='return order'!A5 -> 45891.189 | B164: ='return order'!B5 -> Red Nike 42 | C164: ='return order'!C5 -> Krishna Saud | D164: ='return order'!D5 -> Kailali, lamki | E164: ='return order'!E5 -> 9862054261 | F164: 0 | G164: {=XLOOKUP(C164, 'return order'!$C$2:$C$29, 'return order'!$F$2:$F$29, 0)} -> 1350 | H164: ='return order'!G5 -> 187 | I164: ='return order'!I5 -> Return | J164: ='return order'!K5 -> 45898.338
A165: ='return order'!A6 -> 45891.188 | B165: ='return order'!B6 -> Martin 3 sole 40 | C165: ='return order'!C6 -> Magar Samuyal | D165: ='return order'!D6 -> Dailey Jilla, dullu gaupalika | E165: ='return order'!E6 -> 9700989853 | F165: 0 | G165: {=XLOOKUP(C165, 'return order'!$C$2:$C$29, 'return order'!$F$2:$F$29, 0)} -> 1550 | H165: ='return order'!G6 -> 187 | I165: ='return order'!I6 -> Return | J165: ='return order'!K6 -> 45897.436
A166: ='return order'!A7 -> 45890.182 | B166: ='return order'!B7 -> Red Nike and smile 40 | C166: ='return order'!C7 -> Abhishek Rana Magar | D166: ='return order'!D7 -> Okhaldunga, manebhanjyang view | E166: ='return order'!E7 -> 9767194547 | F166: 0 | G166: {=XLOOKUP(C166, 'return order'!$C$2:$C$29, 'return order'!$F$2:$F$29, 0)} -> 2650 | H166: ='return order'!G7 -> 187 | I166: ='return order'!I7 -> Return | J166: ='return order'!K7 -> 45901.343
A167: ='return order'!A8 -> 45890.18 | B167: ='return order'!B8 -> Chelsea and black Nike 40 | C167: ='return order'!C8 -> Bir Tamang | D167: ='return order'!D8 -> Lakeside pokhara, vakunde | E167: ='return order'!E8 -> 9700572480 | F167: 0 | G167: {=XLOOKUP(C167, 'return order'!$C$2:$C$29, 'return order'!$F$2:$F$29, 0)} -> 2600 | H167: ='return order'!G8 -> 144.5 | I167: ='return order'!I8 -> Return | J167: ='return order'!K8 -> 45896.294
A168: ='return order'!A9 -> 45888.186 | B168: ='return order'!B9 -> Martin 3 sole size 40 | C168: ='return order'!C9 -> Chom Xettry | D168: ='return order'!D9 -> Rolpa, sulichaur | E168: ='return order'!E9 -> 9763886248 | F168: 0 | G168: {=XLOOKUP(C168, 'return order'!$C$2:$C$29, 'return order'!$F$2:$F$29, 0)} -> 1650 | H168: ='return order'!G9 -> 187 | I168: ='return order'!I9 -> Return | J168: ='return order'!K9 -> 45897.41
A169: ='return order'!A10 -> 45887.16 | B169: ='return order'!B10 -> Sr shoes 40 | C169: ='return order'!C10 -> Nawraj Shah | D169: ='return order'!D10 -> Biratnagar, new moon school ward 18 | E169: ='return order'!E10 -> 9801468689 | F169: 0 | G169: {=XLOOKUP(C169, 'return order'!$C$2:$C$29, 'return order'!$F$2:$F$29, 0)} -> 1300 | H169: ='return order'!G10 -> 144.5 | I169: ='return order'!I10 -> Return | J169: ='return order'!K10 -> 45897.218
A170: ='return order'!A11 -> 45876.22 | B170: ='return order'!B11 -> 35 size blue nike | C170: ='return order'!C11 -> Alex | D170: ='return order'!D11 -> rasuwa | E170: ='return order'!E11 -> 9766461241 | F170: 0 | G170: {=XLOOKUP(C170, 'return order'!$C$2:$C$29, 'return order'!$F$2:$F$29, 0)} -> 1350 | H170: ='return order'!G11 -> 30 | I170: ='return order'!I11 -> Return | J170: ='return order'!K11 -> 45878.344
A171: ='return order'!A12 -> 45872.172 | B171: ='return order'!B12 -> Sr smile 43 | C171: ='return order'!C12 -> Resham Tamang | D171: ='return order'!D12 -> Melamchi bazar | E171: ='return order'!E12 -> 9823024947 | F171: 0 | G171: {=XLOOKUP(C171, 'return order'!$C$2:$C$29, 'return order'!$F$2:$F$29, 0)} -> 1350 | H171: ='return order'!G12 -> 187 | I171: ='return order'!I12 -> Return | J171: ='return order'!K12 -> 45877.325
A172: ='return order'!A13 -> 45867.208 | B172: ='return order'!B13 -> Vans full 40 | C172: ='return order'!C13 -> Anish Hamal | D172: ='return order'!D13 -> Pokhara hemja, sundaripuri chowk 1 ma | E172: ='return order'!E13 -> 9762335114 | F172: 0 | G172: {=XLOOKUP(C172, 'return order'!$C$2:$C$29, 'return order'!$F$2:$F$29, 0)} -> 1850 | H172: ='return order'!G13 -> 144.5 | I172: ='return order'!I13 -> Return | J172: ='return order'!K13 -> 45872.475
... A188: ='return order'!A29 -> 45892.233 | B188: ='return order'!B29 -> Red Nike 40 | C188: ='return order'!C29 -> bishwas | D188: ='return order'!D29 -> Chitwan, tandi | E188: ='return order'!E29 -> 9708251241 | F188: 0 | G188: {=XLOOKUP(C188, 'return order'!$C$2:$C$29, 'return order'!$F$2:$F$29, 0)} -> 0 | H188: ='return order'!G29 -> 144.5 | I188: ='return order'!I29 -> Return | J188: ='return order'!K29 -> 45895.334

Sheet balance sheet
B2: Month | C2: Cost price | D2: profit margin | E2: ad cost | F2: net profit | G2: Revenue | H2: Gross Profit | I2: D fee | J2: R fee | K2: Total fee | L2: Delivered Orders | M2: Returned Orders | N2: Total Orders | O2: Delivery Rate | P2: Return Rate | Q2: Active Days | R2: Inactive Days | S2: Most Order Created Date
B3: **January** | C3: =G3-H3 -> 0 | D3: =IFERROR(H3/C3*100, 0) -> 0 | E3: 0 | F3: ='balance sheet'!H3-'balance sheet'!I3-'balance sheet'!E3-'balance sheet'!J3 -> 0 | G3: 0 | H3: 0 | I3: 0 | J3: 0 | K3: 0 | L3: 0 | M3: 0 | N3: 0 | O3: 0 | P3: 0 | Q3: 0 | R3: 31 | S3: N/A
B4: **February** | C4: =G4-H4 -> 0 | D4: =IFERROR(H4/C4*100, 0) -> 0 | E4: 0 | F4: ='balance sheet'!H4-'balance sheet'!I4-'balance sheet'!E4-'balance sheet'!J4 -> 0 | G4: 0 | H4: 0 | I4: 0 | K4: 0 | L4: 0 | M4: 0 | N4: 0 | O4: 0 | P4: 0 | Q4: 0 | R4: 28 | S4: N/A
B5: **March** | C5: =G5-H5 -> 0 | D5: =IFERROR(H5/C5*100, 0) -> 0 | E5: 0 | F5: ='balance sheet'!H5-'balance sheet'!I5-'balance sheet'!E5-'balance sheet'!J5 -> 0 | G5: 0 | H5: 0 | I5: 0 | J5: 0 | K5: 0 | L5: 0 | M5: 0 | N5: 0 | O5: 0 | P5: 0 | Q5: 0 | R5: 31 | S5: N/A
B6: **April** | C6: =G6-H6 -> 20650 | D6: =IFERROR(H6/C6*100, 0) -> 42.615012 | E6: 5156.2 | F6: ='balance sheet'!H6-'balance sheet'!I6-'balance sheet'!E6-'balance sheet'!J6 -> 3503.02 | G6: 29450 | H6: 8800 | I6: 73.63 | J6: 67.15 | K6: 140.78 | L6: 19 | M6: 1 | N6: 20 | O6: 0.95 | P6: 0.05 | Q6: 6 | R6: 24 | S6: 2025-04-30 (7)
B7: **May** | C7: =G7-H7 -> 35100 | D7: =IFERROR(H7/C7*100, 0) -> 26.695157 | E7: 14893.2 | F7: ='balance sheet'!H7-'balance sheet'!I7-'balance sheet'!E7-'balance sheet'!J7 -> -6709.08 | G7: 44470 | H7: 9370 | I7: 940.18 | J7: 245.7 | K7: 1185.88 | L7: 31 | M7: 6 | N7: 37 | O7: 0.8378 | P7: 0.1622 | Q7: 9 | R7: 22 | S7: 2025-05-29 (12)
B8: **June** | C8: =G8-H8 -> 17600 | D8: =IFERROR(H8/C8*100, 0) -> 48.579545 | E8: 3032.4 | F8: ='balance sheet'!H8-'balance sheet'!I8-'balance sheet'!E8-'balance sheet'!J8 -> 4020.17 | G8: 26150 | H8: 8550 | I8: 1348.38 | J8: 149.05 | K8: 1497.43 | L8: 17 | M8: 3 | N8: 20 | O8: 0.85 | P8: 0.15 | Q8: 4 | R8: 26 | S8: 2025-06-03 (11)
B9: **July** | C9: =G9-H9 -> 29000 | D9: =IFERROR(H9/C9*100, 0) -> 47.310345 | E9: 12684 | F9: ='balance sheet'!H9-'balance sheet'!I9-'balance sheet'!E9-'balance sheet'!J9 -> -4434.37 | G9: 42720 | H9: 13720 | I9: 4628.87 | J9: 841.5 | K9: 5470.37 | L9: 28 | M9: 5 | N9: 33 | O9: 0.8485 | P9: 0.1515 | Q9: 9 | R9: 22 | S9: 2025-07-19 (6)
B10: **August** | C10: =G10-H10 -> 29450 | D10: =IFERROR(H10/C10*100, 0) -> 46.519525 | E10: 6903.4 | F10: ='balance sheet'!H10-'balance sheet'!I10-'balance sheet'!E10-'balance sheet'!J10 -> 532.13 | G10: 43150 | H10: 13700 | I10: 4342.97 | J10: 1921.5 | K10: 6264.47 | L10: 26 | M10: 13 | N10: 39 | O10: 0.6667 | P10: 0.3333 | Q10: 12 | R10: 19 | S10: 2025-08-24 (5)
B11: **September** | C11: =G11-H11 -> 3100 | D11: =IFERROR(H11/C11*100, 0) -> 25.806452 | E11: 270.2 | F11: ='balance sheet'!H11-'balance sheet'!I11-'balance sheet'!E11-'balance sheet'!J11 -> 152.04 | G11: 3900 | H11: 800 | I11: 377.76 | J11: 0 | K11: 377.76 | L11: 2 | M11: 0 | N11: 2 | O11: 1 | P11: 0 | Q11: 1 | R11: 29 | S11: 2025-09-16 (2)
B12: **October** | C12: =G12-H12 -> 0 | D12: =IFERROR(H12/C12*100, 0) -> 0 | E12: 0 | F12: ='balance sheet'!H12-'balance sheet'!I12-'balance sheet'!E12-'balance sheet'!J12 -> 0 | G12: 0 | H12: 0 | I12: 0 | J12: 0 | K12: 0 | L12: 0 | M12: 0 | N12: 0 | O12: 0 | P12: 0 | Q12: 0 | R12: 31 | S12: N/A
B13: **November** | C13: =G13-H13 -> 0 | D13: =IFERROR(H13/C13*100, 0) -> 0 | E13: 0 | F13: ='balance sheet'!H13-'balance sheet'!I13-'balance sheet'!E13-'balance sheet'!J13 -> 0 | G13: 0 | H13: 0 | I13: 0 | J13: 0 | K13: 0 | L13: 0 | M13: 0 | N13: 0 | O13: 0 | P13: 0 | Q13: 0 | R13: 30 | S13: N/A
B14: **December** | C14: =G14-H14 -> 0 | D14: =IFERROR(H14/C14*100, 0) -> 0 | E14: 0 | F14: ='balance sheet'!H14-'balance sheet'!I14-'balance sheet'!E14-'balance sheet'!J14 -> 0 | G14: 0 | H14: 0 | I14: 0 | J14: 0 | K14: 0 | L14: 0 | M14: 0 | N14: 0 | O14: 0 | P14: 0 | Q14: 0 | R14: 31 | S14: N/A
B15: **Total** | C15: =sum(C6:C11) -> 134900 | D15: =AVERAGE(D6:D11) -> 39.587673 | E15: 42939.4 | F15: =SUM(F3:F14) -> -2936.09 | G15: **189,840** | H15: **54,940** | I15: **11,711.79** | J15: **3,224.90** | K15: **14,936.69** | L15: **123** | M15: **28** | N15: **151** | O15: **81.46%** | P15: **18.54%** | Q15: **41** | R15: **324** | S15: **-**

Sheet checklist1
A1: =IFERROR(__xludf.DUMMYFUNCTION("QUERY(reference!A1:J188, ""where I = 'Delivered'"", 1)"),"Order created at") -> Order created at | B1: =IFERROR(__xludf.DUMMYFUNCTION("""COMPUTED_VALUE"""),"Order description") -> Order description | C1: =IFERROR(__xludf.DUMMYFUNCTION("""COMPUTED_VALUE"""),"Recipient name") -> Recipient name | D1: =IFERROR(__xludf.DUMMYFUNCTION("""COMPUTED_VALUE"""),"Recipient address") -> Recipient address | E1: =IFERROR(__xludf.DUMMYFUNCTION("""COMPUTED_VALUE"""),"Recipient phone") -> Recipient phone | F1: =IFERROR(__xludf.DUMMYFUNCTION("""COMPUTED_VALUE"""),"proft") -> proft | G1: =IFERROR(__xludf.DUMMYFUNCTION("""COMPUTED_VALUE"""),"Collected amount") -> Collected amount | H1: =IFERROR(__xludf.DUMMYFUNCTION("""COMPUTED_VALUE"""),"Total fee") -> Total fee | I1: =IFERROR(__xludf.DUMMYFUNCTION("""COMPUTED_VALUE"""),"Order status") -> Order status | J1: =IFERROR(__xludf.DUMMYFUNCTION("""COMPUTED_VALUE"""),"Order status") -> Order status
A2: =IFERROR(__xludf.DUMMYFUNCTION("""COMPUTED_VALUE"""),45916.191412037035) -> 45916.191 | B2: =IFERROR(__xludf.DUMMYFUNCTION("""COMPUTED_VALUE"""),"Martin 2 sole half ") -> Martin 2 sole half | C2: =IFERROR(__xludf.DUMMYFUNCTION("""COMPUTED_VALUE"""),"Amit Magar") -> Amit Magar | D2: =IFERROR(__xludf.DUMMYFUNCTION("""COMPUTED_VALUE"""),"Dharan, bhanu chowk ") -> Dharan, bhanu chowk | E2: =IFERROR(__xludf.DUMMYFUNCTION("""COMPUTED_VALUE"""),9.84940118E9) -> 9849401180 | F2: =IFERROR(__xludf.DUMMYFUNCTION("""COMPUTED_VALUE"""),350.0) -> 350 | G2: =IFERROR(__xludf.DUMMYFUNCTION("""COMPUTED_VALUE"""),1350.0) -> 1350 | H2: =IFERROR(__xludf.DUMMYFUNCTION("""COMPUTED_VALUE"""),162.38) -> 162.38 | I2: =IFERROR(__xludf.DUMMYFUNCTION("""COMPUTED_VALUE"""),"Delivered") -> Delivered | J2: =IFERROR(__xludf.DUMMYFUNCTION("""COMPUTED_VALUE"""),45918.31509259259) -> 45918.315
A3: =IFERROR(__xludf.DUMMYFUNCTION("""COMPUTED_VALUE"""),45916.18975694444) -> 45916.19 | B3: =IFERROR(__xludf.DUMMYFUNCTION("""COMPUTED_VALUE"""),"N and red 37 and 40") -> N and red 37 and 40 | C3: =IFERROR(__xludf.DUMMYFUNCTION("""COMPUTED_VALUE"""),"Prabin karki") -> Prabin karki | D3: =IFERROR(__xludf.DUMMYFUNCTION("""COMPUTED_VALUE"""),"Solukhumbu tingla") -> Solukhumbu tingla | E3: =IFERROR(__xludf.DUMMYFUNCTION("""COMPUTED_VALUE"""),9.749215487E9) -> 9749215487 | F3: =IFERROR(__xludf.DUMMYFUNCTION("""COMPUTED_VALUE"""),450.0) -> 450 | G3: =IFERROR(__xludf.DUMMYFUNCTION("""COMPUTED_VALUE"""),2550.0) -> 2550 | H3: =IFERROR(__xludf.DUMMYFUNCTION("""COMPUTED_VALUE"""),215.38) -> 215.38 | I3: =IFERROR(__xludf.DUMMYFUNCTION("""COMPUTED_VALUE"""),"Delivered") -> Delivered | J3: =IFERROR(__xludf.DUMMYFUNCTION("""COMPUTED_VALUE"""),45919.61679398148) -> 45919.617
A4: =IFERROR(__xludf.DUMMYFUNCTION("""COMPUTED_VALUE"""),45894.19651620371) -> 45894.197 | B4: =IFERROR(__xludf.DUMMYFUNCTION("""COMPUTED_VALUE"""),"Martin 1 sole 36") -> Martin 1 sole 36 | C4: =IFERROR(__xludf.DUMMYFUNCTION("""COMPUTED_VALUE"""),"Manoj") -> Manoj | D4: =IFERROR(__xludf.DUMMYFUNCTION("""COMPUTED_VALUE"""),"Sundarijal, ktm dobato chowk") -> Sundarijal, ktm dobato chowk | E4: =IFERROR(__xludf.DUMMYFUNCTION("""COMPUTED_VALUE"""),9.768966994E9) -> 9768966994 | F4: =IFERROR(__xludf.DUMMYFUNCTION("""COMPUTED_VALUE"""),300.0) -> 300 | G4: =IFERROR(__xludf.DUMMYFUNCTION("""COMPUTED_VALUE"""),1100.0) -> 1100 | H4: =IFERROR(__xludf.DUMMYFUNCTION("""COMPUTED_VALUE"""),101.75) -> 101.75 | I4: =IFERROR(__xludf.DUMMYFUNCTION("""COMPUTED_VALUE"""),"Delivered") -> Delivered | J4: =IFERROR(__xludf.DUMMYFUNCTION("""COMPUTED_VALUE"""),45894.44189814814) -> 45894.442
A5: =IFERROR(__xludf.DUMMYFUNCTION("""COMPUTED_VALUE"""),45893.18133101852) -> 45893.181 | B5: =IFERROR(__xludf.DUMMYFUNCTION("""COMPUTED_VALUE"""),"Martin 3 sole 41") -> Martin 3 sole 41 | C5: =IFERROR(__xludf.DUMMYFUNCTION("""COMPUTED_VALUE"""),"Manish Bishwokarma") -> Manish Bishwokarma | D5: =IFERROR(__xludf.DUMMYFUNCTION("""COMPUTED_VALUE"""),"Tanahun, dulegauda ") -> Tanahun, dulegauda | E5: =IFERROR(__xludf.DUMMYFUNCTION("""COMPUTED_VALUE"""),9.815193182E9) -> 9815193182 | F5: =IFERROR(__xludf.DUMMYFUNCTION("""COMPUTED_VALUE"""),650.0) -> 650 | G5: =IFERROR(__xludf.DUMMYFUNCTION("""COMPUTED_VALUE"""),1650.0) -> 1650 | H5: =IFERROR(__xludf.DUMMYFUNCTION("""COMPUTED_VALUE"""),183.13) -> 183.13 | I5: =IFERROR(__xludf.DUMMYFUNCTION("""COMPUTED_VALUE"""),"Delivered") -> Delivered | J5: =IFERROR(__xludf.DUMMYFUNCTION("""COMPUTED_VALUE"""),45894.3146412037) -> 45894.315
A6: =IFERROR(__xludf.DUMMYFUNCTION("""COMPUTED_VALUE"""),45893.17900462963) -> 45893.179 | B6: =IFERROR(__xludf.DUMMYFUNCTION("""COMPUTED_VALUE"""),"Blue Nike 39") -> Blue Nike 39 | C6: =IFERROR(__xludf.DUMMYFUNCTION("""COMPUTED_VALUE"""),"Rajdip Chudal") -> Rajdip Chudal | D6: =IFERROR(__xludf.DUMMYFUNCTION("""COMPUTED_VALUE"""),"Haldibari 4, magalbare jhapa") -> Haldibari 4, magalbare jhapa | E6: =IFERROR(__xludf.DUMMYFUNCTION("""COMPUTED_VALUE"""),9.815936372E9) -> 9815936372 | F6: =IFERROR(__xludf.DUMMYFUNCTION("""COMPUTED_VALUE"""),350.0) -> 350 | G6: =IFERROR(__xludf.DUMMYFUNCTION("""COMPUTED_VALUE"""),1350.0) -> 1350 | H6: =IFERROR(__xludf.DUMMYFUNCTION("""COMPUTED_VALUE"""),182.38) -> 182.38 | I6: =IFERROR(__xludf.DUMMYFUNCTION("""COMPUTED_VALUE"""),"Delivered") -> Delivered | J6: =IFERROR(__xludf.DUMMYFUNCTION("""COMPUTED_VALUE"""),45895.44592592593) -> 45895.446
A7: =IFERROR(__xludf.DUMMYFUNCTION("""COMPUTED_VALUE"""),45893.178032407406) -> 45893.178 | B7: =IFERROR(__xludf.DUMMYFUNCTION("""COMPUTED_VALUE"""),"Martin 3 sole size 39 39 38") -> Martin 3 sole size 39 39 38 | C7: =IFERROR(__xludf.DUMMYFUNCTION("""COMPUTED_VALUE"""),"Laxmi Rai") -> Laxmi Rai | D7: =IFERROR(__xludf.DUMMYFUNCTION("""COMPUTED_VALUE""")," Shree antu, baral bhanjyang") -> Shree antu, baral bhanjyang | E7: =IFERROR(__xludf.DUMMYFUNCTION("""COMPUTED_VALUE"""),9.769723304E9) -> 9769723304 | F7: =IFERROR(__xludf.DUMMYFUNCTION("""COMPUTED_VALUE"""),1300.0) -> 1300 | G7: =IFERROR(__xludf.DUMMYFUNCTION("""COMPUTED_VALUE"""),4650.0) -> 4650 | H7: =IFERROR(__xludf.DUMMYFUNCTION("""COMPUTED_VALUE"""),220.63) -> 220.63 | I7: =IFERROR(__xludf.DUMMYFUNCTION("""COMPUTED_VALUE"""),"Delivered") -> Delivered | J7: =IFERROR(__xludf.DUMMYFUNCTION("""COMPUTED_VALUE"""),45898.376655092594) -> 45898.377
A8: =IFERROR(__xludf.DUMMYFUNCTION("""COMPUTED_VALUE"""),45892.28570601852) -> 45892.286 | B8: =IFERROR(__xludf.DUMMYFUNCTION("""COMPUTED_VALUE"""),"Nike 11 red and Martin 2 sole 42 and 43") -> Nike 11 red and Martin 2 sole 42 and 43 | C8: =IFERROR(__xludf.DUMMYFUNCTION("""COMPUTED_VALUE"""),"Dipak Shah") -> Dipak Shah | D8: =IFERROR(__xludf.DUMMYFUNCTION("""COMPUTED_VALUE"""),"Tinkune, the new summit college") -> Tinkune, the new summit college | E8: =IFERROR(__xludf.DUMMYFUNCTION("""COMPUTED_VALUE"""),9.826881955E9) -> 9826881955 | F8: =IFERROR(__xludf.DUMMYFUNCTION("""COMPUTED_VALUE"""),800.0) -> 800 | G8: =IFERROR(__xludf.DUMMYFUNCTION("""COMPUTED_VALUE"""),2600.0) -> 2600 | H8: =IFERROR(__xludf.DUMMYFUNCTION("""COMPUTED_VALUE"""),105.5) -> 105.5 | I8: =IFERROR(__xludf.DUMMYFUNCTION("""COMPUTED_VALUE"""),"Delivered") -> Delivered | J8: =IFERROR(__xludf.DUMMYFUNCTION("""COMPUTED_VALUE"""),45893.2530324074) -> 45893.253
A9: =IFERROR(__xludf.DUMMYFUNCTION("""COMPUTED_VALUE"""),45892.228217592594) -> 45892.228 | B9: =IFERROR(__xludf.DUMMYFUNCTION("""COMPUTED_VALUE"""),"Martin 1 sole 43") -> Martin 1 sole 43 | C9: =IFERROR(__xludf.DUMMYFUNCTION("""COMPUTED_VALUE"""),"Chandra Bohara") -> Chandra Bohara | D9: =IFERROR(__xludf.DUMMYFUNCTION("""COMPUTED_VALUE"""),"Dadeldhura, bagbazzar tufandadko check najik police bit") -> Dadeldhura, bagbazzar tufandadko check najik police bit | E9: =IFERROR(__xludf.DUMMYFUNCTION("""COMPUTED_VALUE"""),9.865629618E9) -> 9865629618 | F9: =IFERROR(__xludf.DUMMYFUNCTION("""COMPUTED_VALUE"""),450.0) -> 450 | G9: =IFERROR(__xludf.DUMMYFUNCTION("""COMPUTED_VALUE"""),1350.0) -> 1350 | H9: =IFERROR(__xludf.DUMMYFUNCTION("""COMPUTED_VALUE"""),182.38) -> 182.38 | I9: =IFERROR(__xludf.DUMMYFUNCTION("""COMPUTED_VALUE"""),"Delivered") -> Delivered | J9: =IFERROR(__xludf.DUMMYFUNCTION("""COMPUTED_VALUE"""),45895.355046296296) -> 45895.355
A10: =IFERROR(__xludf.DUMMYFUNCTION("""COMPUTED_VALUE"""),45892.22659722222) -> 45892.227 | B10: =IFERROR(__xludf.DUMMYFUNCTION("""COMPUTED_VALUE"""),"Martin 2 sole 40") -> Martin 2 sole 40 | C10: =IFERROR(__xludf.DUMMYFUNCTION("""COMPUTED_VALUE"""),"Prabin Karki") -> Prabin Karki | D10: =IFERROR(__xludf.DUMMYFUNCTION("""COMPUTED_VALUE"""),"Solukhumbu, tingla") -> Solukhumbu, tingla | E10: =IFERROR(__xludf.DUMMYFUNCTION("""COMPUTED_VALUE"""),9.749215487E9) -> 9749215487 | F10: =IFERROR(__xludf.DUMMYFUNCTION("""COMPUTED_VALUE"""),550.0) -> 550 | G10: =IFERROR(__xludf.DUMMYFUNCTION("""COMPUTED_VALUE"""),1550.0) -> 1550 | H10: =IFERROR(__xludf.DUMMYFUNCTION("""COMPUTED_VALUE"""),212.88) -> 212.88 | I10: =IFERROR(__xludf.DUMMYFUNCTION("""COMPUTED_VALUE"""),"Delivered") -> Delivered | J10: =IFERROR(__xludf.DUMMYFUNCTION("""COMPUTED_VALUE"""),45898.67103009259) -> 45898.671
A11: =IFERROR(__xludf.DUMMYFUNCTION("""COMPUTED_VALUE"""),45891.18746527778) -> 45891.187 | B11: =IFERROR(__xludf.DUMMYFUNCTION("""COMPUTED_VALUE"""),"Blue Nike size 42") -> Blue Nike size 42 | C11: =IFERROR(__xludf.DUMMYFUNCTION("""COMPUTED_VALUE"""),"Biraj Tamang") -> Biraj Tamang | D11: =IFERROR(__xludf.DUMMYFUNCTION("""COMPUTED_VALUE"""),"Jhapa, budhabare or buddhashanti ") -> Jhapa, budhabare or buddhashanti | E11: =IFERROR(__xludf.DUMMYFUNCTION("""COMPUTED_VALUE"""),9.702839214E9) -> 9702839214 | F11: =IFERROR(__xludf.DUMMYFUNCTION("""COMPUTED_VALUE"""),350.0) -> 350 | G11: =IFERROR(__xludf.DUMMYFUNCTION("""COMPUTED_VALUE"""),1350.0) -> 1350 | H11: =IFERROR(__xludf.DUMMYFUNCTION("""COMPUTED_VALUE"""),182.38) -> 182.38 | I11: =IFERROR(__xludf.DUMMYFUNCTION("""COMPUTED_VALUE"""),"Delivered") -> Delivered | J11: =IFERROR(__xludf.DUMMYFUNCTION("""COMPUTED_VALUE"""),45894.39797453704) -> 45894.398
A12: =IFERROR(__xludf.DUMMYFUNCTION("""COMPUTED_VALUE"""),45891.18523148148) -> 45891.185 | B12: =IFERROR(__xludf.DUMMYFUNCTION("""COMPUTED_VALUE"""),"Red Nike 40") -> Red Nike 40 | C12: =IFERROR(__xludf.DUMMYFUNCTION("""COMPUTED_VALUE"""),"Sujan Jagebu Limbu") -> Sujan Jagebu Limbu | D12: =IFERROR(__xludf.DUMMYFUNCTION("""COMPUTED_VALUE"""),"Jhapa, birtamod karat chowk Road no 1") -> Jhapa, birtamod karat chowk Road no 1 | E12: =IFERROR(__xludf.DUMMYFUNCTION("""COMPUTED_VALUE"""),9.700427269E9) -> 9700427269 | F12: =IFERROR(__xludf.DUMMYFUNCTION("""COMPUTED_VALUE"""),450.0) -> 450 | G12: =IFERROR(__xludf.DUMMYFUNCTION("""COMPUTED_VALUE"""),1350.0) -> 1350 | H12: =IFERROR(__xludf.DUMMYFUNCTION("""COMPUTED_VALUE"""),182.38) -> 182.38 | I12: =IFERROR(__xludf.DUMMYFUNCTION("""COMPUTED_VALUE"""),"Delivered") -> Delivered | J12: =IFERROR(__xludf.DUMMYFUNCTION("""COMPUTED_VALUE"""),45893.449965277774) -> 45893.45
A13: =IFERROR(__xludf.DUMMYFUNCTION("""COMPUTED_VALUE"""),45890.17833333333) -> 45890.178 | B13: =IFERROR(__xludf.DUMMYFUNCTION("""COMPUTED_VALUE"""),"Casual Adidas shoes 41") -> Casual Adidas shoes 41 | C13: =IFERROR(__xludf.DUMMYFUNCTION("""COMPUTED_VALUE"""),"Asmirt Tamang") -> Asmirt Tamang | D13: =IFERROR(__xludf.DUMMYFUNCTION("""COMPUTED_VALUE"""),"Pokhara") -> Pokhara | E13: =IFERROR(__xludf.DUMMYFUNCTION("""COMPUTED_VALUE"""),9.703252518E9) -> 9703252518 | F13: =IFERROR(__xludf.DUMMYFUNCTION("""COMPUTED_VALUE"""),450.0) -> 450 | G13: =IFERROR(__xludf.DUMMYFUNCTION("""COMPUTED_VALUE"""),1450.0) -> 1450 | H13: =IFERROR(__xludf.DUMMYFUNCTION("""COMPUTED_VALUE"""),162.63) -> 162.63 | I13: =IFERROR(__xludf.DUMMYFUNCTION("""COMPUTED_VALUE"""),"Delivered") -> Delivered | J13: =IFERROR(__xludf.DUMMYFUNCTION("""COMPUTED_VALUE"""),45893.31458333333) -> 45893.315
A14: =IFERROR(__xludf.DUMMYFUNCTION("""COMPUTED_VALUE"""),45890.17673611111) -> 45890.177 | B14: =IFERROR(__xludf.DUMMYFUNCTION("""COMPUTED_VALUE"""),"Martin 2 sole 39 nayabasti") -> Martin 2 sole 39 nayabasti | C14: =IFERROR(__xludf.DUMMYFUNCTION("""COMPUTED_VALUE"""),"Anil Khadgi") -> Anil Khadgi | D14: =IFERROR(__xludf.DUMMYFUNCTION("""COMPUTED_VALUE"""),"Sitapaila mathi ramkot") -> Sitapaila mathi ramkot | E14: =IFERROR(__xludf.DUMMYFUNCTION("""COMPUTED_VALUE"""),9.803874775E9) -> 9803874775 | F14: =IFERROR(__xludf.DUMMYFUNCTION("""COMPUTED_VALUE"""),500.0) -> 500 | G14: =IFERROR(__xludf.DUMMYFUNCTION("""COMPUTED_VALUE"""),1500.0) -> 1500 | H14: =IFERROR(__xludf.DUMMYFUNCTION("""COMPUTED_VALUE"""),102.75) -> 102.75 | I14: =IFERROR(__xludf.DUMMYFUNCTION("""COMPUTED_VALUE"""),"Delivered") -> Delivered | J14: =IFERROR(__xludf.DUMMYFUNCTION("""COMPUTED_VALUE"""),45890.50582175926) -> 45890.506
A15: =IFERROR(__xludf.DUMMYFUNCTION("""COMPUTED_VALUE"""),45890.17537037037) -> 45890.175 | B15: =IFERROR(__xludf.DUMMYFUNCTION("""COMPUTED_VALUE"""),"Martin 3 sole size 43") -> Martin 3 sole size 43 | C15: =IFERROR(__xludf.DUMMYFUNCTION("""COMPUTED_VALUE"""),"Bikash") -> Bikash | D15: =IFERROR(__xludf.DUMMYFUNCTION("""COMPUTED_VALUE"""),"Rolpa, ghartghau") -> Rolpa, ghartghau | E15: =IFERROR(__xludf.DUMMYFUNCTION("""COMPUTED_VALUE"""),9.765840359E9) -> 9765840359 | F15: =IFERROR(__xludf.DUMMYFUNCTION("""COMPUTED_VALUE"""),650.0) -> 650 | G15: =IFERROR(__xludf.DUMMYFUNCTION("""COMPUTED_VALUE"""),1650.0) -> 1650 | H15: =IFERROR(__xludf.DUMMYFUNCTION("""COMPUTED_VALUE"""),213.13) -> 213.13 | I15: =IFERROR(__xludf.DUMMYFUNCTION("""COMPUTED_VALUE"""),"Delivered") -> Delivered | J15: =IFERROR(__xludf.DUMMYFUNCTION("""COMPUTED_VALUE"""),45895.638506944444) -> 45895.639
A16: =IFERROR(__xludf.DUMMYFUNCTION("""COMPUTED_VALUE"""),45889.17605324074) -> 45889.176 | B16: =IFERROR(__xludf.DUMMYFUNCTION("""COMPUTED_VALUE"""),"Chelsea size 43") -> Chelsea size 43 | C16: =IFERROR(__xludf.DUMMYFUNCTION("""COMPUTED_VALUE"""),"Dipendra Chaudhari") -> Dipendra Chaudhari | D16: =IFERROR(__xludf.DUMMYFUNCTION("""COMPUTED_VALUE"""),"Chitwan, madi") -> Chitwan, madi | E16: =IFERROR(__xludf.DUMMYFUNCTION("""COMPUTED_VALUE"""),9.807289391E9) -> 9807289391 | F16: =IFERROR(__xludf.DUMMYFUNCTION("""COMPUTED_VALUE"""),450.0) -> 450 | G16: =IFERROR(__xludf.DUMMYFUNCTION("""COMPUTED_VALUE"""),1450.0) -> 1450 | H16: =IFERROR(__xludf.DUMMYFUNCTION("""COMPUTED_VALUE"""),162.63) -> 162.63 | I16: =IFERROR(__xludf.DUMMYFUNCTION("""COMPUTED_VALUE"""),"Delivered") -> Delivered | J16: =IFERROR(__xludf.DUMMYFUNCTION("""COMPUTED_VALUE"""),45891.61177083333) -> 45891.612
A17: =IFERROR(__xludf.DUMMYFUNCTION("""COMPUTED_VALUE"""),45889.1749074074) -> 45889.175 | B17: =IFERROR(__xludf.DUMMYFUNCTION("""COMPUTED_VALUE"""),"Martin 3 sole size 41") -> Martin 3 sole size 41 | C17: =IFERROR(__xludf.DUMMYFUNCTION("""COMPUTED_VALUE"""),"Ninam Rai") -> Ninam Rai | D17: =IFERROR(__xludf.DUMMYFUNCTION("""COMPUTED_VALUE"""),"Taplejung") -> Taplejung | E17: =IFERROR(__xludf.DUMMYFUNCTION("""COMPUTED_VALUE"""),9.767381711E9) -> 9767381711 | F17: =IFERROR(__xludf.DUMMYFUNCTION("""COMPUTED_VALUE"""),550.0) -> 550 | G17: =IFERROR(__xludf.DUMMYFUNCTION("""COMPUTED_VALUE"""),1550.0) -> 1550 | H17: =IFERROR(__xludf.DUMMYFUNCTION("""COMPUTED_VALUE"""),212.88) -> 212.88 | I17: =IFERROR(__xludf.DUMMYFUNCTION("""COMPUTED_VALUE"""),"Delivered") -> Delivered | J17: =IFERROR(__xludf.DUMMYFUNCTION("""COMPUTED_VALUE"""),45895.23165509259) -> 45895.232
A18: =IFERROR(__xludf.DUMMYFUNCTION("""COMPUTED_VALUE"""),45889.17271990741) -> 45889.173 | B18: =IFERROR(__xludf.DUMMYFUNCTION("""COMPUTED_VALUE"""),"Converse black size 40") -> Converse black size 40 | C18: =IFERROR(__xludf.DUMMYFUNCTION("""COMPUTED_VALUE"""),"Ajeet Khadka") -> Ajeet Khadka | D18: =IFERROR(__xludf.DUMMYFUNCTION("""COMPUTED_VALUE"""),"Bhaktapur, bageswari changunarayan nabarpalika wada no 7") -> Bhaktapur, bageswari changunarayan nabarpalika wada no 7 | E18: =IFERROR(__xludf.DUMMYFUNCTION("""COMPUTED_VALUE"""),9.860944595E9) -> 9860944595 | F18: =IFERROR(__xludf.DUMMYFUNCTION("""COMPUTED_VALUE"""),500.0) -> 500 | G18: =IFERROR(__xludf.DUMMYFUNCTION("""COMPUTED_VALUE"""),1300.0) -> 1300 | H18: =IFERROR(__xludf.DUMMYFUNCTION("""COMPUTED_VALUE"""),182.25) -> 182.25 | I18: =IFERROR(__xludf.DUMMYFUNCTION("""COMPUTED_VALUE"""),"Delivered") -> Delivered | J18: =IFERROR(__xludf.DUMMYFUNCTION("""COMPUTED_VALUE"""),45890.36565972222) -> 45890.366
A19: =IFERROR(__xludf.DUMMYFUNCTION("""COMPUTED_VALUE"""),45888.17891203704) -> 45888.179 | B19: =IFERROR(__xludf.DUMMYFUNCTION("""COMPUTED_VALUE"""),"Martin single 41 and 42") -> Martin single 41 and 42 | C19: =IFERROR(__xludf.DUMMYFUNCTION("""COMPUTED_VALUE"""),"Sitaram Pun") -> Sitaram Pun | D19: =IFERROR(__xludf.DUMMYFUNCTION("""COMPUTED_VALUE"""),"Pyuthan, sari") -> Pyuthan, sari | E19: =IFERROR(__xludf.DUMMYFUNCTION("""COMPUTED_VALUE"""),9.762095448E9) -> 9762095448 | F19: =IFERROR(__xludf.DUMMYFUNCTION("""COMPUTED_VALUE"""),550.0) -> 550 | G19: =IFERROR(__xludf.DUMMYFUNCTION("""COMPUTED_VALUE"""),2550.0) -> 2550 | H19: =IFERROR(__xludf.DUMMYFUNCTION("""COMPUTED_VALUE"""),185.38) -> 185.38 | I19: =IFERROR(__xludf.DUMMYFUNCTION("""COMPUTED_VALUE"""),"Delivered") -> Delivered | J19: =IFERROR(__xludf.DUMMYFUNCTION("""COMPUTED_VALUE"""),45893.495370370365) -> 45893.495
A20: =IFERROR(__xludf.DUMMYFUNCTION("""COMPUTED_VALUE"""),45888.17722222222) -> 45888.177 | B20: =IFERROR(__xludf.DUMMYFUNCTION("""COMPUTED_VALUE"""),"Martin 3 sole size 39") -> Martin 3 sole size 39 | C20: =IFERROR(__xludf.DUMMYFUNCTION("""COMPUTED_VALUE"""),"Bali Rawat") -> Bali Rawat | D20: =IFERROR(__xludf.DUMMYFUNCTION("""COMPUTED_VALUE"""),"Nepalgunj, muktpur 12, haltpost najik") -> Nepalgunj, muktpur 12, haltpost najik | E20: =IFERROR(__xludf.DUMMYFUNCTION("""COMPUTED_VALUE"""),9.745506225E9) -> 9745506225 | F20: =IFERROR(__xludf.DUMMYFUNCTION("""COMPUTED_VALUE"""),600.0) -> 600 | G20: =IFERROR(__xludf.DUMMYFUNCTION("""COMPUTED_VALUE"""),1600.0) -> 1600 | H20: =IFERROR(__xludf.DUMMYFUNCTION("""COMPUTED_VALUE"""),213.0) -> 213 | I20: =IFERROR(__xludf.DUMMYFUNCTION("""COMPUTED_VALUE"""),"Delivered") -> Delivered | J20: =IFERROR(__xludf.DUMMYFUNCTION("""COMPUTED_VALUE"""),45889.45898148148) -> 45889.459
A21: =IFERROR(__xludf.DUMMYFUNCTION("""COMPUTED_VALUE"""),45888.17445601852) -> 45888.174 | B21: =IFERROR(__xludf.DUMMYFUNCTION("""COMPUTED_VALUE"""),"Martin single 42") -> Martin single 42 | C21: =IFERROR(__xludf.DUMMYFUNCTION("""COMPUTED_VALUE"""),"Shree krishna") -> Shree krishna | D21: =IFERROR(__xludf.DUMMYFUNCTION("""COMPUTED_VALUE"""),"Ghalate, bhaktapur") -> Ghalate, bhaktapur | E21: =IFERROR(__xludf.DUMMYFUNCTION("""COMPUTED_VALUE"""),9.765007077E9) -> 9765007077 | F21: =IFERROR(__xludf.DUMMYFUNCTION("""COMPUTED_VALUE"""),400.0) -> 400 | G21: =IFERROR(__xludf.DUMMYFUNCTION("""COMPUTED_VALUE"""),1300.0) -> 1300 | H21: =IFERROR(__xludf.DUMMYFUNCTION("""COMPUTED_VALUE"""),102.25) -> 102.25 | I21: =IFERROR(__xludf.DUMMYFUNCTION("""COMPUTED_VALUE"""),"Delivered") -> Delivered | J21: =IFERROR(__xludf.DUMMYFUNCTION("""COMPUTED_VALUE"""),45889.2105787037) -> 45889.211
A22: =IFERROR(__xludf.DUMMYFUNCTION("""COMPUTED_VALUE"""),45887.16681712963) -> 45887.167 | B22: =IFERROR(__xludf.DUMMYFUNCTION("""COMPUTED_VALUE"""),"Martin triple sole size 40") -> Martin triple sole size 40 | C22: =IFERROR(__xludf.DUMMYFUNCTION("""COMPUTED_VALUE"""),"Aashish Gautam") -> Aashish Gautam | D22: =IFERROR(__xludf.DUMMYFUNCTION("""COMPUTED_VALUE"""),"Baitadi, patan, metallic municipality 7, kanda bazzar") -> Baitadi, patan, metallic municipality 7, kanda bazzar | E22: =IFERROR(__xludf.DUMMYFUNCTION("""COMPUTED_VALUE"""),9.768483761E9) -> 9768483761 | F22: =IFERROR(__xludf.DUMMYFUNCTION("""COMPUTED_VALUE"""),650.0) -> 650 | G22: =IFERROR(__xludf.DUMMYFUNCTION("""COMPUTED_VALUE"""),1650.0) -> 1650 | H22: =IFERROR(__xludf.DUMMYFUNCTION("""COMPUTED_VALUE"""),143.13) -> 143.13 | I22: =IFERROR(__xludf.DUMMYFUNCTION("""COMPUTED_VALUE"""),"Delivered") -> Delivered | J22: =IFERROR(__xludf.DUMMYFUNCTION("""COMPUTED_VALUE"""),45891.40899305556) -> 45891.409
A23: =IFERROR(__xludf.DUMMYFUNCTION("""COMPUTED_VALUE"""),45887.16091435185) -> 45887.161 | B23: =IFERROR(__xludf.DUMMYFUNCTION("""COMPUTED_VALUE"""),"Martin 3 sole size 40") -> Martin 3 sole size 40 | C23: =IFERROR(__xludf.DUMMYFUNCTION("""COMPUTED_VALUE"""),"Prince Shrestha") -> Prince Shrestha | D23: =IFERROR(__xludf.DUMMYFUNCTION("""COMPUTED_VALUE"""),"Beni bazzar ") -> Beni bazzar | E23: =IFERROR(__xludf.DUMMYFUNCTION("""COMPUTED_VALUE"""),9.765610848E9) -> 9765610848 | F23: =IFERROR(__xludf.DUMMYFUNCTION("""COMPUTED_VALUE"""),650.0) -> 650 | G23: =IFERROR(__xludf.DUMMYFUNCTION("""COMPUTED_VALUE"""),1650.0) -> 1650 | H23: =IFERROR(__xludf.DUMMYFUNCTION("""COMPUTED_VALUE"""),183.13) -> 183.13 | I23: =IFERROR(__xludf.DUMMYFUNCTION("""COMPUTED_VALUE"""),"Delivered") -> Delivered | J23: =IFERROR(__xludf.DUMMYFUNCTION("""COMPUTED_VALUE"""),45891.24974537037) -> 45891.25
A24: =IFERROR(__xludf.DUMMYFUNCTION("""COMPUTED_VALUE"""),45886.18208333333) -> 45886.182 | B24: =IFERROR(__xludf.DUMMYFUNCTION("""COMPUTED_VALUE"""),"Nike 40 Black white ") -> Nike 40 Black white | C24: =IFERROR(__xludf.DUMMYFUNCTION("""COMPUTED_VALUE"""),"Siddhartha Gautam") -> Siddhartha Gautam | D24: =IFERROR(__xludf.DUMMYFUNCTION("""COMPUTED_VALUE"""),"Kathmandu,Balkot big mart, Brihaspati marga") -> Kathmandu,Balkot big mart, Brihaspati marga | E24: =IFERROR(__xludf.DUMMYFUNCTION("""COMPUTED_VALUE"""),9.862541342E9) -> 9862541342 | F24: =IFERROR(__xludf.DUMMYFUNCTION("""COMPUTED_VALUE"""),300.0) -> 300 | G24: =IFERROR(__xludf.DUMMYFUNCTION("""COMPUTED_VALUE"""),1300.0) -> 1300 | H24: =IFERROR(__xludf.DUMMYFUNCTION("""COMPUTED_VALUE"""),3.25) -> 3.25 | I24: =IFERROR(__xludf.DUMMYFUNCTION("""COMPUTED_VALUE"""),"Delivered") -> Delivered | J24: =IFERROR(__xludf.DUMMYFUNCTION("""COMPUTED_VALUE"""),45886.49072916667) -> 45886.491
A25: =IFERROR(__xludf.DUMMYFUNCTION("""COMPUTED_VALUE"""),45873.199583333335) -> 45873.2 | B25: =IFERROR(__xludf.DUMMYFUNCTION("""COMPUTED_VALUE"""),"Martin naysbasti 3 sole 41") -> Martin naysbasti 3 sole 41 | C25: =IFERROR(__xludf.DUMMYFUNCTION("""COMPUTED_VALUE"""),"Santosh") -> Santosh | D25: =IFERROR(__xludf.DUMMYFUNCTION("""COMPUTED_VALUE"""),"Dang, ghorahi") -> Dang, ghorahi | E25: =IFERROR(__xludf.DUMMYFUNCTION("""COMPUTED_VALUE"""),9.818118588E9) -> 9818118588 | F25: =IFERROR(__xludf.DUMMYFUNCTION("""COMPUTED_VALUE"""),550.0) -> 550 | G25: =IFERROR(__xludf.DUMMYFUNCTION("""COMPUTED_VALUE"""),1550.0) -> 1550 | H25: =IFERROR(__xludf.DUMMYFUNCTION("""COMPUTED_VALUE"""),182.88) -> 182.88 | I25: =IFERROR(__xludf.DUMMYFUNCTION("""COMPUTED_VALUE"""),"Delivered") -> Delivered | J25: =IFERROR(__xludf.DUMMYFUNCTION("""COMPUTED_VALUE"""),45882.43194444444) -> 45882.432
A26: =IFERROR(__xludf.DUMMYFUNCTION("""COMPUTED_VALUE"""),45873.19865740741) -> 45873.199 | B26: =IFERROR(__xludf.DUMMYFUNCTION("""COMPUTED_VALUE"""),"Martin half 2 sole 39") -> Martin half 2 sole 39 | C26: =IFERROR(__xludf.DUMMYFUNCTION("""COMPUTED_VALUE"""),"Sudip Darnal") -> Sudip Darnal | D26: =IFERROR(__xludf.DUMMYFUNCTION("""COMPUTED_VALUE"""),"Sangwale ward 4, sindhuli") -> Sangwale ward 4, sindhuli | E26: =IFERROR(__xludf.DUMMYFUNCTION("""COMPUTED_VALUE"""),9.766529083E9) -> 9766529083 | F26: =IFERROR(__xludf.DUMMYFUNCTION("""COMPUTED_VALUE"""),350.0) -> 350 | G26: =IFERROR(__xludf.DUMMYFUNCTION("""COMPUTED_VALUE"""),1350.0) -> 1350 | H26: =IFERROR(__xludf.DUMMYFUNCTION("""COMPUTED_VALUE"""),162.38) -> 162.38 | I26: =IFERROR(__xludf.DUMMYFUNCTION("""COMPUTED_VALUE"""),"Delivered") -> Delivered | J26: =IFERROR(__xludf.DUMMYFUNCTION("""COMPUTED_VALUE"""),45877.46166666667) -> 45877.462
A27: =IFERROR(__xludf.DUMMYFUNCTION("""COMPUTED_VALUE"""),45872.17322916667) -> 45872.173 | B27: =IFERROR(__xludf.DUMMYFUNCTION("""COMPUTED_VALUE"""),"Sr smile 41") -> Sr smile 41 | C27: =IFERROR(__xludf.DUMMYFUNCTION("""COMPUTED_VALUE"""),"Bibash Thapa") -> Bibash Thapa | D27: =IFERROR(__xludf.DUMMYFUNCTION("""COMPUTED_VALUE"""),"Gulariya 6, bardiya") -> Gulariya 6, bardiya | E27: =IFERROR(__xludf.DUMMYFUNCTION("""COMPUTED_VALUE"""),9.816523777E9) -> 9816523777 | F27: =IFERROR(__xludf.DUMMYFUNCTION("""COMPUTED_VALUE"""),450.0) -> 450 | G27: =IFERROR(__xludf.DUMMYFUNCTION("""COMPUTED_VALUE"""),1450.0) -> 1450 | H27: =IFERROR(__xludf.DUMMYFUNCTION("""COMPUTED_VALUE"""),182.63) -> 182.63 | I27: =IFERROR(__xludf.DUMMYFUNCTION("""COMPUTED_VALUE"""),"Delivered") -> Delivered | J27: =IFERROR(__xludf.DUMMYFUNCTION("""COMPUTED_VALUE"""),45873.35476851852) -> 45873.355
A28: =IFERROR(__xludf.DUMMYFUNCTION("""COMPUTED_VALUE"""),45872.17152777778) -> 45872.172 | B28: =IFERROR(__xludf.DUMMYFUNCTION("""COMPUTED_VALUE"""),"Martin nayabasti factory 40") -> Martin nayabasti factory 40 | C28: =IFERROR(__xludf.DUMMYFUNCTION("""COMPUTED_VALUE"""),"Nischal Tamang") -> Nischal Tamang | D28: =IFERROR(__xludf.DUMMYFUNCTION("""COMPUTED_VALUE"""),"Dingla, bhojpur") -> Dingla, bhojpur | E28: =IFERROR(__xludf.DUMMYFUNCTION("""COMPUTED_VALUE"""),9.820330404E9) -> 9820330404 | F28: =IFERROR(__xludf.DUMMYFUNCTION("""COMPUTED_VALUE"""),550.0) -> 550 | G28: =IFERROR(__xludf.DUMMYFUNCTION("""COMPUTED_VALUE"""),1550.0) -> 1550 | H28: =IFERROR(__xludf.DUMMYFUNCTION("""COMPUTED_VALUE"""),212.88) -> 212.88 | I28: =IFERROR(__xludf.DUMMYFUNCTION("""COMPUTED_VALUE"""),"Delivered") -> Delivered | J28: =IFERROR(__xludf.DUMMYFUNCTION("""COMPUTED_VALUE"""),45875.59798611111) -> 45875.598
A29: =IFERROR(__xludf.DUMMYFUNCTION("""COMPUTED_VALUE"""),45872.17049768519) -> 45872.171 | B29: =IFERROR(__xludf.DUMMYFUNCTION("""COMPUTED_VALUE"""),"Martin single sole 42") -> Martin single sole 42 | C29: =IFERROR(__xludf.DUMMYFUNCTION("""COMPUTED_VALUE"""),"Rohan Bam") -> Rohan Bam | D29: =IFERROR(__xludf.DUMMYFUNCTION("""COMPUTED_VALUE"""),"Bardageriya gaupalika, ward no 2, kumbiya, kailali") -> Bardageriya gaupalika, ward no 2, kumbiya, kailali | E29: =IFERROR(__xludf.DUMMYFUNCTION("""COMPUTED_VALUE"""),9.815663088E9) -> 9815663088 | F29: =IFERROR(__xludf.DUMMYFUNCTION("""COMPUTED_VALUE"""),350.0) -> 350 | G29: =IFERROR(__xludf.DUMMYFUNCTION("""COMPUTED_VALUE"""),1350.0) -> 1350 | H29: =IFERROR(__xludf.DUMMYFUNCTION("""COMPUTED_VALUE"""),182.38) -> 182.38 | I29: =IFERROR(__xludf.DUMMYFUNCTION("""COMPUTED_VALUE"""),"Delivered") -> Delivered | J29: =IFERROR(__xludf.DUMMYFUNCTION("""COMPUTED_VALUE"""),45877.282442129625) -> 45877.282
A30: =IFERROR(__xludf.DUMMYFUNCTION("""COMPUTED_VALUE"""),45869.2041087963) -> 45869.204 | B30: =IFERROR(__xludf.DUMMYFUNCTION("""COMPUTED_VALUE"""),"Martin single sole 41") -> Martin single sole 41 | C30: =IFERROR(__xludf.DUMMYFUNCTION("""COMPUTED_VALUE"""),"Santosh Pariyar") -> Santosh Pariyar | D30: =IFERROR(__xludf.DUMMYFUNCTION("""COMPUTED_VALUE"""),"Gogli chowk, dang") -> Gogli chowk, dang | E30: =IFERROR(__xludf.DUMMYFUNCTION("""COMPUTED_VALUE"""),9.706877325E9) -> 9706877325 | F30: =IFERROR(__xludf.DUMMYFUNCTION("""COMPUTED_VALUE"""),350.0) -> 350 | G30: =IFERROR(__xludf.DUMMYFUNCTION("""COMPUTED_VALUE"""),1350.0) -> 1350 | H30: =IFERROR(__xludf.DUMMYFUNCTION("""COMPUTED_VALUE"""),182.38) -> 182.38 | I30: =IFERROR(__xludf.DUMMYFUNCTION("""COMPUTED_VALUE"""),"Delivered") -> Delivered | J30: =IFERROR(__xludf.DUMMYFUNCTION("""COMPUTED_VALUE"""),45872.361342592594) -> 45872.361
A31: =IFERROR(__xludf.DUMMYFUNCTION("""COMPUTED_VALUE"""),45869.20298611111) -> 45869.203 | B31: =IFERROR(__xludf.DUMMYFUNCTION("""COMPUTED_VALUE"""),"Sr gray 42") -> Sr gray 42 | C31: =IFERROR(__xludf.DUMMYFUNCTION("""COMPUTED_VALUE"""),"Subarth Kunwar") -> Subarth Kunwar | D31: =IFERROR(__xludf.DUMMYFUNCTION("""COMPUTED_VALUE"""),"Baneshwor soa and swimming pool or ananda events and meeting") -> Baneshwor soa and swimming pool or ananda events and meeting | E31: =IFERROR(__xludf.DUMMYFUNCTION("""COMPUTED_VALUE"""),9.763313182E9) -> 9763313182 | F31: =IFERROR(__xludf.DUMMYFUNCTION("""COMPUTED_VALUE"""),400.0) -> 400 | G31: =IFERROR(__xludf.DUMMYFUNCTION("""COMPUTED_VALUE"""),1400.0) -> 1400 | H31: =IFERROR(__xludf.DUMMYFUNCTION("""COMPUTED_VALUE"""),102.5) -> 102.5 | I31: =IFERROR(__xludf.DUMMYFUNCTION("""COMPUTED_VALUE"""),"Delivered") -> Delivered | J31: =IFERROR(__xludf.DUMMYFUNCTION("""COMPUTED_VALUE"""),45869.45903935185) -> 45869.459
A32: =IFERROR(__xludf.DUMMYFUNCTION("""COMPUTED_VALUE"""),45867.21146990741) -> 45867.211 | B32: =IFERROR(__xludf.DUMMYFUNCTION("""COMPUTED_VALUE"""),"Nie 11 red and black") -> Nie 11 red and black | C32: =IFERROR(__xludf.DUMMYFUNCTION("""COMPUTED_VALUE"""),"Raj Thegim Limbu") -> Raj Thegim Limbu | D32: =IFERROR(__xludf.DUMMYFUNCTION("""COMPUTED_VALUE"""),"Jalthal, jhapa") -> Jalthal, jhapa | E32: =IFERROR(__xludf.DUMMYFUNCTION("""COMPUTED_VALUE"""),9.814977789E9) -> 9814977789 | F32: =IFERROR(__xludf.DUMMYFUNCTION("""COMPUTED_VALUE"""),700.0) -> 700 | G32: =IFERROR(__xludf.DUMMYFUNCTION("""COMPUTED_VALUE"""),2500.0) -> 2500 | H32: =IFERROR(__xludf.DUMMYFUNCTION("""COMPUTED_VALUE"""),185.25) -> 185.25 | I32: =IFERROR(__xludf.DUMMYFUNCTION("""COMPUTED_VALUE"""),"Delivered") -> Delivered | J32: =IFERROR(__xludf.DUMMYFUNCTION("""COMPUTED_VALUE"""),45870.19578703704) -> 45870.196
A33: =IFERROR(__xludf.DUMMYFUNCTION("""COMPUTED_VALUE"""),45867.20958333333) -> 45867.21 | B33: =IFERROR(__xludf.DUMMYFUNCTION("""COMPUTED_VALUE"""),"White Nike 37") -> White Nike 37 | C33: =IFERROR(__xludf.DUMMYFUNCTION("""COMPUTED_VALUE"""),"Gaurav Jaiswal") -> Gaurav Jaiswal | D33: =IFERROR(__xludf.DUMMYFUNCTION("""COMPUTED_VALUE"""),"Nepalgunj, dhamboji chowk siddhartha Bank najik") -> Nepalgunj, dhamboji chowk siddhartha Bank najik | E33: =IFERROR(__xludf.DUMMYFUNCTION("""COMPUTED_VALUE"""),9.762065388E9) -> 9762065388 | F33: =IFERROR(__xludf.DUMMYFUNCTION("""COMPUTED_VALUE"""),350.0) -> 350 | G33: =IFERROR(__xludf.DUMMYFUNCTION("""COMPUTED_VALUE"""),1350.0) -> 1350 | H33: =IFERROR(__xludf.DUMMYFUNCTION("""COMPUTED_VALUE"""),212.38) -> 212.38 | I33: =IFERROR(__xludf.DUMMYFUNCTION("""COMPUTED_VALUE"""),"Delivered") -> Delivered | J33: =IFERROR(__xludf.DUMMYFUNCTION("""COMPUTED_VALUE"""),45872.44072916667) -> 45872.441
A34: =IFERROR(__xludf.DUMMYFUNCTION("""COMPUTED_VALUE"""),45865.19533564815) -> 45865.195 | B34: =IFERROR(__xludf.DUMMYFUNCTION("""COMPUTED_VALUE"""),"Martin 3 sole size 39") -> Martin 3 sole size 39 | C34: =IFERROR(__xludf.DUMMYFUNCTION("""COMPUTED_VALUE"""),"Manoj") -> Manoj | D34: =IFERROR(__xludf.DUMMYFUNCTION("""COMPUTED_VALUE"""),"Ktm, sundarijal dobato chowk") -> Ktm, sundarijal dobato chowk | E34: =IFERROR(__xludf.DUMMYFUNCTION("""COMPUTED_VALUE"""),9.768966994E9) -> 9768966994 | F34: =IFERROR(__xludf.DUMMYFUNCTION("""COMPUTED_VALUE"""),500.0) -> 500 | G34: =IFERROR(__xludf.DUMMYFUNCTION("""COMPUTED_VALUE"""),1500.0) -> 1500 | H34: =IFERROR(__xludf.DUMMYFUNCTION("""COMPUTED_VALUE"""),102.75) -> 102.75 | I34: =IFERROR(__xludf.DUMMYFUNCTION("""COMPUTED_VALUE"""),"Delivered") -> Delivered | J34: =IFERROR(__xludf.DUMMYFUNCTION("""COMPUTED_VALUE"""),45867.2159837963) -> 45867.216
A35: =IFERROR(__xludf.DUMMYFUNCTION("""COMPUTED_VALUE"""),45865.183171296296) -> 45865.183 | B35: =IFERROR(__xludf.DUMMYFUNCTION("""COMPUTED_VALUE"""),"Chelsea size 41") -> Chelsea size 41 | C35: =IFERROR(__xludf.DUMMYFUNCTION("""COMPUTED_VALUE"""),"Sudesh Shrestha") -> Sudesh Shrestha | D35: =IFERROR(__xludf.DUMMYFUNCTION("""COMPUTED_VALUE"""),"Sundar haraicha 12, biratchowk Road no 12") -> Sundar haraicha 12, biratchowk Road no 12 | E35: =IFERROR(__xludf.DUMMYFUNCTION("""COMPUTED_VALUE"""),9.862232928E9) -> 9862232928 | F35: =IFERROR(__xludf.DUMMYFUNCTION("""COMPUTED_VALUE"""),450.0) -> 450 | G35: =IFERROR(__xludf.DUMMYFUNCTION("""COMPUTED_VALUE"""),1350.0) -> 1350 | H35: =IFERROR(__xludf.DUMMYFUNCTION("""COMPUTED_VALUE"""),162.38) -> 162.38 | I35: =IFERROR(__xludf.DUMMYFUNCTION("""COMPUTED_VALUE"""),"Delivered") -> Delivered | J35: =IFERROR(__xludf.DUMMYFUNCTION("""COMPUTED_VALUE"""),45867.38013888889) -> 45867.38
A36: =IFERROR(__xludf.DUMMYFUNCTION("""COMPUTED_VALUE"""),45865.18116898148) -> 45865.181 | B36: =IFERROR(__xludf.DUMMYFUNCTION("""COMPUTED_VALUE"""),"Sb dunk 41") -> Sb dunk 41 | C36: =IFERROR(__xludf.DUMMYFUNCTION("""COMPUTED_VALUE"""),"Sijan Shrestha") -> Sijan Shrestha | D36: =IFERROR(__xludf.DUMMYFUNCTION("""COMPUTED_VALUE"""),"Beni, myagdi") -> Beni, myagdi | E36: =IFERROR(__xludf.DUMMYFUNCTION("""COMPUTED_VALUE"""),9.84764997E9) -> 9847649970 | F36: =IFERROR(__xludf.DUMMYFUNCTION("""COMPUTED_VALUE"""),400.0) -> 400 | G36: =IFERROR(__xludf.DUMMYFUNCTION("""COMPUTED_VALUE"""),1400.0) -> 1400 | H36: =IFERROR(__xludf.DUMMYFUNCTION("""COMPUTED_VALUE"""),212.5) -> 212.5 | I36: =IFERROR(__xludf.DUMMYFUNCTION("""COMPUTED_VALUE"""),"Delivered") -> Delivered | J36: =IFERROR(__xludf.DUMMYFUNCTION("""COMPUTED_VALUE"""),45867.280752314815) -> 45867.281
A37: =IFERROR(__xludf.DUMMYFUNCTION("""COMPUTED_VALUE"""),45865.17979166667) -> 45865.18 | B37: =IFERROR(__xludf.DUMMYFUNCTION("""COMPUTED_VALUE"""),"Red Nike ") -> Red Nike | C37: =IFERROR(__xludf.DUMMYFUNCTION("""COMPUTED_VALUE"""),"Aayush Panthi") -> Aayush Panthi | D37: =IFERROR(__xludf.DUMMYFUNCTION("""COMPUTED_VALUE"""),"Butwal, bhakwari 7, lec college side") -> Butwal, bhakwari 7, lec college side | E37: =IFERROR(__xludf.DUMMYFUNCTION("""COMPUTED_VALUE"""),9.844755593E9) -> 9844755593 | F37: =IFERROR(__xludf.DUMMYFUNCTION("""COMPUTED_VALUE"""),350.0) -> 350 | G37: =IFERROR(__xludf.DUMMYFUNCTION("""COMPUTED_VALUE"""),1350.0) -> 1350 | H37: =IFERROR(__xludf.DUMMYFUNCTION("""COMPUTED_VALUE"""),182.38) -> 182.38 | I37: =IFERROR(__xludf.DUMMYFUNCTION("""COMPUTED_VALUE"""),"Delivered") -> Delivered | J37: =IFERROR(__xludf.DUMMYFUNCTION("""COMPUTED_VALUE"""),45866.38072916667) -> 45866.381
A38: =IFERROR(__xludf.DUMMYFUNCTION("""COMPUTED_VALUE"""),45865.17822916667) -> 45865.178 | B38: =IFERROR(__xludf.DUMMYFUNCTION("""COMPUTED_VALUE"""),"Dark brown 40") -> Dark brown 40 | C38: =IFERROR(__xludf.DUMMYFUNCTION("""COMPUTED_VALUE"""),"Govinda Khatiwada") -> Govinda Khatiwada | D38: =IFERROR(__xludf.DUMMYFUNCTION("""COMPUTED_VALUE"""),"Salleri bazar, solukhumbu") -> Salleri bazar, solukhumbu | E38: =IFERROR(__xludf.DUMMYFUNCTION("""COMPUTED_VALUE"""),9.869667233E9) -> 9869667233 | F38: =IFERROR(__xludf.DUMMYFUNCTION("""COMPUTED_VALUE"""),320.0) -> 320 | G38: =IFERROR(__xludf.DUMMYFUNCTION("""COMPUTED_VALUE"""),1320.0) -> 1320 | H38: =IFERROR(__xludf.DUMMYFUNCTION("""COMPUTED_VALUE"""),212.3) -> 212.3 | I38: =IFERROR(__xludf.DUMMYFUNCTION("""COMPUTED_VALUE"""),"Delivered") -> Delivered | J38: =IFERROR(__xludf.DUMMYFUNCTION("""COMPUTED_VALUE"""),45867.60194444444) -> 45867.602
A39: =IFERROR(__xludf.DUMMYFUNCTION("""COMPUTED_VALUE"""),45864.20482638889) -> 45864.205 | B39: =IFERROR(__xludf.DUMMYFUNCTION("""COMPUTED_VALUE"""),"Size 39 Martin 3 sole") -> Size 39 Martin 3 sole | C39: =IFERROR(__xludf.DUMMYFUNCTION("""COMPUTED_VALUE"""),"Rohan") -> Rohan | D39: =IFERROR(__xludf.DUMMYFUNCTION("""COMPUTED_VALUE"""),"Manakamana suit hotel, gogechaur, banepa") -> Manakamana suit hotel, gogechaur, banepa | E39: =IFERROR(__xludf.DUMMYFUNCTION("""COMPUTED_VALUE"""),9.701538165E9) -> 9701538165 | F39: =IFERROR(__xludf.DUMMYFUNCTION("""COMPUTED_VALUE"""),600.0) -> 600 | G39: =IFERROR(__xludf.DUMMYFUNCTION("""COMPUTED_VALUE"""),1600.0) -> 1600 | H39: =IFERROR(__xludf.DUMMYFUNCTION("""COMPUTED_VALUE"""),163.0) -> 163 | I39: =IFERROR(__xludf.DUMMYFUNCTION("""COMPUTED_VALUE"""),"Delivered") -> Delivered | J39: =IFERROR(__xludf.DUMMYFUNCTION("""COMPUTED_VALUE"""),45865.5271875) -> 45865.527
A40: =IFERROR(__xludf.DUMMYFUNCTION("""COMPUTED_VALUE"""),45864.203668981485) -> 45864.204 | B40: =IFERROR(__xludf.DUMMYFUNCTION("""COMPUTED_VALUE"""),"Single sole Martin 43") -> Single sole Martin 43 | C40: =IFERROR(__xludf.DUMMYFUNCTION("""COMPUTED_VALUE"""),"Ankit Rajbanshi") -> Ankit Rajbanshi | D40: =IFERROR(__xludf.DUMMYFUNCTION("""COMPUTED_VALUE"""),"Mechinagar-10, dhulabari, jhapa") -> Mechinagar-10, dhulabari, jhapa | E40: =IFERROR(__xludf.DUMMYFUNCTION("""COMPUTED_VALUE"""),9.827940827E9) -> 9827940827 | F40: =IFERROR(__xludf.DUMMYFUNCTION("""COMPUTED_VALUE"""),350.0) -> 350 | G40: =IFERROR(__xludf.DUMMYFUNCTION("""COMPUTED_VALUE"""),1350.0) -> 1350 | H40: =IFERROR(__xludf.DUMMYFUNCTION("""COMPUTED_VALUE"""),182.38) -> 182.38 | I40: =IFERROR(__xludf.DUMMYFUNCTION("""COMPUTED_VALUE"""),"Delivered") -> Delivered | J40: =IFERROR(__xludf.DUMMYFUNCTION("""COMPUTED_VALUE"""),45866.45042824074) -> 45866.45
A41: =IFERROR(__xludf.DUMMYFUNCTION("""COMPUTED_VALUE"""),45864.191504629634) -> 45864.192 | B41: =IFERROR(__xludf.DUMMYFUNCTION("""COMPUTED_VALUE"""),"Brown 40") -> Brown 40 | C41: =IFERROR(__xludf.DUMMYFUNCTION("""COMPUTED_VALUE"""),"Toshu Sah") -> Toshu Sah | D41: =IFERROR(__xludf.DUMMYFUNCTION("""COMPUTED_VALUE"""),"Chyasal, lalitpur") -> Chyasal, lalitpur | E41: =IFERROR(__xludf.DUMMYFUNCTION("""COMPUTED_VALUE"""),9.700310751E9) -> 9700310751 | F41: =IFERROR(__xludf.DUMMYFUNCTION("""COMPUTED_VALUE"""),300.0) -> 300 | G41: =IFERROR(__xludf.DUMMYFUNCTION("""COMPUTED_VALUE"""),1300.0) -> 1300 | H41: =IFERROR(__xludf.DUMMYFUNCTION("""COMPUTED_VALUE"""),102.25) -> 102.25 | I41: =IFERROR(__xludf.DUMMYFUNCTION("""COMPUTED_VALUE"""),"Delivered") -> Delivered | J41: =IFERROR(__xludf.DUMMYFUNCTION("""COMPUTED_VALUE"""),45865.17994212963) -> 45865.18
A42: =IFERROR(__xludf.DUMMYFUNCTION("""COMPUTED_VALUE"""),45863.22542824074) -> 45863.225 | B42: =IFERROR(__xludf.DUMMYFUNCTION("""COMPUTED_VALUE"""),"Martin half double sole") -> Martin half double sole | C42: =IFERROR(__xludf.DUMMYFUNCTION("""COMPUTED_VALUE"""),"Abhishek rokaya") -> Abhishek rokaya | D42: =IFERROR(__xludf.DUMMYFUNCTION("""COMPUTED_VALUE"""),"Durbarmarg , yakyeti marg Jane bato") -> Durbarmarg , yakyeti marg Jane bato | E42: =IFERROR(__xludf.DUMMYFUNCTION("""COMPUTED_VALUE"""),9.822767923E9) -> 9822767923 | F42: =IFERROR(__xludf.DUMMYFUNCTION("""COMPUTED_VALUE"""),400.0) -> 400 | G42: =IFERROR(__xludf.DUMMYFUNCTION("""COMPUTED_VALUE"""),1300.0) -> 1300 | H42: =IFERROR(__xludf.DUMMYFUNCTION("""COMPUTED_VALUE"""),102.25) -> 102.25 | I42: =IFERROR(__xludf.DUMMYFUNCTION("""COMPUTED_VALUE"""),"Delivered") -> Delivered | J42: =IFERROR(__xludf.DUMMYFUNCTION("""COMPUTED_VALUE"""),45863.423414351855) -> 45863.423
A43: =IFERROR(__xludf.DUMMYFUNCTION("""COMPUTED_VALUE"""),45863.22326388889) -> 45863.223 | B43: =IFERROR(__xludf.DUMMYFUNCTION("""COMPUTED_VALUE"""),"Sky blue Nike size 42") -> Sky blue Nike size 42 | C43: =IFERROR(__xludf.DUMMYFUNCTION("""COMPUTED_VALUE"""),"Rohan Grg Prajoo") -> Rohan Grg Prajoo | D43: =IFERROR(__xludf.DUMMYFUNCTION("""COMPUTED_VALUE"""),"Tersapatti 3 pokhara") -> Tersapatti 3 pokhara | E43: =IFERROR(__xludf.DUMMYFUNCTION("""COMPUTED_VALUE"""),9.705554376E9) -> 9705554376 | F43: =IFERROR(__xludf.DUMMYFUNCTION("""COMPUTED_VALUE"""),350.0) -> 350 | G43: =IFERROR(__xludf.DUMMYFUNCTION("""COMPUTED_VALUE"""),1350.0) -> 1350 | H43: =IFERROR(__xludf.DUMMYFUNCTION("""COMPUTED_VALUE"""),162.38) -> 162.38 | I43: =IFERROR(__xludf.DUMMYFUNCTION("""COMPUTED_VALUE"""),"Delivered") -> Delivered | J43: =IFERROR(__xludf.DUMMYFUNCTION("""COMPUTED_VALUE"""),45866.33039351852) -> 45866.33
A44: =IFERROR(__xludf.DUMMYFUNCTION("""COMPUTED_VALUE"""),45863.203414351854) -> 45863.203 | B44: =IFERROR(__xludf.DUMMYFUNCTION("""COMPUTED_VALUE"""),"Red Nike 43") -> Red Nike 43 | C44: =IFERROR(__xludf.DUMMYFUNCTION("""COMPUTED_VALUE"""),"Sagar") -> Sagar | D44: =IFERROR(__xludf.DUMMYFUNCTION("""COMPUTED_VALUE"""),"Dhangadhi bhakat chowk, ward no. 9") -> Dhangadhi bhakat chowk, ward no. 9 | E44: =IFERROR(__xludf.DUMMYFUNCTION("""COMPUTED_VALUE"""),9.814660801E9) -> 9814660801 | F44: =IFERROR(__xludf.DUMMYFUNCTION("""COMPUTED_VALUE"""),350.0) -> 350 | G44: =IFERROR(__xludf.DUMMYFUNCTION("""COMPUTED_VALUE"""),1350.0) -> 1350 | H44: =IFERROR(__xludf.DUMMYFUNCTION("""COMPUTED_VALUE"""),182.38) -> 182.38 | I44: =IFERROR(__xludf.DUMMYFUNCTION("""COMPUTED_VALUE"""),"Delivered") -> Delivered | J44: =IFERROR(__xludf.DUMMYFUNCTION("""COMPUTED_VALUE"""),45865.2788425926) -> 45865.279
A45: =IFERROR(__xludf.DUMMYFUNCTION("""COMPUTED_VALUE"""),45863.20244212963) -> 45863.202 | B45: =IFERROR(__xludf.DUMMYFUNCTION("""COMPUTED_VALUE"""),"Nike white and vans 41") -> Nike white and vans 41 | C45: =IFERROR(__xludf.DUMMYFUNCTION("""COMPUTED_VALUE"""),"Manoj Parsai") -> Manoj Parsai | D45: =IFERROR(__xludf.DUMMYFUNCTION("""COMPUTED_VALUE"""),"Nayabazar 10, pokhara, kaski") -> Nayabazar 10, pokhara, kaski | E45: =IFERROR(__xludf.DUMMYFUNCTION("""COMPUTED_VALUE"""),9.816148089E9) -> 9816148089 | F45: =IFERROR(__xludf.DUMMYFUNCTION("""COMPUTED_VALUE"""),950.0) -> 950 | G45: =IFERROR(__xludf.DUMMYFUNCTION("""COMPUTED_VALUE"""),2550.0) -> 2550 | H45: =IFERROR(__xludf.DUMMYFUNCTION("""COMPUTED_VALUE"""),165.38) -> 165.38 | I45: =IFERROR(__xludf.DUMMYFUNCTION("""COMPUTED_VALUE"""),"Delivered") -> Delivered | J45: =IFERROR(__xludf.DUMMYFUNCTION("""COMPUTED_VALUE"""),45864.416226851856) -> 45864.416
A46: =IFERROR(__xludf.DUMMYFUNCTION("""COMPUTED_VALUE"""),45862.1970949074) -> 45862.197 | B46: =IFERROR(__xludf.DUMMYFUNCTION("""COMPUTED_VALUE"""),"Sr sports and vans 42") -> Sr sports and vans 42 | C46: =IFERROR(__xludf.DUMMYFUNCTION("""COMPUTED_VALUE"""),"Abhishek Shrestha") -> Abhishek Shrestha | D46: =IFERROR(__xludf.DUMMYFUNCTION("""COMPUTED_VALUE"""),"Tokha, kathmandu") -> Tokha, kathmandu | E46: =IFERROR(__xludf.DUMMYFUNCTION("""COMPUTED_VALUE"""),9.803226972E9) -> 9803226972 | F46: =IFERROR(__xludf.DUMMYFUNCTION("""COMPUTED_VALUE"""),900.0) -> 900 | G46: =IFERROR(__xludf.DUMMYFUNCTION("""COMPUTED_VALUE"""),2500.0) -> 2500 | H46: =IFERROR(__xludf.DUMMYFUNCTION("""COMPUTED_VALUE"""),105.25) -> 105.25 | I46: =IFERROR(__xludf.DUMMYFUNCTION("""COMPUTED_VALUE"""),"Delivered") -> Delivered | J46: =IFERROR(__xludf.DUMMYFUNCTION("""COMPUTED_VALUE"""),45863.3140625) -> 45863.314
A47: =IFERROR(__xludf.DUMMYFUNCTION("""COMPUTED_VALUE"""),45862.19537037037) -> 45862.195 | B47: =IFERROR(__xludf.DUMMYFUNCTION("""COMPUTED_VALUE"""),"Dark brown 42") -> Dark brown 42 | C47: =IFERROR(__xludf.DUMMYFUNCTION("""COMPUTED_VALUE"""),"Suraj Gyawali") -> Suraj Gyawali | D47: =IFERROR(__xludf.DUMMYFUNCTION("""COMPUTED_VALUE"""),"Parsyang pokhara") -> Parsyang pokhara | E47: =IFERROR(__xludf.DUMMYFUNCTION("""COMPUTED_VALUE"""),9.84730756E9) -> 9847307560 | F47: =IFERROR(__xludf.DUMMYFUNCTION("""COMPUTED_VALUE"""),350.0) -> 350 | G47: =IFERROR(__xludf.DUMMYFUNCTION("""COMPUTED_VALUE"""),1350.0) -> 1350 | H47: =IFERROR(__xludf.DUMMYFUNCTION("""COMPUTED_VALUE"""),162.38) -> 162.38 | I47: =IFERROR(__xludf.DUMMYFUNCTION("""COMPUTED_VALUE"""),"Delivered") -> Delivered | J47: =IFERROR(__xludf.DUMMYFUNCTION("""COMPUTED_VALUE"""),45863.42010416667) -> 45863.42
A48: =IFERROR(__xludf.DUMMYFUNCTION("""COMPUTED_VALUE"""),45862.188368055555) -> 45862.188 | B48: =IFERROR(__xludf.DUMMYFUNCTION("""COMPUTED_VALUE"""),"Vans 42") -> Vans 42 | C48: =IFERROR(__xludf.DUMMYFUNCTION("""COMPUTED_VALUE"""),"Bhuwan Dev") -> Bhuwan Dev | D48: =IFERROR(__xludf.DUMMYFUNCTION("""COMPUTED_VALUE"""),"Soil management dictorate harihar bhawan, lalitpur ") -> Soil management dictorate harihar bhawan, lalitpur | E48: =IFERROR(__xludf.DUMMYFUNCTION("""COMPUTED_VALUE"""),9.766381427E9) -> 9766381427 | F48: =IFERROR(__xludf.DUMMYFUNCTION("""COMPUTED_VALUE"""),700.0) -> 700 | G48: =IFERROR(__xludf.DUMMYFUNCTION("""COMPUTED_VALUE"""),1300.0) -> 1300 | H48: =IFERROR(__xludf.DUMMYFUNCTION("""COMPUTED_VALUE"""),102.25) -> 102.25 | I48: =IFERROR(__xludf.DUMMYFUNCTION("""COMPUTED_VALUE"""),"Delivered") -> Delivered | J48: =IFERROR(__xludf.DUMMYFUNCTION("""COMPUTED_VALUE"""),45863.28288194444) -> 45863.283
A49: =IFERROR(__xludf.DUMMYFUNCTION("""COMPUTED_VALUE"""),45861.20143518518) -> 45861.201 | B49: =IFERROR(__xludf.DUMMYFUNCTION("""COMPUTED_VALUE"""),"Dunk Low pro 39") -> Dunk Low pro 39 | C49: =IFERROR(__xludf.DUMMYFUNCTION("""COMPUTED_VALUE"""),"Arpan Neupane") -> Arpan Neupane | D49: =IFERROR(__xludf.DUMMYFUNCTION("""COMPUTED_VALUE"""),"Kharaney path, leknath kaski") -> Kharaney path, leknath kaski | E49: =IFERROR(__xludf.DUMMYFUNCTION("""COMPUTED_VALUE"""),9.846952971E9) -> 9846952971 | F49: =IFERROR(__xludf.DUMMYFUNCTION("""COMPUTED_VALUE"""),350.0) -> 350 | G49: =IFERROR(__xludf.DUMMYFUNCTION("""COMPUTED_VALUE"""),1350.0) -> 1350 | H49: =IFERROR(__xludf.DUMMYFUNCTION("""COMPUTED_VALUE"""),162.38) -> 162.38 | I49: =IFERROR(__xludf.DUMMYFUNCTION("""COMPUTED_VALUE"""),"Delivered") -> Delivered | J49: =IFERROR(__xludf.DUMMYFUNCTION("""COMPUTED_VALUE"""),45862.362337962964) -> 45862.362
A50: =IFERROR(__xludf.DUMMYFUNCTION("""COMPUTED_VALUE"""),45861.199224537035) -> 45861.199 | B50: =IFERROR(__xludf.DUMMYFUNCTION("""COMPUTED_VALUE"""),"Vans 41") -> Vans 41 | C50: =IFERROR(__xludf.DUMMYFUNCTION("""COMPUTED_VALUE"""),"Menal Shrestha") -> Menal Shrestha | D50: =IFERROR(__xludf.DUMMYFUNCTION("""COMPUTED_VALUE"""),"Steel Tower, jawalakhel") -> Steel Tower, jawalakhel | E50: =IFERROR(__xludf.DUMMYFUNCTION("""COMPUTED_VALUE"""),9.818994553E9) -> 9818994553 | F50: =IFERROR(__xludf.DUMMYFUNCTION("""COMPUTED_VALUE"""),700.0) -> 700 | G50: =IFERROR(__xludf.DUMMYFUNCTION("""COMPUTED_VALUE"""),1300.0) -> 1300 | H50: =IFERROR(__xludf.DUMMYFUNCTION("""COMPUTED_VALUE"""),102.25) -> 102.25 | I50: =IFERROR(__xludf.DUMMYFUNCTION("""COMPUTED_VALUE"""),"Delivered") -> Delivered | J50: =IFERROR(__xludf.DUMMYFUNCTION("""COMPUTED_VALUE"""),45861.44431712963) -> 45861.444
A51: =IFERROR(__xludf.DUMMYFUNCTION("""COMPUTED_VALUE"""),45860.51074074074) -> 45860.511 | B51: =IFERROR(__xludf.DUMMYFUNCTION("""COMPUTED_VALUE"""),"Sr delta size 39") -> Sr delta size 39 | C51: =IFERROR(__xludf.DUMMYFUNCTION("""COMPUTED_VALUE"""),"Sanjit Tamang") -> Sanjit Tamang | D51: =IFERROR(__xludf.DUMMYFUNCTION("""COMPUTED_VALUE"""),"Sirutar, bhaktapur") -> Sirutar, bhaktapur | E51: =IFERROR(__xludf.DUMMYFUNCTION("""COMPUTED_VALUE"""),9.826764749E9) -> 9826764749 | F51: =IFERROR(__xludf.DUMMYFUNCTION("""COMPUTED_VALUE"""),300.0) -> 300 | G51: =IFERROR(__xludf.DUMMYFUNCTION("""COMPUTED_VALUE"""),1300.0) -> 1300 | H51: =IFERROR(__xludf.DUMMYFUNCTION("""COMPUTED_VALUE"""),102.25) -> 102.25 | I51: =IFERROR(__xludf.DUMMYFUNCTION("""COMPUTED_VALUE"""),"Delivered") -> Delivered | J51: =IFERROR(__xludf.DUMMYFUNCTION("""COMPUTED_VALUE"""),45862.395266203705) -> 45862.395
A52: =IFERROR(__xludf.DUMMYFUNCTION("""COMPUTED_VALUE"""),45857.22825231482) -> 45857.228 | B52: =IFERROR(__xludf.DUMMYFUNCTION("""COMPUTED_VALUE"""),"Vans 43") -> Vans 43 | C52: =IFERROR(__xludf.DUMMYFUNCTION("""COMPUTED_VALUE"""),"Newar Shyam") -> Newar Shyam | D52: =IFERROR(__xludf.DUMMYFUNCTION("""COMPUTED_VALUE"""),"Pakhapani, dang") -> Pakhapani, dang | E52: =IFERROR(__xludf.DUMMYFUNCTION("""COMPUTED_VALUE"""),9.843713594E9) -> 9843713594 | F52: =IFERROR(__xludf.DUMMYFUNCTION("""COMPUTED_VALUE"""),750.0) -> 750 | G52: =IFERROR(__xludf.DUMMYFUNCTION("""COMPUTED_VALUE"""),1350.0) -> 1350 | H52: =IFERROR(__xludf.DUMMYFUNCTION("""COMPUTED_VALUE"""),232.38) -> 232.38 | I52: =IFERROR(__xludf.DUMMYFUNCTION("""COMPUTED_VALUE"""),"Delivered") -> Delivered | J52: =IFERROR(__xludf.DUMMYFUNCTION("""COMPUTED_VALUE"""),45860.518425925926) -> 45860.518
A53: =IFERROR(__xludf.DUMMYFUNCTION("""COMPUTED_VALUE"""),45857.20888888889) -> 45857.209 | B53: =IFERROR(__xludf.DUMMYFUNCTION("""COMPUTED_VALUE"""),"Gray 42") -> Gray 42 | C53: =IFERROR(__xludf.DUMMYFUNCTION("""COMPUTED_VALUE"""),"Diwash") -> Diwash | D53: =IFERROR(__xludf.DUMMYFUNCTION("""COMPUTED_VALUE"""),"Morang pathari") -> Morang pathari | E53: =IFERROR(__xludf.DUMMYFUNCTION("""COMPUTED_VALUE"""),9.746898035E9) -> 9746898035 | F53: =IFERROR(__xludf.DUMMYFUNCTION("""COMPUTED_VALUE"""),450.0) -> 450 | G53: =IFERROR(__xludf.DUMMYFUNCTION("""COMPUTED_VALUE"""),1450.0) -> 1450 | H53: =IFERROR(__xludf.DUMMYFUNCTION("""COMPUTED_VALUE"""),232.63) -> 232.63 | I53: =IFERROR(__xludf.DUMMYFUNCTION("""COMPUTED_VALUE"""),"Delivered") -> Delivered | J53: =IFERROR(__xludf.DUMMYFUNCTION("""COMPUTED_VALUE"""),45862.316307870366) -> 45862.316
A54: =IFERROR(__xludf.DUMMYFUNCTION("""COMPUTED_VALUE"""),45857.206296296295) -> 45857.206 | B54: =IFERROR(__xludf.DUMMYFUNCTION("""COMPUTED_VALUE"""),"Nike White and gray 43") -> Nike White and gray 43 | C54: =IFERROR(__xludf.DUMMYFUNCTION("""COMPUTED_VALUE"""),"Nishan sigdel") -> Nishan sigdel | D54: =IFERROR(__xludf.DUMMYFUNCTION("""COMPUTED_VALUE"""),"Sunsari, ramdhuni bhasi, lalpur") -> Sunsari, ramdhuni bhasi, lalpur | E54: =IFERROR(__xludf.DUMMYFUNCTION("""COMPUTED_VALUE"""),9.829369398E9) -> 9829369398 | F54: =IFERROR(__xludf.DUMMYFUNCTION("""COMPUTED_VALUE"""),450.0) -> 450 | G54: =IFERROR(__xludf.DUMMYFUNCTION("""COMPUTED_VALUE"""),2450.0) -> 2450 | H54: =IFERROR(__xludf.DUMMYFUNCTION("""COMPUTED_VALUE"""),215.13) -> 215.13 | I54: =IFERROR(__xludf.DUMMYFUNCTION("""COMPUTED_VALUE"""),"Delivered") -> Delivered | J54: =IFERROR(__xludf.DUMMYFUNCTION("""COMPUTED_VALUE"""),45860.3343287037) -> 45860.334
A55: =IFERROR(__xludf.DUMMYFUNCTION("""COMPUTED_VALUE"""),45857.19940972222) -> 45857.199 | B55: =IFERROR(__xludf.DUMMYFUNCTION("""COMPUTED_VALUE"""),"Brown 39 nike") -> Brown 39 nike | C55: =IFERROR(__xludf.DUMMYFUNCTION("""COMPUTED_VALUE"""),"Samir Khadka") -> Samir Khadka | D55: =IFERROR(__xludf.DUMMYFUNCTION("""COMPUTED_VALUE"""),"Mullani, manakamana mandir") -> Mullani, manakamana mandir | E55: =IFERROR(__xludf.DUMMYFUNCTION("""COMPUTED_VALUE"""),9.80344133E9) -> 9803441330 | F55: =IFERROR(__xludf.DUMMYFUNCTION("""COMPUTED_VALUE"""),300.0) -> 300 | G55: =IFERROR(__xludf.DUMMYFUNCTION("""COMPUTED_VALUE"""),1300.0) -> 1300 | H55: =IFERROR(__xludf.DUMMYFUNCTION("""COMPUTED_VALUE"""),152.25) -> 152.25 | I55: =IFERROR(__xludf.DUMMYFUNCTION("""COMPUTED_VALUE"""),"Delivered") -> Delivered | J55: =IFERROR(__xludf.DUMMYFUNCTION("""COMPUTED_VALUE"""),45858.38641203704) -> 45858.386
A56: =IFERROR(__xludf.DUMMYFUNCTION("""COMPUTED_VALUE"""),45857.197800925926) -> 45857.198 | B56: =IFERROR(__xludf.DUMMYFUNCTION("""COMPUTED_VALUE"""),"Nike 11 red 44") -> Nike 11 red 44 | C56: =IFERROR(__xludf.DUMMYFUNCTION("""COMPUTED_VALUE"""),"Dipesh Bhusal") -> Dipesh Bhusal | D56: =IFERROR(__xludf.DUMMYFUNCTION("""COMPUTED_VALUE"""),"Accham district, sanfebagar") -> Accham district, sanfebagar | E56: =IFERROR(__xludf.DUMMYFUNCTION("""COMPUTED_VALUE"""),9.86471728E9) -> 9864717280 | F56: =IFERROR(__xludf.DUMMYFUNCTION("""COMPUTED_VALUE"""),650.0) -> 650 | G56: =IFERROR(__xludf.DUMMYFUNCTION("""COMPUTED_VALUE"""),1450.0) -> 1450 | H56: =IFERROR(__xludf.DUMMYFUNCTION("""COMPUTED_VALUE"""),212.63) -> 212.63 | I56: =IFERROR(__xludf.DUMMYFUNCTION("""COMPUTED_VALUE"""),"Delivered") -> Delivered | J56: =IFERROR(__xludf.DUMMYFUNCTION("""COMPUTED_VALUE"""),45860.51934027778) -> 45860.519
A57: =IFERROR(__xludf.DUMMYFUNCTION("""COMPUTED_VALUE"""),45857.19510416666) -> 45857.195 | B57: =IFERROR(__xludf.DUMMYFUNCTION("""COMPUTED_VALUE"""),"Vans 41") -> Vans 41 | C57: =IFERROR(__xludf.DUMMYFUNCTION("""COMPUTED_VALUE"""),"Aashish Aryal") -> Aashish Aryal | D57: =IFERROR(__xludf.DUMMYFUNCTION("""COMPUTED_VALUE"""),"Sunwal 13, badera") -> Sunwal 13, badera | E57: =IFERROR(__xludf.DUMMYFUNCTION("""COMPUTED_VALUE"""),9.762248226E9) -> 9762248226 | F57: =IFERROR(__xludf.DUMMYFUNCTION("""COMPUTED_VALUE"""),700.0) -> 700 | G57: =IFERROR(__xludf.DUMMYFUNCTION("""COMPUTED_VALUE"""),1300.0) -> 1300 | H57: =IFERROR(__xludf.DUMMYFUNCTION("""COMPUTED_VALUE"""),232.25) -> 232.25 | I57: =IFERROR(__xludf.DUMMYFUNCTION("""COMPUTED_VALUE"""),"Delivered") -> Delivered | J57: =IFERROR(__xludf.DUMMYFUNCTION("""COMPUTED_VALUE"""),45860.359872685185) -> 45860.36
A58: =IFERROR(__xludf.DUMMYFUNCTION("""COMPUTED_VALUE"""),45822.13050925926) -> 45822.131 | B58: =IFERROR(__xludf.DUMMYFUNCTION("""COMPUTED_VALUE"""),"Red full size 42 skating") -> Red full size 42 skating | C58: =IFERROR(__xludf.DUMMYFUNCTION("""COMPUTED_VALUE"""),"Bishwas") -> Bishwas | D58: =IFERROR(__xludf.DUMMYFUNCTION("""COMPUTED_VALUE"""),"Cea high school, balaju") -> Cea high school, balaju | E58: =IFERROR(__xludf.DUMMYFUNCTION("""COMPUTED_VALUE"""),9.82801524E9) -> 9828015240 | F58: =IFERROR(__xludf.DUMMYFUNCTION("""COMPUTED_VALUE"""),300.0) -> 300 | G58: =IFERROR(__xludf.DUMMYFUNCTION("""COMPUTED_VALUE"""),1300.0) -> 1300 | H58: =IFERROR(__xludf.DUMMYFUNCTION("""COMPUTED_VALUE"""),62.25) -> 62.25 | I58: =IFERROR(__xludf.DUMMYFUNCTION("""COMPUTED_VALUE"""),"Delivered") -> Delivered | J58: =IFERROR(__xludf.DUMMYFUNCTION("""COMPUTED_VALUE"""),45823.447384259256) -> 45823.447
A59: =IFERROR(__xludf.DUMMYFUNCTION("""COMPUTED_VALUE"""),45822.128287037034) -> 45822.128 | B59: =IFERROR(__xludf.DUMMYFUNCTION("""COMPUTED_VALUE"""),"Vans size 42") -> Vans size 42 | C59: =IFERROR(__xludf.DUMMYFUNCTION("""COMPUTED_VALUE"""),"Abhishek") -> Abhishek | D59: =IFERROR(__xludf.DUMMYFUNCTION("""COMPUTED_VALUE"""),"Biratchowk, morang") -> Biratchowk, morang | E59: =IFERROR(__xludf.DUMMYFUNCTION("""COMPUTED_VALUE"""),9.803475204E9) -> 9803475204 | F59: =IFERROR(__xludf.DUMMYFUNCTION("""COMPUTED_VALUE"""),700.0) -> 700 | G59: =IFERROR(__xludf.DUMMYFUNCTION("""COMPUTED_VALUE"""),1300.0) -> 1300 | H59: =IFERROR(__xludf.DUMMYFUNCTION("""COMPUTED_VALUE"""),82.25) -> 82.25 | I59: =IFERROR(__xludf.DUMMYFUNCTION("""COMPUTED_VALUE"""),"Delivered") -> Delivered | J59: =IFERROR(__xludf.DUMMYFUNCTION("""COMPUTED_VALUE"""),45827.51219907407) -> 45827.512
A60: =IFERROR(__xludf.DUMMYFUNCTION("""COMPUTED_VALUE"""),45813.1583912037) -> 45813.158 | B60: =IFERROR(__xludf.DUMMYFUNCTION("""COMPUTED_VALUE"""),"Brown Nike size 38") -> Brown Nike size 38 | C60: =IFERROR(__xludf.DUMMYFUNCTION("""COMPUTED_VALUE"""),"Mousam lama") -> Mousam lama | D60: =IFERROR(__xludf.DUMMYFUNCTION("""COMPUTED_VALUE"""),"Bhadrapur-2, jhapa, sagarmatha") -> Bhadrapur-2, jhapa, sagarmatha | E60: =IFERROR(__xludf.DUMMYFUNCTION("""COMPUTED_VALUE"""),9.70776491E9) -> 9707764910 | F60: =IFERROR(__xludf.DUMMYFUNCTION("""COMPUTED_VALUE"""),300.0) -> 300 | G60: =IFERROR(__xludf.DUMMYFUNCTION("""COMPUTED_VALUE"""),1300.0) -> 1300 | H60: =IFERROR(__xludf.DUMMYFUNCTION("""COMPUTED_VALUE"""),82.25) -> 82.25 | I60: =IFERROR(__xludf.DUMMYFUNCTION("""COMPUTED_VALUE"""),"Delivered") -> Delivered | J60: =IFERROR(__xludf.DUMMYFUNCTION("""COMPUTED_VALUE"""),45822.32089120371) -> 45822.321
A61: =IFERROR(__xludf.DUMMYFUNCTION("""COMPUTED_VALUE"""),45812.194236111114) -> 45812.194 | B61: =IFERROR(__xludf.DUMMYFUNCTION("""COMPUTED_VALUE"""),"Martin size 41 double sole") -> Martin size 41 double sole | C61: =IFERROR(__xludf.DUMMYFUNCTION("""COMPUTED_VALUE"""),"Abhishek tamang") -> Abhishek tamang | D61: =IFERROR(__xludf.DUMMYFUNCTION("""COMPUTED_VALUE"""),"Itahari, sathi petrol pump") -> Itahari, sathi petrol pump | E61: =IFERROR(__xludf.DUMMYFUNCTION("""COMPUTED_VALUE"""),9.766341801E9) -> 9766341801 | F61: =IFERROR(__xludf.DUMMYFUNCTION("""COMPUTED_VALUE"""),600.0) -> 600 | G61: =IFERROR(__xludf.DUMMYFUNCTION("""COMPUTED_VALUE"""),1600.0) -> 1600 | H61: =IFERROR(__xludf.DUMMYFUNCTION("""COMPUTED_VALUE"""),83.0) -> 83 | I61: =IFERROR(__xludf.DUMMYFUNCTION("""COMPUTED_VALUE"""),"Delivered") -> Delivered | J61: =IFERROR(__xludf.DUMMYFUNCTION("""COMPUTED_VALUE"""),45815.330034722225) -> 45815.33
A62: =IFERROR(__xludf.DUMMYFUNCTION("""COMPUTED_VALUE"""),45812.19016203703) -> 45812.19 | B62: =IFERROR(__xludf.DUMMYFUNCTION("""COMPUTED_VALUE"""),"Martin double sole size 40") -> Martin double sole size 40 | C62: =IFERROR(__xludf.DUMMYFUNCTION("""COMPUTED_VALUE"""),"Krishna shrestha ") -> Krishna shrestha | D62: =IFERROR(__xludf.DUMMYFUNCTION("""COMPUTED_VALUE"""),"Syangja District, waling municipality") -> Syangja District, waling municipality | E62: =IFERROR(__xludf.DUMMYFUNCTION("""COMPUTED_VALUE"""),9.816675875E9) -> 9816675875 | F62: =IFERROR(__xludf.DUMMYFUNCTION("""COMPUTED_VALUE"""),550.0) -> 550 | G62: =IFERROR(__xludf.DUMMYFUNCTION("""COMPUTED_VALUE"""),1550.0) -> 1550 | H62: =IFERROR(__xludf.DUMMYFUNCTION("""COMPUTED_VALUE"""),82.88) -> 82.88 | I62: =IFERROR(__xludf.DUMMYFUNCTION("""COMPUTED_VALUE"""),"Delivered") -> Delivered | J62: =IFERROR(__xludf.DUMMYFUNCTION("""COMPUTED_VALUE"""),45814.104895833334) -> 45814.105
A63: =IFERROR(__xludf.DUMMYFUNCTION("""COMPUTED_VALUE"""),45812.1859375) -> 45812.186 | B63: =IFERROR(__xludf.DUMMYFUNCTION("""COMPUTED_VALUE"""),"Utsav Nike 40 ") -> Utsav Nike 40 | C63: =IFERROR(__xludf.DUMMYFUNCTION("""COMPUTED_VALUE"""),"Adib aslam") -> Adib aslam | D63: =IFERROR(__xludf.DUMMYFUNCTION("""COMPUTED_VALUE"""),"Near kinderjoy montessori, tikathali") -> Near kinderjoy montessori, tikathali | E63: =IFERROR(__xludf.DUMMYFUNCTION("""COMPUTED_VALUE"""),9.76900403E9) -> 9769004030 | F63: =IFERROR(__xludf.DUMMYFUNCTION("""COMPUTED_VALUE"""),400.0) -> 400 | G63: =IFERROR(__xludf.DUMMYFUNCTION("""COMPUTED_VALUE"""),1200.0) -> 1200 | H63: =IFERROR(__xludf.DUMMYFUNCTION("""COMPUTED_VALUE"""),62.0) -> 62 | I63: =IFERROR(__xludf.DUMMYFUNCTION("""COMPUTED_VALUE"""),"Delivered") -> Delivered | J63: =IFERROR(__xludf.DUMMYFUNCTION("""COMPUTED_VALUE"""),45812.573472222226) -> 45812.573
A64: =IFERROR(__xludf.DUMMYFUNCTION("""COMPUTED_VALUE"""),45812.18383101852) -> 45812.184 | B64: =IFERROR(__xludf.DUMMYFUNCTION("""COMPUTED_VALUE"""),"Vans and Nike size 41 and 42") -> Vans and Nike size 41 and 42 | C64: =IFERROR(__xludf.DUMMYFUNCTION("""COMPUTED_VALUE"""),"Sandip pariyar") -> Sandip pariyar | D64: =IFERROR(__xludf.DUMMYFUNCTION("""COMPUTED_VALUE"""),"Pokhara, leknath argau chowk") -> Pokhara, leknath argau chowk | E64: =IFERROR(__xludf.DUMMYFUNCTION("""COMPUTED_VALUE"""),9.814744722E9) -> 9814744722 | F64: =IFERROR(__xludf.DUMMYFUNCTION("""COMPUTED_VALUE"""),900.0) -> 900 | G64: =IFERROR(__xludf.DUMMYFUNCTION("""COMPUTED_VALUE"""),2500.0) -> 2500 | H64: =IFERROR(__xludf.DUMMYFUNCTION("""COMPUTED_VALUE"""),85.25) -> 85.25 | I64: =IFERROR(__xludf.DUMMYFUNCTION("""COMPUTED_VALUE"""),"Delivered") -> Delivered | J64: =IFERROR(__xludf.DUMMYFUNCTION("""COMPUTED_VALUE"""),45814.34135416667) -> 45814.341
A65: =IFERROR(__xludf.DUMMYFUNCTION("""COMPUTED_VALUE"""),45812.18256944444) -> 45812.183 | B65: =IFERROR(__xludf.DUMMYFUNCTION("""COMPUTED_VALUE"""),"Nike size 43") -> Nike size 43 | C65: =IFERROR(__xludf.DUMMYFUNCTION("""COMPUTED_VALUE"""),"Digital chaudhary") -> Digital chaudhary | D65: =IFERROR(__xludf.DUMMYFUNCTION("""COMPUTED_VALUE"""),"Saptari, kalyanpur") -> Saptari, kalyanpur | E65: =IFERROR(__xludf.DUMMYFUNCTION("""COMPUTED_VALUE"""),9.828836978E9) -> 9828836978 | F65: =IFERROR(__xludf.DUMMYFUNCTION("""COMPUTED_VALUE"""),300.0) -> 300 | G65: =IFERROR(__xludf.DUMMYFUNCTION("""COMPUTED_VALUE"""),1300.0) -> 1300 | H65: =IFERROR(__xludf.DUMMYFUNCTION("""COMPUTED_VALUE"""),82.25) -> 82.25 | I65: =IFERROR(__xludf.DUMMYFUNCTION("""COMPUTED_VALUE"""),"Delivered") -> Delivered | J65: =IFERROR(__xludf.DUMMYFUNCTION("""COMPUTED_VALUE"""),45813.43583333334) -> 45813.436
A66: =IFERROR(__xludf.DUMMYFUNCTION("""COMPUTED_VALUE"""),45811.2071875) -> 45811.207 | B66: =IFERROR(__xludf.DUMMYFUNCTION("""COMPUTED_VALUE"""),"Samba shoes size 42") -> Samba shoes size 42 | C66: =IFERROR(__xludf.DUMMYFUNCTION("""COMPUTED_VALUE"""),"Aashish basnet") -> Aashish basnet | D66: =IFERROR(__xludf.DUMMYFUNCTION("""COMPUTED_VALUE"""),"Sainamaina 9, basgandhi rupandehi") -> Sainamaina 9, basgandhi rupandehi | E66: =IFERROR(__xludf.DUMMYFUNCTION("""COMPUTED_VALUE"""),9.840784344E9) -> 9840784344 | F66: =IFERROR(__xludf.DUMMYFUNCTION("""COMPUTED_VALUE"""),300.0) -> 300 | G66: =IFERROR(__xludf.DUMMYFUNCTION("""COMPUTED_VALUE"""),1300.0) -> 1300 | H66: =IFERROR(__xludf.DUMMYFUNCTION("""COMPUTED_VALUE"""),82.25) -> 82.25 | I66: =IFERROR(__xludf.DUMMYFUNCTION("""COMPUTED_VALUE"""),"Delivered") -> Delivered | J66: =IFERROR(__xludf.DUMMYFUNCTION("""COMPUTED_VALUE"""),45812.31383101852) -> 45812.314
A67: =IFERROR(__xludf.DUMMYFUNCTION("""COMPUTED_VALUE"""),45811.20578703703) -> 45811.206 | B67: =IFERROR(__xludf.DUMMYFUNCTION("""COMPUTED_VALUE"""),"Vans shoes size 43") -> Vans shoes size 43 | C67: =IFERROR(__xludf.DUMMYFUNCTION("""COMPUTED_VALUE"""),"Sujal") -> Sujal | D67: =IFERROR(__xludf.DUMMYFUNCTION("""COMPUTED_VALUE"""),"Pokhara birauta, ram mandir") -> Pokhara birauta, ram mandir | E67: =IFERROR(__xludf.DUMMYFUNCTION("""COMPUTED_VALUE"""),9.826664765E9) -> 9826664765 | F67: =IFERROR(__xludf.DUMMYFUNCTION("""COMPUTED_VALUE"""),700.0) -> 700 | G67: =IFERROR(__xludf.DUMMYFUNCTION("""COMPUTED_VALUE"""),1300.0) -> 1300 | H67: =IFERROR(__xludf.DUMMYFUNCTION("""COMPUTED_VALUE"""),82.25) -> 82.25 | I67: =IFERROR(__xludf.DUMMYFUNCTION("""COMPUTED_VALUE"""),"Delivered") -> Delivered | J67: =IFERROR(__xludf.DUMMYFUNCTION("""COMPUTED_VALUE"""),45812.445810185185) -> 45812.446
A68: =IFERROR(__xludf.DUMMYFUNCTION("""COMPUTED_VALUE"""),45811.20447916667) -> 45811.204 | B68: =IFERROR(__xludf.DUMMYFUNCTION("""COMPUTED_VALUE"""),"Sr shoes size 42") -> Sr shoes size 42 | C68: =IFERROR(__xludf.DUMMYFUNCTION("""COMPUTED_VALUE"""),"Adib aslam") -> Adib aslam | D68: =IFERROR(__xludf.DUMMYFUNCTION("""COMPUTED_VALUE"""),"Near kinderjoy Montessori, tikathali") -> Near kinderjoy Montessori, tikathali | E68: =IFERROR(__xludf.DUMMYFUNCTION("""COMPUTED_VALUE"""),9.76900403E9) -> 9769004030 | F68: =IFERROR(__xludf.DUMMYFUNCTION("""COMPUTED_VALUE"""),400.0) -> 400 | G68: =IFERROR(__xludf.DUMMYFUNCTION("""COMPUTED_VALUE"""),1400.0) -> 1400 | H68: =IFERROR(__xludf.DUMMYFUNCTION("""COMPUTED_VALUE"""),62.5) -> 62.5 | I68: =IFERROR(__xludf.DUMMYFUNCTION("""COMPUTED_VALUE"""),"Delivered") -> Delivered | J68: =IFERROR(__xludf.DUMMYFUNCTION("""COMPUTED_VALUE"""),45812.40385416667) -> 45812.404
A69: =IFERROR(__xludf.DUMMYFUNCTION("""COMPUTED_VALUE"""),45811.201932870375) -> 45811.202 | B69: =IFERROR(__xludf.DUMMYFUNCTION("""COMPUTED_VALUE"""),"Nike black n white sports size 42") -> Nike black n white sports size 42 | C69: =IFERROR(__xludf.DUMMYFUNCTION("""COMPUTED_VALUE"""),"Mani Yadav") -> Mani Yadav | D69: =IFERROR(__xludf.DUMMYFUNCTION("""COMPUTED_VALUE"""),"Pokhariya nagarpalika, basanpur tole") -> Pokhariya nagarpalika, basanpur tole | E69: =IFERROR(__xludf.DUMMYFUNCTION("""COMPUTED_VALUE"""),9.805199354E9) -> 9805199354 | F69: =IFERROR(__xludf.DUMMYFUNCTION("""COMPUTED_VALUE"""),300.0) -> 300 | G69: =IFERROR(__xludf.DUMMYFUNCTION("""COMPUTED_VALUE"""),1300.0) -> 1300 | H69: =IFERROR(__xludf.DUMMYFUNCTION("""COMPUTED_VALUE"""),82.25) -> 82.25 | I69: =IFERROR(__xludf.DUMMYFUNCTION("""COMPUTED_VALUE"""),"Delivered") -> Delivered | J69: =IFERROR(__xludf.DUMMYFUNCTION("""COMPUTED_VALUE"""),45816.25824074074) -> 45816.258
A70: =IFERROR(__xludf.DUMMYFUNCTION("""COMPUTED_VALUE"""),45811.196504629625) -> 45811.196 | B70: =IFERROR(__xludf.DUMMYFUNCTION("""COMPUTED_VALUE"""),"Utsav shoes size 42") -> Utsav shoes size 42 | C70: =IFERROR(__xludf.DUMMYFUNCTION("""COMPUTED_VALUE"""),"Dipen khadka") -> Dipen khadka | D70: =IFERROR(__xludf.DUMMYFUNCTION("""COMPUTED_VALUE"""),"Bharatpur 21, parbatipur") -> Bharatpur 21, parbatipur | E70: =IFERROR(__xludf.DUMMYFUNCTION("""COMPUTED_VALUE"""),9.746280186E9) -> 9746280186 | F70: =IFERROR(__xludf.DUMMYFUNCTION("""COMPUTED_VALUE"""),500.0) -> 500 | G70: =IFERROR(__xludf.DUMMYFUNCTION("""COMPUTED_VALUE"""),1300.0) -> 1300 | H70: =IFERROR(__xludf.DUMMYFUNCTION("""COMPUTED_VALUE"""),82.25) -> 82.25 | I70: =IFERROR(__xludf.DUMMYFUNCTION("""COMPUTED_VALUE"""),"Delivered") -> Delivered | J70: =IFERROR(__xludf.DUMMYFUNCTION("""COMPUTED_VALUE"""),45816.42743055556) -> 45816.427
A71: =IFERROR(__xludf.DUMMYFUNCTION("""COMPUTED_VALUE"""),45811.19473379629) -> 45811.195 | B71: =IFERROR(__xludf.DUMMYFUNCTION("""COMPUTED_VALUE"""),"Tbl and vans size 43") -> Tbl and vans size 43 | C71: =IFERROR(__xludf.DUMMYFUNCTION("""COMPUTED_VALUE"""),"Tankeeyy") -> Tankeeyy | D71: =IFERROR(__xludf.DUMMYFUNCTION("""COMPUTED_VALUE"""),"Jantabasti pipal Chowk, itahari") -> Jantabasti pipal Chowk, itahari | E71: =IFERROR(__xludf.DUMMYFUNCTION("""COMPUTED_VALUE"""),9.709130886E9) -> 9709130886 | F71: =IFERROR(__xludf.DUMMYFUNCTION("""COMPUTED_VALUE"""),800.0) -> 800 | G71: =IFERROR(__xludf.DUMMYFUNCTION("""COMPUTED_VALUE"""),2400.0) -> 2400 | H71: =IFERROR(__xludf.DUMMYFUNCTION("""COMPUTED_VALUE"""),85.0) -> 85 | I71: =IFERROR(__xludf.DUMMYFUNCTION("""COMPUTED_VALUE"""),"Delivered") -> Delivered | J71: =IFERROR(__xludf.DUMMYFUNCTION("""COMPUTED_VALUE"""),45812.41483796296) -> 45812.415
A72: =IFERROR(__xludf.DUMMYFUNCTION("""COMPUTED_VALUE"""),45811.193402777775) -> 45811.193 | B72: =IFERROR(__xludf.DUMMYFUNCTION("""COMPUTED_VALUE"""),"Chelsea and Nike sr size 43") -> Chelsea and Nike sr size 43 | C72: =IFERROR(__xludf.DUMMYFUNCTION("""COMPUTED_VALUE"""),"Ajay pragyan") -> Ajay pragyan | D72: =IFERROR(__xludf.DUMMYFUNCTION("""COMPUTED_VALUE"""),"Gulmi, tamgash") -> Gulmi, tamgash | E72: =IFERROR(__xludf.DUMMYFUNCTION("""COMPUTED_VALUE"""),9.847532187E9) -> 9847532187 | F72: =IFERROR(__xludf.DUMMYFUNCTION("""COMPUTED_VALUE"""),500.0) -> 500 | G72: =IFERROR(__xludf.DUMMYFUNCTION("""COMPUTED_VALUE"""),2500.0) -> 2500 | H72: =IFERROR(__xludf.DUMMYFUNCTION("""COMPUTED_VALUE"""),85.25) -> 85.25 | I72: =IFERROR(__xludf.DUMMYFUNCTION("""COMPUTED_VALUE"""),"Delivered") -> Delivered | J72: =IFERROR(__xludf.DUMMYFUNCTION("""COMPUTED_VALUE"""),45813.353993055556) -> 45813.354
A73: =IFERROR(__xludf.DUMMYFUNCTION("""COMPUTED_VALUE"""),45811.19211805555) -> 45811.192 | B73: =IFERROR(__xludf.DUMMYFUNCTION("""COMPUTED_VALUE"""),"Dark brown size 41") -> Dark brown size 41 | C73: =IFERROR(__xludf.DUMMYFUNCTION("""COMPUTED_VALUE"""),"Alone boy") -> Alone boy | D73: =IFERROR(__xludf.DUMMYFUNCTION("""COMPUTED_VALUE"""),"Syangja, arjunchaupari") -> Syangja, arjunchaupari | E73: =IFERROR(__xludf.DUMMYFUNCTION("""COMPUTED_VALUE"""),9.703982249E9) -> 9703982249 | F73: =IFERROR(__xludf.DUMMYFUNCTION("""COMPUTED_VALUE"""),300.0) -> 300 | G73: =IFERROR(__xludf.DUMMYFUNCTION("""COMPUTED_VALUE"""),1300.0) -> 1300 | H73: =IFERROR(__xludf.DUMMYFUNCTION("""COMPUTED_VALUE"""),82.25) -> 82.25 | I73: =IFERROR(__xludf.DUMMYFUNCTION("""COMPUTED_VALUE"""),"Delivered") -> Delivered | J73: =IFERROR(__xludf.DUMMYFUNCTION("""COMPUTED_VALUE"""),45813.54565972222) -> 45813.546
A74: =IFERROR(__xludf.DUMMYFUNCTION("""COMPUTED_VALUE"""),45811.18950231481) -> 45811.19 | B74: =IFERROR(__xludf.DUMMYFUNCTION("""COMPUTED_VALUE"""),"Vans half shoes 40") -> Vans half shoes 40 | C74: =IFERROR(__xludf.DUMMYFUNCTION("""COMPUTED_VALUE"""),"Sabin pandey") -> Sabin pandey | D74: =IFERROR(__xludf.DUMMYFUNCTION("""COMPUTED_VALUE"""),"Morang, thydia") -> Morang, thydia | E74: =IFERROR(__xludf.DUMMYFUNCTION("""COMPUTED_VALUE"""),9.801992885E9) -> 9801992885 | F74: =IFERROR(__xludf.DUMMYFUNCTION("""COMPUTED_VALUE"""),700.0) -> 700 | G74: =IFERROR(__xludf.DUMMYFUNCTION("""COMPUTED_VALUE"""),1300.0) -> 1300 | H74: =IFERROR(__xludf.DUMMYFUNCTION("""COMPUTED_VALUE"""),82.25) -> 82.25 | I74: =IFERROR(__xludf.DUMMYFUNCTION("""COMPUTED_VALUE"""),"Delivered") -> Delivered | J74: =IFERROR(__xludf.DUMMYFUNCTION("""COMPUTED_VALUE"""),45812.50335648148) -> 45812.503
A75: =IFERROR(__xludf.DUMMYFUNCTION("""COMPUTED_VALUE"""),45808.16628472222) -> 45808.166 | B75: =IFERROR(__xludf.DUMMYFUNCTION("""COMPUTED_VALUE"""),"Samba shoes size 43") -> Samba shoes size 43 | C75: =IFERROR(__xludf.DUMMYFUNCTION("""COMPUTED_VALUE"""),"Sudip") -> Sudip | D75: =IFERROR(__xludf.DUMMYFUNCTION("""COMPUTED_VALUE"""),"Tokha road, nature club resataurant") -> Tokha road, nature club resataurant | E75: =IFERROR(__xludf.DUMMYFUNCTION("""COMPUTED_VALUE"""),9.867371428E9) -> 9867371428 | F75: =IFERROR(__xludf.DUMMYFUNCTION("""COMPUTED_VALUE"""),300.0) -> 300 | G75: =IFERROR(__xludf.DUMMYFUNCTION("""COMPUTED_VALUE"""),1300.0) -> 1300 | H75: =IFERROR(__xludf.DUMMYFUNCTION("""COMPUTED_VALUE"""),62.25) -> 62.25 | I75: =IFERROR(__xludf.DUMMYFUNCTION("""COMPUTED_VALUE"""),"Delivered") -> Delivered | J75: =IFERROR(__xludf.DUMMYFUNCTION("""COMPUTED_VALUE"""),45809.26428240741) -> 45809.264
A76: =IFERROR(__xludf.DUMMYFUNCTION("""COMPUTED_VALUE"""),45807.17722222222) -> 45807.177 | B76: =IFERROR(__xludf.DUMMYFUNCTION("""COMPUTED_VALUE"""),"Brown shoes size 41") -> Brown shoes size 41 | C76: =IFERROR(__xludf.DUMMYFUNCTION("""COMPUTED_VALUE"""),"Sukdev thapa") -> Sukdev thapa | D76: =IFERROR(__xludf.DUMMYFUNCTION("""COMPUTED_VALUE"""),"Dang lamahi") -> Dang lamahi | E76: =IFERROR(__xludf.DUMMYFUNCTION("""COMPUTED_VALUE"""),9.806230424E9) -> 9806230424 | F76: =IFERROR(__xludf.DUMMYFUNCTION("""COMPUTED_VALUE"""),300.0) -> 300 | G76: =IFERROR(__xludf.DUMMYFUNCTION("""COMPUTED_VALUE"""),1300.0) -> 1300 | H76: =IFERROR(__xludf.DUMMYFUNCTION("""COMPUTED_VALUE"""),82.25) -> 82.25 | I76: =IFERROR(__xludf.DUMMYFUNCTION("""COMPUTED_VALUE"""),"Delivered") -> Delivered | J76: =IFERROR(__xludf.DUMMYFUNCTION("""COMPUTED_VALUE"""),45810.61547453704) -> 45810.615
A77: =IFERROR(__xludf.DUMMYFUNCTION("""COMPUTED_VALUE"""),45807.17543981482) -> 45807.175 | B77: =IFERROR(__xludf.DUMMYFUNCTION("""COMPUTED_VALUE"""),"Utsav shoes size 42") -> Utsav shoes size 42 | C77: =IFERROR(__xludf.DUMMYFUNCTION("""COMPUTED_VALUE"""),"Nisan tamang") -> Nisan tamang | D77: =IFERROR(__xludf.DUMMYFUNCTION("""COMPUTED_VALUE"""),"Dhulabari") -> Dhulabari | E77: =IFERROR(__xludf.DUMMYFUNCTION("""COMPUTED_VALUE"""),9.764470296E9) -> 9764470296 | F77: =IFERROR(__xludf.DUMMYFUNCTION("""COMPUTED_VALUE"""),450.0) -> 450 | G77: =IFERROR(__xludf.DUMMYFUNCTION("""COMPUTED_VALUE"""),1250.0) -> 1250 | H77: =IFERROR(__xludf.DUMMYFUNCTION("""COMPUTED_VALUE"""),82.13) -> 82.13 | I77: =IFERROR(__xludf.DUMMYFUNCTION("""COMPUTED_VALUE"""),"Delivered") -> Delivered | J77: =IFERROR(__xludf.DUMMYFUNCTION("""COMPUTED_VALUE"""),45809.37590277778) -> 45809.376
A78: =IFERROR(__xludf.DUMMYFUNCTION("""COMPUTED_VALUE"""),45807.17444444445) -> 45807.174 | B78: =IFERROR(__xludf.DUMMYFUNCTION("""COMPUTED_VALUE"""),"Nike blue shoes and white size 41") -> Nike blue shoes and white size 41 | C78: =IFERROR(__xludf.DUMMYFUNCTION("""COMPUTED_VALUE"""),"Shree Krishna sapkota") -> Shree Krishna sapkota | D78: =IFERROR(__xludf.DUMMYFUNCTION("""COMPUTED_VALUE"""),"Beni bazzar, myagdi") -> Beni bazzar, myagdi | E78: =IFERROR(__xludf.DUMMYFUNCTION("""COMPUTED_VALUE"""),9.769477499E9) -> 9769477499 | F78: =IFERROR(__xludf.DUMMYFUNCTION("""COMPUTED_VALUE"""),400.0) -> 400 | G78: =IFERROR(__xludf.DUMMYFUNCTION("""COMPUTED_VALUE"""),2400.0) -> 2400 | H78: =IFERROR(__xludf.DUMMYFUNCTION("""COMPUTED_VALUE"""),85.0) -> 85 | I78: =IFERROR(__xludf.DUMMYFUNCTION("""COMPUTED_VALUE"""),"Delivered") -> Delivered | J78: =IFERROR(__xludf.DUMMYFUNCTION("""COMPUTED_VALUE"""),45813.280960648146) -> 45813.281
A79: =IFERROR(__xludf.DUMMYFUNCTION("""COMPUTED_VALUE"""),45806.75989583333) -> 45806.76 | B79: =IFERROR(__xludf.DUMMYFUNCTION("""COMPUTED_VALUE"""),"Sr shoes size 43") -> Sr shoes size 43 | C79: =IFERROR(__xludf.DUMMYFUNCTION("""COMPUTED_VALUE"""),"Samir kc") -> Samir kc | D79: =IFERROR(__xludf.DUMMYFUNCTION("""COMPUTED_VALUE""")," Location-thinthana,munalclub") -> Location-thinthana,munalclub | E79: =IFERROR(__xludf.DUMMYFUNCTION("""COMPUTED_VALUE"""),9.844821299E9) -> 9844821299 | F79: =IFERROR(__xludf.DUMMYFUNCTION("""COMPUTED_VALUE"""),300.0) -> 300 | G79: =IFERROR(__xludf.DUMMYFUNCTION("""COMPUTED_VALUE"""),1300.0) -> 1300 | H79: =IFERROR(__xludf.DUMMYFUNCTION("""COMPUTED_VALUE"""),62.25) -> 62.25 | I79: =IFERROR(__xludf.DUMMYFUNCTION("""COMPUTED_VALUE"""),"Delivered") -> Delivered | J79: =IFERROR(__xludf.DUMMYFUNCTION("""COMPUTED_VALUE"""),45808.42049768519) -> 45808.421
A80: =IFERROR(__xludf.DUMMYFUNCTION("""COMPUTED_VALUE"""),45806.44621527778) -> 45806.446 | B80: =IFERROR(__xludf.DUMMYFUNCTION("""COMPUTED_VALUE"""),"Lofer black size 39") -> Lofer black size 39 | C80: =IFERROR(__xludf.DUMMYFUNCTION("""COMPUTED_VALUE"""),"MD noore nabi") -> MD noore nabi | D80: =IFERROR(__xludf.DUMMYFUNCTION("""COMPUTED_VALUE"""),"Butwal, pharsatikar 4") -> Butwal, pharsatikar 4 | E80: =IFERROR(__xludf.DUMMYFUNCTION("""COMPUTED_VALUE"""),9.7047297E9) -> 9704729700 | F80: =IFERROR(__xludf.DUMMYFUNCTION("""COMPUTED_VALUE"""),500.0) -> 500 | G80: =IFERROR(__xludf.DUMMYFUNCTION("""COMPUTED_VALUE"""),1300.0) -> 1300 | H80: =IFERROR(__xludf.DUMMYFUNCTION("""COMPUTED_VALUE"""),82.25) -> 82.25 | I80: =IFERROR(__xludf.DUMMYFUNCTION("""COMPUTED_VALUE"""),"Delivered") -> Delivered | J80: =IFERROR(__xludf.DUMMYFUNCTION("""COMPUTED_VALUE"""),45809.487708333334) -> 45809.488
A81: =IFERROR(__xludf.DUMMYFUNCTION("""COMPUTED_VALUE"""),45806.440833333334) -> 45806.441 | C81: =IFERROR(__xludf.DUMMYFUNCTION("""COMPUTED_VALUE"""),"Bibek rai") -> Bibek rai | D81: =IFERROR(__xludf.DUMMYFUNCTION("""COMPUTED_VALUE"""),"Lalitpur, purna Chandi mandir ") -> Lalitpur, purna Chandi mandir | E81: =IFERROR(__xludf.DUMMYFUNCTION("""COMPUTED_VALUE"""),9.810065122E9) -> 9810065122 | F81: =IFERROR(__xludf.DUMMYFUNCTION("""COMPUTED_VALUE"""),260.0) -> 260 | G81: =IFERROR(__xludf.DUMMYFUNCTION("""COMPUTED_VALUE"""),1260.0) -> 1260 | H81: =IFERROR(__xludf.DUMMYFUNCTION("""COMPUTED_VALUE"""),3.15) -> 3.15 | I81: =IFERROR(__xludf.DUMMYFUNCTION("""COMPUTED_VALUE"""),"Delivered") -> Delivered | J81: =IFERROR(__xludf.DUMMYFUNCTION("""COMPUTED_VALUE"""),45807.21878472222) -> 45807.219
A82: =IFERROR(__xludf.DUMMYFUNCTION("""COMPUTED_VALUE"""),45806.43519675926) -> 45806.435 | B82: =IFERROR(__xludf.DUMMYFUNCTION("""COMPUTED_VALUE"""),"Brown Nike size 41") -> Brown Nike size 41 | C82: =IFERROR(__xludf.DUMMYFUNCTION("""COMPUTED_VALUE"""),"Nisan or jibika tamang") -> Nisan or jibika tamang | D82: =IFERROR(__xludf.DUMMYFUNCTION("""COMPUTED_VALUE"""),"Dhulabari") -> Dhulabari | E82: =IFERROR(__xludf.DUMMYFUNCTION("""COMPUTED_VALUE"""),9.764470296E9) -> 9764470296 | F82: =IFERROR(__xludf.DUMMYFUNCTION("""COMPUTED_VALUE"""),300.0) -> 300 | G82: =IFERROR(__xludf.DUMMYFUNCTION("""COMPUTED_VALUE"""),1300.0) -> 1300 | H82: =IFERROR(__xludf.DUMMYFUNCTION("""COMPUTED_VALUE"""),82.25) -> 82.25 | I82: =IFERROR(__xludf.DUMMYFUNCTION("""COMPUTED_VALUE"""),"Delivered") -> Delivered | J82: =IFERROR(__xludf.DUMMYFUNCTION("""COMPUTED_VALUE"""),45809.37627314815) -> 45809.376
A83: =IFERROR(__xludf.DUMMYFUNCTION("""COMPUTED_VALUE"""),45806.42952546296) -> 45806.43 | B83: =IFERROR(__xludf.DUMMYFUNCTION("""COMPUTED_VALUE"""),"Brown Nike of size 36") -> Brown Nike of size 36 | C83: =IFERROR(__xludf.DUMMYFUNCTION("""COMPUTED_VALUE"""),"Salin") -> Salin | D83: =IFERROR(__xludf.DUMMYFUNCTION("""COMPUTED_VALUE"""),"Dilli bazzar, ktm") -> Dilli bazzar, ktm | E83: =IFERROR(__xludf.DUMMYFUNCTION("""COMPUTED_VALUE"""),9.847148778E9) -> 9847148778 | F83: =IFERROR(__xludf.DUMMYFUNCTION("""COMPUTED_VALUE"""),300.0) -> 300 | G83: =IFERROR(__xludf.DUMMYFUNCTION("""COMPUTED_VALUE"""),1300.0) -> 1300 | H83: =IFERROR(__xludf.DUMMYFUNCTION("""COMPUTED_VALUE"""),3.25) -> 3.25 | I83: =IFERROR(__xludf.DUMMYFUNCTION("""COMPUTED_VALUE"""),"Delivered") -> Delivered | J83: =IFERROR(__xludf.DUMMYFUNCTION("""COMPUTED_VALUE"""),45807.29958333333) -> 45807.3
A84: =IFERROR(__xludf.DUMMYFUNCTION("""COMPUTED_VALUE"""),45806.188692129625) -> 45806.189 | B84: =IFERROR(__xludf.DUMMYFUNCTION("""COMPUTED_VALUE"""),"Vans shoes size 37") -> Vans shoes size 37 | C84: =IFERROR(__xludf.DUMMYFUNCTION("""COMPUTED_VALUE"""),"Bikash chaulagain") -> Bikash chaulagain | D84: =IFERROR(__xludf.DUMMYFUNCTION("""COMPUTED_VALUE"""),"Kalikot tadi") -> Kalikot tadi | E84: =IFERROR(__xludf.DUMMYFUNCTION("""COMPUTED_VALUE"""),9.76545561E9) -> 9765455610 | F84: =IFERROR(__xludf.DUMMYFUNCTION("""COMPUTED_VALUE"""),0.0) -> 0 | G84: =IFERROR(__xludf.DUMMYFUNCTION("""COMPUTED_VALUE"""),1300.0) -> 1300 | H84: =IFERROR(__xludf.DUMMYFUNCTION("""COMPUTED_VALUE"""),82.25) -> 82.25 | I84: =IFERROR(__xludf.DUMMYFUNCTION("""COMPUTED_VALUE"""),"Delivered") -> Delivered | J84: =IFERROR(__xludf.DUMMYFUNCTION("""COMPUTED_VALUE"""),45809.5961574074) -> 45809.596
A85: =IFERROR(__xludf.DUMMYFUNCTION("""COMPUTED_VALUE"""),45806.185381944444) -> 45806.185 | B85: =IFERROR(__xludf.DUMMYFUNCTION("""COMPUTED_VALUE"""),"White shoes size 43") -> White shoes size 43 | C85: =IFERROR(__xludf.DUMMYFUNCTION("""COMPUTED_VALUE"""),"Nabin") -> Nabin | D85: =IFERROR(__xludf.DUMMYFUNCTION("""COMPUTED_VALUE"""),"Bhaktapur duwakot near kmc hospital") -> Bhaktapur duwakot near kmc hospital | E85: =IFERROR(__xludf.DUMMYFUNCTION("""COMPUTED_VALUE"""),9.849083465E9) -> 9849083465 | F85: =IFERROR(__xludf.DUMMYFUNCTION("""COMPUTED_VALUE"""),300.0) -> 300 | G85: =IFERROR(__xludf.DUMMYFUNCTION("""COMPUTED_VALUE"""),1300.0) -> 1300 | H85: =IFERROR(__xludf.DUMMYFUNCTION("""COMPUTED_VALUE"""),3.25) -> 3.25 | I85: =IFERROR(__xludf.DUMMYFUNCTION("""COMPUTED_VALUE"""),"Delivered") -> Delivered | J85: =IFERROR(__xludf.DUMMYFUNCTION("""COMPUTED_VALUE"""),45806.49050925926) -> 45806.491
A86: =IFERROR(__xludf.DUMMYFUNCTION("""COMPUTED_VALUE"""),45806.18256944444) -> 45806.183 | B86: =IFERROR(__xludf.DUMMYFUNCTION("""COMPUTED_VALUE"""),"Sr shoes size 39") -> Sr shoes size 39 | C86: =IFERROR(__xludf.DUMMYFUNCTION("""COMPUTED_VALUE"""),"Siddharth") -> Siddharth | D86: =IFERROR(__xludf.DUMMYFUNCTION("""COMPUTED_VALUE"""),"PepsiCola kapur garden, ktm") -> PepsiCola kapur garden, ktm | E86: =IFERROR(__xludf.DUMMYFUNCTION("""COMPUTED_VALUE"""),9.865111985E9) -> 9865111985 | F86: =IFERROR(__xludf.DUMMYFUNCTION("""COMPUTED_VALUE"""),260.0) -> 260 | G86: =IFERROR(__xludf.DUMMYFUNCTION("""COMPUTED_VALUE"""),1260.0) -> 1260 | H86: =IFERROR(__xludf.DUMMYFUNCTION("""COMPUTED_VALUE"""),3.15) -> 3.15 | I86: =IFERROR(__xludf.DUMMYFUNCTION("""COMPUTED_VALUE"""),"Delivered") -> Delivered | J86: =IFERROR(__xludf.DUMMYFUNCTION("""COMPUTED_VALUE"""),45806.51385416667) -> 45806.514
A87: =IFERROR(__xludf.DUMMYFUNCTION("""COMPUTED_VALUE"""),45806.17908564815) -> 45806.179 | B87: =IFERROR(__xludf.DUMMYFUNCTION("""COMPUTED_VALUE"""),"Samba shoes size 37") -> Samba shoes size 37 | C87: =IFERROR(__xludf.DUMMYFUNCTION("""COMPUTED_VALUE"""),"Jenny kumal") -> Jenny kumal | D87: =IFERROR(__xludf.DUMMYFUNCTION("""COMPUTED_VALUE"""),"Kushma parbat") -> Kushma parbat | E87: =IFERROR(__xludf.DUMMYFUNCTION("""COMPUTED_VALUE"""),9.805122929E9) -> 9805122929 | F87: =IFERROR(__xludf.DUMMYFUNCTION("""COMPUTED_VALUE"""),300.0) -> 300 | G87: =IFERROR(__xludf.DUMMYFUNCTION("""COMPUTED_VALUE"""),1300.0) -> 1300 | H87: =IFERROR(__xludf.DUMMYFUNCTION("""COMPUTED_VALUE"""),82.25) -> 82.25 | I87: =IFERROR(__xludf.DUMMYFUNCTION("""COMPUTED_VALUE"""),"Delivered") -> Delivered | J87: =IFERROR(__xludf.DUMMYFUNCTION("""COMPUTED_VALUE"""),45813.317291666666) -> 45813.317
A88: =IFERROR(__xludf.DUMMYFUNCTION("""COMPUTED_VALUE"""),45806.17574074074) -> 45806.176 | B88: =IFERROR(__xludf.DUMMYFUNCTION("""COMPUTED_VALUE"""),"Dr. Martin single sole size 41") -> Dr. Martin single sole size 41 | C88: =IFERROR(__xludf.DUMMYFUNCTION("""COMPUTED_VALUE"""),"Ram karki") -> Ram karki | D88: =IFERROR(__xludf.DUMMYFUNCTION("""COMPUTED_VALUE"""),"Bhojpur") -> Bhojpur | E88: =IFERROR(__xludf.DUMMYFUNCTION("""COMPUTED_VALUE"""),9.864549595E9) -> 9864549595 | F88: =IFERROR(__xludf.DUMMYFUNCTION("""COMPUTED_VALUE"""),300.0) -> 300 | G88: =IFERROR(__xludf.DUMMYFUNCTION("""COMPUTED_VALUE"""),1300.0) -> 1300 | H88: =IFERROR(__xludf.DUMMYFUNCTION("""COMPUTED_VALUE"""),82.25) -> 82.25 | I88: =IFERROR(__xludf.DUMMYFUNCTION("""COMPUTED_VALUE"""),"Delivered") -> Delivered | J88: =IFERROR(__xludf.DUMMYFUNCTION("""COMPUTED_VALUE"""),45809.59614583333) -> 45809.596
A89: =IFERROR(__xludf.DUMMYFUNCTION("""COMPUTED_VALUE"""),45806.172673611116) -> 45806.173 | B89: =IFERROR(__xludf.DUMMYFUNCTION("""COMPUTED_VALUE"""),"Sport shoes Nike waterproof size 42") -> Sport shoes Nike waterproof size 42 | C89: =IFERROR(__xludf.DUMMYFUNCTION("""COMPUTED_VALUE"""),"Dil Bahadur pariyar") -> Dil Bahadur pariyar | D89: =IFERROR(__xludf.DUMMYFUNCTION("""COMPUTED_VALUE"""),"Pokhara 18, besitol near baglung buspark") -> Pokhara 18, besitol near baglung buspark | E89: =IFERROR(__xludf.DUMMYFUNCTION("""COMPUTED_VALUE"""),9.805885012E9) -> 9805885012 | F89: =IFERROR(__xludf.DUMMYFUNCTION("""COMPUTED_VALUE"""),300.0) -> 300 | G89: =IFERROR(__xludf.DUMMYFUNCTION("""COMPUTED_VALUE"""),1300.0) -> 1300 | H89: =IFERROR(__xludf.DUMMYFUNCTION("""COMPUTED_VALUE"""),82.25) -> 82.25 | I89: =IFERROR(__xludf.DUMMYFUNCTION("""COMPUTED_VALUE"""),"Delivered") -> Delivered | J89: =IFERROR(__xludf.DUMMYFUNCTION("""COMPUTED_VALUE"""),45807.33319444444) -> 45807.333
A90: =IFERROR(__xludf.DUMMYFUNCTION("""COMPUTED_VALUE"""),45785.089317129634) -> 45785.089 | B90: =IFERROR(__xludf.DUMMYFUNCTION("""COMPUTED_VALUE"""),"Red jordan") -> Red jordan | C90: =IFERROR(__xludf.DUMMYFUNCTION("""COMPUTED_VALUE"""),"Aditya mukhiya bin") -> Aditya mukhiya bin | D90: =IFERROR(__xludf.DUMMYFUNCTION("""COMPUTED_VALUE"""),"Mmc college road, manakamana chowk, hetauda") -> Mmc college road, manakamana chowk, hetauda | E90: =IFERROR(__xludf.DUMMYFUNCTION("""COMPUTED_VALUE"""),9.704578101E9) -> 9704578101 | F90: =IFERROR(__xludf.DUMMYFUNCTION("""COMPUTED_VALUE"""),200.0) -> 200 | G90: =IFERROR(__xludf.DUMMYFUNCTION("""COMPUTED_VALUE"""),1200.0) -> 1200 | H90: =IFERROR(__xludf.DUMMYFUNCTION("""COMPUTED_VALUE"""),3.0) -> 3 | I90: =IFERROR(__xludf.DUMMYFUNCTION("""COMPUTED_VALUE"""),"Delivered") -> Delivered | J90: =IFERROR(__xludf.DUMMYFUNCTION("""COMPUTED_VALUE"""),45786.363078703704) -> 45786.363
A91: =IFERROR(__xludf.DUMMYFUNCTION("""COMPUTED_VALUE"""),45785.08814814815) -> 45785.088 | B91: =IFERROR(__xludf.DUMMYFUNCTION("""COMPUTED_VALUE"""),"Maroon full Jordan of size 42") -> Maroon full Jordan of size 42 | C91: =IFERROR(__xludf.DUMMYFUNCTION("""COMPUTED_VALUE"""),"Dany") -> Dany | D91: =IFERROR(__xludf.DUMMYFUNCTION("""COMPUTED_VALUE"""),"Katari, udayapur") -> Katari, udayapur | E91: =IFERROR(__xludf.DUMMYFUNCTION("""COMPUTED_VALUE"""),9.708876627E9) -> 9708876627 | F91: =IFERROR(__xludf.DUMMYFUNCTION("""COMPUTED_VALUE"""),200.0) -> 200 | G91: =IFERROR(__xludf.DUMMYFUNCTION("""COMPUTED_VALUE"""),1200.0) -> 1200 | H91: =IFERROR(__xludf.DUMMYFUNCTION("""COMPUTED_VALUE"""),3.0) -> 3 | I91: =IFERROR(__xludf.DUMMYFUNCTION("""COMPUTED_VALUE"""),"Delivered") -> Delivered | J91: =IFERROR(__xludf.DUMMYFUNCTION("""COMPUTED_VALUE"""),45790.40101851852) -> 45790.401
A92: =IFERROR(__xludf.DUMMYFUNCTION("""COMPUTED_VALUE"""),45782.225543981476) -> 45782.226 | B92: =IFERROR(__xludf.DUMMYFUNCTION("""COMPUTED_VALUE"""),"Red full Jordan and white Nike of size 41 costing RS. 1200 each") -> Red full Jordan and white Nike of size 41 costing RS. 1200 each | C92: =IFERROR(__xludf.DUMMYFUNCTION("""COMPUTED_VALUE"""),"Arman Kapar") -> Arman Kapar | D92: =IFERROR(__xludf.DUMMYFUNCTION("""COMPUTED_VALUE"""),"Gyanseshwor Chowk opposite of German embassy") -> Gyanseshwor Chowk opposite of German embassy | E92: =IFERROR(__xludf.DUMMYFUNCTION("""COMPUTED_VALUE"""),9.813149928E9) -> 9813149928 | F92: =IFERROR(__xludf.DUMMYFUNCTION("""COMPUTED_VALUE"""),400.0) -> 400 | G92: =IFERROR(__xludf.DUMMYFUNCTION("""COMPUTED_VALUE"""),2400.0) -> 2400 | H92: =IFERROR(__xludf.DUMMYFUNCTION("""COMPUTED_VALUE"""),6.0) -> 6 | I92: =IFERROR(__xludf.DUMMYFUNCTION("""COMPUTED_VALUE"""),"Delivered") -> Delivered | J92: =IFERROR(__xludf.DUMMYFUNCTION("""COMPUTED_VALUE"""),45783.21871527778) -> 45783.219
A93: =IFERROR(__xludf.DUMMYFUNCTION("""COMPUTED_VALUE"""),45782.1949537037) -> 45782.195 | B93: =IFERROR(__xludf.DUMMYFUNCTION("""COMPUTED_VALUE"""),"Sb dunk low pro of size 42 costing RS. 1200") -> Sb dunk low pro of size 42 costing RS. 1200 | C93: =IFERROR(__xludf.DUMMYFUNCTION("""COMPUTED_VALUE"""),"Iman Panta") -> Iman Panta | D93: =IFERROR(__xludf.DUMMYFUNCTION("""COMPUTED_VALUE"""),"Dungedhara-16, basanthali") -> Dungedhara-16, basanthali | E93: =IFERROR(__xludf.DUMMYFUNCTION("""COMPUTED_VALUE"""),9.709300431E9) -> 9709300431 | F93: =IFERROR(__xludf.DUMMYFUNCTION("""COMPUTED_VALUE"""),200.0) -> 200 | G93: =IFERROR(__xludf.DUMMYFUNCTION("""COMPUTED_VALUE"""),1200.0) -> 1200 | H93: =IFERROR(__xludf.DUMMYFUNCTION("""COMPUTED_VALUE"""),3.0) -> 3 | I93: =IFERROR(__xludf.DUMMYFUNCTION("""COMPUTED_VALUE"""),"Delivered") -> Delivered | J93: =IFERROR(__xludf.DUMMYFUNCTION("""COMPUTED_VALUE"""),45782.53430555556) -> 45782.534
A94: =IFERROR(__xludf.DUMMYFUNCTION("""COMPUTED_VALUE"""),45782.15113425926) -> 45782.151 | B94: =IFERROR(__xludf.DUMMYFUNCTION("""COMPUTED_VALUE"""),"Black Nike shoes of size 43 costing RS. 1200") -> Black Nike shoes of size 43 costing RS. 1200 | C94: =IFERROR(__xludf.DUMMYFUNCTION("""COMPUTED_VALUE"""),"Roshan Rajbanshi") -> Roshan Rajbanshi | D94: =IFERROR(__xludf.DUMMYFUNCTION("""COMPUTED_VALUE"""),"Kakarvitta( Mechinagar-7, satighatta)") -> Kakarvitta( Mechinagar-7, satighatta) | E94: =IFERROR(__xludf.DUMMYFUNCTION("""COMPUTED_VALUE"""),9.807919104E9) -> 9807919104 | F94: =IFERROR(__xludf.DUMMYFUNCTION("""COMPUTED_VALUE"""),200.0) -> 200 | G94: =IFERROR(__xludf.DUMMYFUNCTION("""COMPUTED_VALUE"""),1200.0) -> 1200 | H94: =IFERROR(__xludf.DUMMYFUNCTION("""COMPUTED_VALUE"""),3.0) -> 3 | I94: =IFERROR(__xludf.DUMMYFUNCTION("""COMPUTED_VALUE"""),"Delivered") -> Delivered | J94: =IFERROR(__xludf.DUMMYFUNCTION("""COMPUTED_VALUE"""),45785.47127314815) -> 45785.471
A95: =IFERROR(__xludf.DUMMYFUNCTION("""COMPUTED_VALUE"""),45782.14842592593) -> 45782.148 | B95: =IFERROR(__xludf.DUMMYFUNCTION("""COMPUTED_VALUE"""),"Chocolaty Nike and black tbl of size 43 costing RS 1200 each") -> Chocolaty Nike and black tbl of size 43 costing RS 1200 each | C95: =IFERROR(__xludf.DUMMYFUNCTION("""COMPUTED_VALUE"""),"Marco Kapali") -> Marco Kapali | D95: =IFERROR(__xludf.DUMMYFUNCTION("""COMPUTED_VALUE"""),"Thankoat") -> Thankoat | E95: =IFERROR(__xludf.DUMMYFUNCTION("""COMPUTED_VALUE"""),9.741759216E9) -> 9741759216 | F95: =IFERROR(__xludf.DUMMYFUNCTION("""COMPUTED_VALUE"""),400.0) -> 400 | G95: =IFERROR(__xludf.DUMMYFUNCTION("""COMPUTED_VALUE"""),2400.0) -> 2400 | H95: =IFERROR(__xludf.DUMMYFUNCTION("""COMPUTED_VALUE"""),6.0) -> 6 | I95: =IFERROR(__xludf.DUMMYFUNCTION("""COMPUTED_VALUE"""),"Delivered") -> Delivered | J95: =IFERROR(__xludf.DUMMYFUNCTION("""COMPUTED_VALUE"""),45783.400925925926) -> 45783.401
A96: =IFERROR(__xludf.DUMMYFUNCTION("""COMPUTED_VALUE"""),45781.22458333333) -> 45781.225 | B96: =IFERROR(__xludf.DUMMYFUNCTION("""COMPUTED_VALUE"""),"Veins size 40 costing RS. 1200") -> Veins size 40 costing RS. 1200 | C96: =IFERROR(__xludf.DUMMYFUNCTION("""COMPUTED_VALUE"""),"Amit Magar") -> Amit Magar | D96: =IFERROR(__xludf.DUMMYFUNCTION("""COMPUTED_VALUE"""),"Dharan, bhanuchowk") -> Dharan, bhanuchowk | E96: =IFERROR(__xludf.DUMMYFUNCTION("""COMPUTED_VALUE"""),9.84940118E9) -> 9849401180 | F96: =IFERROR(__xludf.DUMMYFUNCTION("""COMPUTED_VALUE"""),600.0) -> 600 | G96: =IFERROR(__xludf.DUMMYFUNCTION("""COMPUTED_VALUE"""),1200.0) -> 1200 | H96: =IFERROR(__xludf.DUMMYFUNCTION("""COMPUTED_VALUE"""),3.0) -> 3 | I96: =IFERROR(__xludf.DUMMYFUNCTION("""COMPUTED_VALUE"""),"Delivered") -> Delivered | J96: =IFERROR(__xludf.DUMMYFUNCTION("""COMPUTED_VALUE"""),45783.40699074074) -> 45783.407
A97: =IFERROR(__xludf.DUMMYFUNCTION("""COMPUTED_VALUE"""),45781.123831018514) -> 45781.124 | B97: =IFERROR(__xludf.DUMMYFUNCTION("""COMPUTED_VALUE"""),"Jordan blue of size 43 and as well sb dunk low pro of size 42 costing RS. 1200 each") -> Jordan blue of size 43 and as well sb dunk low pro of size 42 costing RS. 1200 each | C97: =IFERROR(__xludf.DUMMYFUNCTION("""COMPUTED_VALUE"""),"Arman Kapar") -> Arman Kapar | D97: =IFERROR(__xludf.DUMMYFUNCTION("""COMPUTED_VALUE"""),"Gyaneshwor chowk") -> Gyaneshwor chowk | E97: =IFERROR(__xludf.DUMMYFUNCTION("""COMPUTED_VALUE"""),9.813149928E9) -> 9813149928 | F97: =IFERROR(__xludf.DUMMYFUNCTION("""COMPUTED_VALUE"""),0.0) -> 0 | G97: =IFERROR(__xludf.DUMMYFUNCTION("""COMPUTED_VALUE"""),0.0) -> 0 | H97: =IFERROR(__xludf.DUMMYFUNCTION("""COMPUTED_VALUE"""),0.0) -> 0 | I97: =IFERROR(__xludf.DUMMYFUNCTION("""COMPUTED_VALUE"""),"Delivered") -> Delivered | J97: =IFERROR(__xludf.DUMMYFUNCTION("""COMPUTED_VALUE"""),45781.425162037034) -> 45781.425
A98: =IFERROR(__xludf.DUMMYFUNCTION("""COMPUTED_VALUE"""),45780.74403935185) -> 45780.744 | B98: =IFERROR(__xludf.DUMMYFUNCTION("""COMPUTED_VALUE"""),"Jordan Vietnam red shoes and sb dunk low pro blue of size 42 costing RS. 1200 each") -> Jordan Vietnam red shoes and sb dunk low pro blue of size 42 costing RS. 1200 each | C98: =IFERROR(__xludf.DUMMYFUNCTION("""COMPUTED_VALUE"""),"Dany") -> Dany | D98: =IFERROR(__xludf.DUMMYFUNCTION("""COMPUTED_VALUE"""),"Katari, udayapur") -> Katari, udayapur | E98: =IFERROR(__xludf.DUMMYFUNCTION("""COMPUTED_VALUE"""),9.708876627E9) -> 9708876627 | F98: =IFERROR(__xludf.DUMMYFUNCTION("""COMPUTED_VALUE"""),200.0) -> 200 | G98: =IFERROR(__xludf.DUMMYFUNCTION("""COMPUTED_VALUE"""),1200.0) -> 1200 | H98: =IFERROR(__xludf.DUMMYFUNCTION("""COMPUTED_VALUE"""),3.0) -> 3 | I98: =IFERROR(__xludf.DUMMYFUNCTION("""COMPUTED_VALUE"""),"Delivered") -> Delivered | J98: =IFERROR(__xludf.DUMMYFUNCTION("""COMPUTED_VALUE"""),45785.37040509259) -> 45785.37
A99: =IFERROR(__xludf.DUMMYFUNCTION("""COMPUTED_VALUE"""),45780.16887731482) -> 45780.169 | B99: =IFERROR(__xludf.DUMMYFUNCTION("""COMPUTED_VALUE"""),"Vans shoes of size 40") -> Vans shoes of size 40 | C99: =IFERROR(__xludf.DUMMYFUNCTION("""COMPUTED_VALUE"""),"Madan Khanal") -> Madan Khanal | D99: =IFERROR(__xludf.DUMMYFUNCTION("""COMPUTED_VALUE"""),"Milanchowk, butwal") -> Milanchowk, butwal | E99: =IFERROR(__xludf.DUMMYFUNCTION("""COMPUTED_VALUE"""),9.844821643E9) -> 9844821643 | F99: =IFERROR(__xludf.DUMMYFUNCTION("""COMPUTED_VALUE"""),600.0) -> 600 | G99: =IFERROR(__xludf.DUMMYFUNCTION("""COMPUTED_VALUE"""),1200.0) -> 1200 | H99: =IFERROR(__xludf.DUMMYFUNCTION("""COMPUTED_VALUE"""),3.0) -> 3 | I99: =IFERROR(__xludf.DUMMYFUNCTION("""COMPUTED_VALUE"""),"Delivered") -> Delivered | J99: =IFERROR(__xludf.DUMMYFUNCTION("""COMPUTED_VALUE"""),45783.40759259259) -> 45783.408
A100: =IFERROR(__xludf.DUMMYFUNCTION("""COMPUTED_VALUE"""),45780.13763888889) -> 45780.138 | B100: =IFERROR(__xludf.DUMMYFUNCTION("""COMPUTED_VALUE"""),"Black Nike of size 41 costing RS 1200") -> Black Nike of size 41 costing RS 1200 | C100: =IFERROR(__xludf.DUMMYFUNCTION("""COMPUTED_VALUE"""),"Tarzan Chhantyal") -> Tarzan Chhantyal | D100: =IFERROR(__xludf.DUMMYFUNCTION("""COMPUTED_VALUE"""),"Dilu beauty parlour, tokha") -> Dilu beauty parlour, tokha | E100: =IFERROR(__xludf.DUMMYFUNCTION("""COMPUTED_VALUE"""),9.808462623E9) -> 9808462623 | F100: =IFERROR(__xludf.DUMMYFUNCTION("""COMPUTED_VALUE"""),200.0) -> 200 | G100: =IFERROR(__xludf.DUMMYFUNCTION("""COMPUTED_VALUE"""),1200.0) -> 1200 | H100: =IFERROR(__xludf.DUMMYFUNCTION("""COMPUTED_VALUE"""),3.0) -> 3 | I100: =IFERROR(__xludf.DUMMYFUNCTION("""COMPUTED_VALUE"""),"Delivered") -> Delivered | J100: =IFERROR(__xludf.DUMMYFUNCTION("""COMPUTED_VALUE"""),45780.549363425926) -> 45780.549
...

Sheet delievered
B2: =IFERROR(__xludf.DUMMYFUNCTION("QUERY(reference!A1:J188, ""where I = 'Delivered'"", 1)"),"Order created at") -> Order created at | C2: =IFERROR(__xludf.DUMMYFUNCTION("""COMPUTED_VALUE"""),"Order description") -> Order description | D2: =IFERROR(__xludf.DUMMYFUNCTION("""COMPUTED_VALUE"""),"Recipient name") -> Recipient name | E2: =IFERROR(__xludf.DUMMYFUNCTION("""COMPUTED_VALUE"""),"Recipient address") -> Recipient address | F2: =IFERROR(__xludf.DUMMYFUNCTION("""COMPUTED_VALUE"""),"Recipient phone") -> Recipient phone | G2: =IFERROR(__xludf.DUMMYFUNCTION("""COMPUTED_VALUE"""),"proft") -> proft | H2: =IFERROR(__xludf.DUMMYFUNCTION("""COMPUTED_VALUE"""),"Collected amount") -> Collected amount | I2: =IFERROR(__xludf.DUMMYFUNCTION("""COMPUTED_VALUE"""),"Total fee") -> Total fee | J2: =IFERROR(__xludf.DUMMYFUNCTION("""COMPUTED_VALUE"""),"Order status") -> Order status | K2: =IFERROR(__xludf.DUMMYFUNCTION("""COMPUTED_VALUE"""),"Order status") -> Order status | L2: Tierwise | M2: Province
B3: =IFERROR(__xludf.DUMMYFUNCTION("""COMPUTED_VALUE"""),45916.191412037035) -> 45916.191 | C3: =IFERROR(__xludf.DUMMYFUNCTION("""COMPUTED_VALUE"""),"Martin 2 sole half ") -> Martin 2 sole half | D3: =IFERROR(__xludf.DUMMYFUNCTION("""COMPUTED_VALUE"""),"Amit Magar") -> Amit Magar | E3: =IFERROR(__xludf.DUMMYFUNCTION("""COMPUTED_VALUE"""),"Dharan, bhanu chowk ") -> Dharan, bhanu chowk | F3: =IFERROR(__xludf.DUMMYFUNCTION("""COMPUTED_VALUE"""),9.84940118E9) -> 9849401180 | G3: =IFERROR(__xludf.DUMMYFUNCTION("""COMPUTED_VALUE"""),350.0) -> 350 | H3: =IFERROR(__xludf.DUMMYFUNCTION("""COMPUTED_VALUE"""),1350.0) -> 1350 | I3: =IFERROR(__xludf.DUMMYFUNCTION("""COMPUTED_VALUE"""),162.38) -> 162.38 | J3: =IFERROR(__xludf.DUMMYFUNCTION("""COMPUTED_VALUE"""),"Delivered") -> Delivered | K3: =IFERROR(__xludf.DUMMYFUNCTION("""COMPUTED_VALUE"""),45918.31509259259) -> 45918.315 | L3: =IFERROR(__xludf.DUMMYFUNCTION("IFS( OR(REGEXMATCH(LOWER(E3), ""sirutar|sundarijal|sitapaila|duwakot|tikathali|bhaktapur|lalitpur|kathmandu|ktm|changunarayan|bageswari|ghalate|tinkune|balkot|tikathali""), REGEXMATCH(LOWER(E3), ""inside valley"")), ""Inside Valley"", REGEXMATCH(LOWER"&"(E3), ""dharan|pokhara|biratnagar|birgunj|narayanghat|itahari|hetauda|janakpur|madi""), ""Tier 1"", REGEXMATCH(LOWER(E3), ""nepalgunj|butwal|birtamod|dhangadhi|ghorahi|beni|kushma|waling|haldibari|dulegauda|baitadi|bhadrapur|syangja|parbat|myagdi|dang|n"&"uwakot|jhapa""), ""Tier 2"", TRUE, ""Tier 3"" )"),"Tier 1") -> Tier 1 | M3: Koshi
B4: =IFERROR(__xludf.DUMMYFUNCTION("""COMPUTED_VALUE"""),45916.18975694444) -> 45916.19 | C4: =IFERROR(__xludf.DUMMYFUNCTION("""COMPUTED_VALUE"""),"N and red 37 and 40") -> N and red 37 and 40 | D4: =IFERROR(__xludf.DUMMYFUNCTION("""COMPUTED_VALUE"""),"Prabin karki") -> Prabin karki | E4: =IFERROR(__xludf.DUMMYFUNCTION("""COMPUTED_VALUE"""),"Solukhumbu tingla") -> Solukhumbu tingla | F4: =IFERROR(__xludf.DUMMYFUNCTION("""COMPUTED_VALUE"""),9.749215487E9) -> 9749215487 | G4: =IFERROR(__xludf.DUMMYFUNCTION("""COMPUTED_VALUE"""),450.0) -> 450 | H4: =IFERROR(__xludf.DUMMYFUNCTION("""COMPUTED_VALUE"""),2550.0) -> 2550 | I4: =IFERROR(__xludf.DUMMYFUNCTION("""COMPUTED_VALUE"""),215.38) -> 215.38 | J4: =IFERROR(__xludf.DUMMYFUNCTION("""COMPUTED_VALUE"""),"Delivered") -> Delivered | K4: =IFERROR(__xludf.DUMMYFUNCTION("""COMPUTED_VALUE"""),45919.61679398148) -> 45919.617 | L4: =IFERROR(__xludf.DUMMYFUNCTION("IFS( OR(REGEXMATCH(LOWER(E4), ""sirutar|sundarijal|sitapaila|duwakot|tikathali|bhaktapur|lalitpur|kathmandu|ktm|changunarayan|bageswari|ghalate|tinkune|balkot|tikathali""), REGEXMATCH(LOWER(E4), ""inside valley"")), ""Inside Valley"", REGEXMATCH(LOWER"&"(E4), ""dharan|pokhara|biratnagar|birgunj|narayanghat|itahari|hetauda|janakpur|madi""), ""Tier 1"", REGEXMATCH(LOWER(E4), ""nepalgunj|butwal|birtamod|dhangadhi|ghorahi|beni|kushma|waling|haldibari|dulegauda|baitadi|bhadrapur|syangja|parbat|myagdi|dang|n"&"uwakot|jhapa""), ""Tier 2"", TRUE, ""Tier 3"" )"),"Tier 3") -> Tier 3 | M4: Koshi | N4: Province | O4: Tier 1 | P4: Tier 2 | Q4: Tier 3 | R4: Total
B5: =IFERROR(__xludf.DUMMYFUNCTION("""COMPUTED_VALUE"""),45894.19651620371) -> 45894.197 | C5: =IFERROR(__xludf.DUMMYFUNCTION("""COMPUTED_VALUE"""),"Martin 1 sole 36") -> Martin 1 sole 36 | D5: =IFERROR(__xludf.DUMMYFUNCTION("""COMPUTED_VALUE"""),"Manoj") -> Manoj | E5: =IFERROR(__xludf.DUMMYFUNCTION("""COMPUTED_VALUE"""),"Sundarijal, ktm dobato chowk") -> Sundarijal, ktm dobato chowk | F5: =IFERROR(__xludf.DUMMYFUNCTION("""COMPUTED_VALUE"""),9.768966994E9) -> 9768966994 | G5: =IFERROR(__xludf.DUMMYFUNCTION("""COMPUTED_VALUE"""),300.0) -> 300 | H5: =IFERROR(__xludf.DUMMYFUNCTION("""COMPUTED_VALUE"""),1100.0) -> 1100 | I5: =IFERROR(__xludf.DUMMYFUNCTION("""COMPUTED_VALUE"""),101.75) -> 101.75 | J5: =IFERROR(__xludf.DUMMYFUNCTION("""COMPUTED_VALUE"""),"Delivered") -> Delivered | K5: =IFERROR(__xludf.DUMMYFUNCTION("""COMPUTED_VALUE"""),45894.44189814814) -> 45894.442 | L5: =IFERROR(__xludf.DUMMYFUNCTION("IFS( OR(REGEXMATCH(LOWER(E5), ""sirutar|sundarijal|sitapaila|duwakot|tikathali|bhaktapur|lalitpur|kathmandu|ktm|changunarayan|bageswari|ghalate|tinkune|balkot|tikathali""), REGEXMATCH(LOWER(E5), ""inside valley"")), ""Inside Valley"", REGEXMATCH(LOWER"&"(E5), ""dharan|pokhara|biratnagar|birgunj|narayanghat|itahari|hetauda|janakpur|madi""), ""Tier 1"", REGEXMATCH(LOWER(E5), ""nepalgunj|butwal|birtamod|dhangadhi|ghorahi|beni|kushma|waling|haldibari|dulegauda|baitadi|bhadrapur|syangja|parbat|myagdi|dang|n"&"uwakot|jhapa""), ""Tier 2"", TRUE, ""Tier 3"" )"),"Inside Valley") -> Inside Valley | M5: Bagmati | N5: **Bagmati** | O5: 24 | P5: 2 | Q5: 17 | R5: **43**
B6: =IFERROR(__xludf.DUMMYFUNCTION("""COMPUTED_VALUE"""),45893.18133101852) -> 45893.181 | C6: =IFERROR(__xludf.DUMMYFUNCTION("""COMPUTED_VALUE"""),"Martin 3 sole 41") -> Martin 3 sole 41 | D6: =IFERROR(__xludf.DUMMYFUNCTION("""COMPUTED_VALUE"""),"Manish Bishwokarma") -> Manish Bishwokarma | E6: =IFERROR(__xludf.DUMMYFUNCTION("""COMPUTED_VALUE"""),"Tanahun, dulegauda ") -> Tanahun, dulegauda | F6: =IFERROR(__xludf.DUMMYFUNCTION("""COMPUTED_VALUE"""),9.815193182E9) -> 9815193182 | G6: =IFERROR(__xludf.DUMMYFUNCTION("""COMPUTED_VALUE"""),650.0) -> 650 | H6: =IFERROR(__xludf.DUMMYFUNCTION("""COMPUTED_VALUE"""),1650.0) -> 1650 | I6: =IFERROR(__xludf.DUMMYFUNCTION("""COMPUTED_VALUE"""),183.13) -> 183.13 | J6: =IFERROR(__xludf.DUMMYFUNCTION("""COMPUTED_VALUE"""),"Delivered") -> Delivered | K6: =IFERROR(__xludf.DUMMYFUNCTION("""COMPUTED_VALUE"""),45894.3146412037) -> 45894.315 | L6: =IFERROR(__xludf.DUMMYFUNCTION("IFS( OR(REGEXMATCH(LOWER(E6), ""sirutar|sundarijal|sitapaila|duwakot|tikathali|bhaktapur|lalitpur|kathmandu|ktm|changunarayan|bageswari|ghalate|tinkune|balkot|tikathali""), REGEXMATCH(LOWER(E6), ""inside valley"")), ""Inside Valley"", REGEXMATCH(LOWER"&"(E6), ""dharan|pokhara|biratnagar|birgunj|narayanghat|itahari|hetauda|janakpur|madi""), ""Tier 1"", REGEXMATCH(LOWER(E6), ""nepalgunj|butwal|birtamod|dhangadhi|ghorahi|beni|kushma|waling|haldibari|dulegauda|baitadi|bhadrapur|syangja|parbat|myagdi|dang|n"&"uwakot|jhapa""), ""Tier 2"", TRUE, ""Tier 3"" )"),"Tier 2") -> Tier 2 | M6: Gandaki | N6: **Koshi** | O6: 6 | P6: 8 | Q6: 19 | R6: **33**
B7: =IFERROR(__xludf.DUMMYFUNCTION("""COMPUTED_VALUE"""),45893.17900462963) -> 45893.179 | C7: =IFERROR(__xludf.DUMMYFUNCTION("""COMPUTED_VALUE"""),"Blue Nike 39") -> Blue Nike 39 | D7: =IFERROR(__xludf.DUMMYFUNCTION("""COMPUTED_VALUE"""),"Rajdip Chudal") -> Rajdip Chudal | E7: =IFERROR(__xludf.DUMMYFUNCTION("""COMPUTED_VALUE"""),"Haldibari 4, magalbare jhapa") -> Haldibari 4, magalbare jhapa | F7: =IFERROR(__xludf.DUMMYFUNCTION("""COMPUTED_VALUE"""),9.815936372E9) -> 9815936372 | G7: =IFERROR(__xludf.DUMMYFUNCTION("""COMPUTED_VALUE"""),350.0) -> 350 | H7: =IFERROR(__xludf.DUMMYFUNCTION("""COMPUTED_VALUE"""),1350.0) -> 1350 | I7: =IFERROR(__xludf.DUMMYFUNCTION("""COMPUTED_VALUE"""),182.38) -> 182.38 | J7: =IFERROR(__xludf.DUMMYFUNCTION("""COMPUTED_VALUE"""),"Delivered") -> Delivered | K7: =IFERROR(__xludf.DUMMYFUNCTION("""COMPUTED_VALUE"""),45895.44592592593) -> 45895.446 | L7: =IFERROR(__xludf.DUMMYFUNCTION("IFS( OR(REGEXMATCH(LOWER(E7), ""sirutar|sundarijal|sitapaila|duwakot|tikathali|bhaktapur|lalitpur|kathmandu|ktm|changunarayan|bageswari|ghalate|tinkune|balkot|tikathali""), REGEXMATCH(LOWER(E7), ""inside valley"")), ""Inside Valley"", REGEXMATCH(LOWER"&"(E7), ""dharan|pokhara|biratnagar|birgunj|narayanghat|itahari|hetauda|janakpur|madi""), ""Tier 1"", REGEXMATCH(LOWER(E7), ""nepalgunj|butwal|birtamod|dhangadhi|ghorahi|beni|kushma|waling|haldibari|dulegauda|baitadi|bhadrapur|syangja|parbat|myagdi|dang|n"&"uwakot|jhapa""), ""Tier 2"", TRUE, ""Tier 3"" )"),"Tier 2") -> Tier 2 | M7: Koshi | N7: **Gandaki** | O7: 7 | P7: 10 | Q7: 4 | R7: **21**
B8: =IFERROR(__xludf.DUMMYFUNCTION("""COMPUTED_VALUE"""),45893.178032407406) -> 45893.178 | C8: =IFERROR(__xludf.DUMMYFUNCTION("""COMPUTED_VALUE"""),"Martin 3 sole size 39 39 38") -> Martin 3 sole size 39 39 38 | D8: =IFERROR(__xludf.DUMMYFUNCTION("""COMPUTED_VALUE"""),"Laxmi Rai") -> Laxmi Rai | E8: =IFERROR(__xludf.DUMMYFUNCTION("""COMPUTED_VALUE""")," Shree antu, baral bhanjyang") -> Shree antu, baral bhanjyang | F8: =IFERROR(__xludf.DUMMYFUNCTION("""COMPUTED_VALUE"""),9.769723304E9) -> 9769723304 | G8: =IFERROR(__xludf.DUMMYFUNCTION("""COMPUTED_VALUE"""),1300.0) -> 1300 | H8: =IFERROR(__xludf.DUMMYFUNCTION("""COMPUTED_VALUE"""),4650.0) -> 4650 | I8: =IFERROR(__xludf.DUMMYFUNCTION("""COMPUTED_VALUE"""),220.63) -> 220.63 | J8: =IFERROR(__xludf.DUMMYFUNCTION("""COMPUTED_VALUE"""),"Delivered") -> Delivered | K8: =IFERROR(__xludf.DUMMYFUNCTION("""COMPUTED_VALUE"""),45898.376655092594) -> 45898.377 | L8: =IFERROR(__xludf.DUMMYFUNCTION("IFS( OR(REGEXMATCH(LOWER(E8), ""sirutar|sundarijal|sitapaila|duwakot|tikathali|bhaktapur|lalitpur|kathmandu|ktm|changunarayan|bageswari|ghalate|tinkune|balkot|tikathali""), REGEXMATCH(LOWER(E8), ""inside valley"")), ""Inside Valley"", REGEXMATCH(LOWER"&"(E8), ""dharan|pokhara|biratnagar|birgunj|narayanghat|itahari|hetauda|janakpur|madi""), ""Tier 1"", REGEXMATCH(LOWER(E8), ""nepalgunj|butwal|birtamod|dhangadhi|ghorahi|beni|kushma|waling|haldibari|dulegauda|baitadi|bhadrapur|syangja|parbat|myagdi|dang|n"&"uwakot|jhapa""), ""Tier 2"", TRUE, ""Tier 3"" )"),"Tier 3") -> Tier 3 | M8: Madhesh | N8: **Lumbini** | O8: 0 | P8: 10 | Q8: 8 | R8: **18**
B9: =IFERROR(__xludf.DUMMYFUNCTION("""COMPUTED_VALUE"""),45892.28570601852) -> 45892.286 | C9: =IFERROR(__xludf.DUMMYFUNCTION("""COMPUTED_VALUE"""),"Nike 11 red and Martin 2 sole 42 and 43") -> Nike 11 red and Martin 2 sole 42 and 43 | D9: =IFERROR(__xludf.DUMMYFUNCTION("""COMPUTED_VALUE"""),"Dipak Shah") -> Dipak Shah | E9: =IFERROR(__xludf.DUMMYFUNCTION("""COMPUTED_VALUE"""),"Tinkune, the new summit college") -> Tinkune, the new summit college | F9: =IFERROR(__xludf.DUMMYFUNCTION("""COMPUTED_VALUE"""),9.826881955E9) -> 9826881955 | G9: =IFERROR(__xludf.DUMMYFUNCTION("""COMPUTED_VALUE"""),800.0) -> 800 | H9: =IFERROR(__xludf.DUMMYFUNCTION("""COMPUTED_VALUE"""),2600.0) -> 2600 | I9: =IFERROR(__xludf.DUMMYFUNCTION("""COMPUTED_VALUE"""),105.5) -> 105.5 | J9: =IFERROR(__xludf.DUMMYFUNCTION("""COMPUTED_VALUE"""),"Delivered") -> Delivered | K9: =IFERROR(__xludf.DUMMYFUNCTION("""COMPUTED_VALUE"""),45893.2530324074) -> 45893.253 | L9: =IFERROR(__xludf.DUMMYFUNCTION("IFS( OR(REGEXMATCH(LOWER(E9), ""sirutar|sundarijal|sitapaila|duwakot|tikathali|bhaktapur|lalitpur|kathmandu|ktm|changunarayan|bageswari|ghalate|tinkune|balkot|tikathali""), REGEXMATCH(LOWER(E9), ""inside valley"")), ""Inside Valley"", REGEXMATCH(LOWER"&"(E9), ""dharan|pokhara|biratnagar|birgunj|narayanghat|itahari|hetauda|janakpur|madi""), ""Tier 1"", REGEXMATCH(LOWER(E9), ""nepalgunj|butwal|birtamod|dhangadhi|ghorahi|beni|kushma|waling|haldibari|dulegauda|baitadi|bhadrapur|syangja|parbat|myagdi|dang|n"&"uwakot|jhapa""), ""Tier 2"", TRUE, ""Tier 3"" )"),"Inside Valley") -> Inside Valley | M9: Bagmati | N9: **Sudurpashchim** | O9: 0 | P9: 1 | Q9: 3 | R9: **4**
B10: =IFERROR(__xludf.DUMMYFUNCTION("""COMPUTED_VALUE"""),45892.228217592594) -> 45892.228 | C10: =IFERROR(__xludf.DUMMYFUNCTION("""COMPUTED_VALUE"""),"Martin 1 sole 43") -> Martin 1 sole 43 | D10: =IFERROR(__xludf.DUMMYFUNCTION("""COMPUTED_VALUE"""),"Chandra Bohara") -> Chandra Bohara | E10: =IFERROR(__xludf.DUMMYFUNCTION("""COMPUTED_VALUE"""),"Dadeldhura, bagbazzar tufandadko check najik police bit") -> Dadeldhura, bagbazzar tufandadko check najik police bit | F10: =IFERROR(__xludf.DUMMYFUNCTION("""COMPUTED_VALUE"""),9.865629618E9) -> 9865629618 | G10: =IFERROR(__xludf.DUMMYFUNCTION("""COMPUTED_VALUE"""),450.0) -> 450 | H10: =IFERROR(__xludf.DUMMYFUNCTION("""COMPUTED_VALUE"""),1350.0) -> 1350 | I10: =IFERROR(__xludf.DUMMYFUNCTION("""COMPUTED_VALUE"""),182.38) -> 182.38 | J10: =IFERROR(__xludf.DUMMYFUNCTION("""COMPUTED_VALUE"""),"Delivered") -> Delivered | K10: =IFERROR(__xludf.DUMMYFUNCTION("""COMPUTED_VALUE"""),45895.355046296296) -> 45895.355 | L10: =IFERROR(__xludf.DUMMYFUNCTION("IFS( OR(REGEXMATCH(LOWER(E10), ""sirutar|sundarijal|sitapaila|duwakot|tikathali|bhaktapur|lalitpur|kathmandu|ktm|changunarayan|bageswari|ghalate|tinkune|balkot|tikathali""), REGEXMATCH(LOWER(E10), ""inside valley"")), ""Inside Valley"", REGEXMATCH(LOW"&"ER(E10), ""dharan|pokhara|biratnagar|birgunj|narayanghat|itahari|hetauda|janakpur|madi""), ""Tier 1"", REGEXMATCH(LOWER(E10), ""nepalgunj|butwal|birtamod|dhangadhi|ghorahi|beni|kushma|waling|haldibari|dulegauda|baitadi|bhadrapur|syangja|parbat|myagdi|da"&"ng|nuwakot|jhapa""), ""Tier 2"", TRUE, ""Tier 3"" )"),"Tier 3") -> Tier 3 | M10: Sudurpashchim | N10: **Madhesh** | O10: 0 | P10: 0 | Q10: 3 | R10: **3**
B11: =IFERROR(__xludf.DUMMYFUNCTION("""COMPUTED_VALUE"""),45892.22659722222) -> 45892.227 | C11: =IFERROR(__xludf.DUMMYFUNCTION("""COMPUTED_VALUE"""),"Martin 2 sole 40") -> Martin 2 sole 40 | D11: =IFERROR(__xludf.DUMMYFUNCTION("""COMPUTED_VALUE"""),"Prabin Karki") -> Prabin Karki | E11: =IFERROR(__xludf.DUMMYFUNCTION("""COMPUTED_VALUE"""),"Solukhumbu, tingla") -> Solukhumbu, tingla | F11: =IFERROR(__xludf.DUMMYFUNCTION("""COMPUTED_VALUE"""),9.749215487E9) -> 9749215487 | G11: =IFERROR(__xludf.DUMMYFUNCTION("""COMPUTED_VALUE"""),550.0) -> 550 | H11: =IFERROR(__xludf.DUMMYFUNCTION("""COMPUTED_VALUE"""),1550.0) -> 1550 | I11: =IFERROR(__xludf.DUMMYFUNCTION("""COMPUTED_VALUE"""),212.88) -> 212.88 | J11: =IFERROR(__xludf.DUMMYFUNCTION("""COMPUTED_VALUE"""),"Delivered") -> Delivered | K11: =IFERROR(__xludf.DUMMYFUNCTION("""COMPUTED_VALUE"""),45898.67103009259) -> 45898.671 | L11: =IFERROR(__xludf.DUMMYFUNCTION("IFS( OR(REGEXMATCH(LOWER(E11), ""sirutar|sundarijal|sitapaila|duwakot|tikathali|bhaktapur|lalitpur|kathmandu|ktm|changunarayan|bageswari|ghalate|tinkune|balkot|tikathali""), REGEXMATCH(LOWER(E11), ""inside valley"")), ""Inside Valley"", REGEXMATCH(LOW"&"ER(E11), ""dharan|pokhara|biratnagar|birgunj|narayanghat|itahari|hetauda|janakpur|madi""), ""Tier 1"", REGEXMATCH(LOWER(E11), ""nepalgunj|butwal|birtamod|dhangadhi|ghorahi|beni|kushma|waling|haldibari|dulegauda|baitadi|bhadrapur|syangja|parbat|myagdi|da"&"ng|nuwakot|jhapa""), ""Tier 2"", TRUE, ""Tier 3"" )"),"Tier 3") -> Tier 3 | M11: Koshi | N11: **Karnali** | O11: 0 | P11: 0 | Q11: 1 | R11: **1**
B12: =IFERROR(__xludf.DUMMYFUNCTION("""COMPUTED_VALUE"""),45891.18746527778) -> 45891.187 | C12: =IFERROR(__xludf.DUMMYFUNCTION("""COMPUTED_VALUE"""),"Blue Nike size 42") -> Blue Nike size 42 | D12: =IFERROR(__xludf.DUMMYFUNCTION("""COMPUTED_VALUE"""),"Biraj Tamang") -> Biraj Tamang | E12: =IFERROR(__xludf.DUMMYFUNCTION("""COMPUTED_VALUE"""),"Jhapa, budhabare or buddhashanti ") -> Jhapa, budhabare or buddhashanti | F12: =IFERROR(__xludf.DUMMYFUNCTION("""COMPUTED_VALUE"""),9.702839214E9) -> 9702839214 | G12: =IFERROR(__xludf.DUMMYFUNCTION("""COMPUTED_VALUE"""),350.0) -> 350 | H12: =IFERROR(__xludf.DUMMYFUNCTION("""COMPUTED_VALUE"""),1350.0) -> 1350 | I12: =IFERROR(__xludf.DUMMYFUNCTION("""COMPUTED_VALUE"""),182.38) -> 182.38 | J12: =IFERROR(__xludf.DUMMYFUNCTION("""COMPUTED_VALUE"""),"Delivered") -> Delivered | K12: =IFERROR(__xludf.DUMMYFUNCTION("""COMPUTED_VALUE"""),45894.39797453704) -> 45894.398 | L12: =IFERROR(__xludf.DUMMYFUNCTION("IFS( OR(REGEXMATCH(LOWER(E12), ""sirutar|sundarijal|sitapaila|duwakot|tikathali|bhaktapur|lalitpur|kathmandu|ktm|changunarayan|bageswari|ghalate|tinkune|balkot|tikathali""), REGEXMATCH(LOWER(E12), ""inside valley"")), ""Inside Valley"", REGEXMATCH(LOW"&"ER(E12), ""dharan|pokhara|biratnagar|birgunj|narayanghat|itahari|hetauda|janakpur|madi""), ""Tier 1"", REGEXMATCH(LOWER(E12), ""nepalgunj|butwal|birtamod|dhangadhi|ghorahi|beni|kushma|waling|haldibari|dulegauda|baitadi|bhadrapur|syangja|parbat|myagdi|da"&"ng|nuwakot|jhapa""), ""Tier 2"", TRUE, ""Tier 3"" )"),"Tier 2") -> Tier 2 | M12: Koshi | O12: =sum(Table2[Tier 1]) -> 37 | P12: =SUM(Table2[Tier 2]) -> 31 | Q12: =SUM(Table2[Tier 3]) -> 55 | R12: 123
B13: =IFERROR(__xludf.DUMMYFUNCTION("""COMPUTED_VALUE"""),45891.18523148148) -> 45891.185 | C13: =IFERROR(__xludf.DUMMYFUNCTION("""COMPUTED_VALUE"""),"Red Nike 40") -> Red Nike 40 | D13: =IFERROR(__xludf.DUMMYFUNCTION("""COMPUTED_VALUE"""),"Sujan Jagebu Limbu") -> Sujan Jagebu Limbu | E13: =IFERROR(__xludf.DUMMYFUNCTION("""COMPUTED_VALUE"""),"Jhapa, birtamod karat chowk Road no 1") -> Jhapa, birtamod karat chowk Road no 1 | F13: =IFERROR(__xludf.DUMMYFUNCTION("""COMPUTED_VALUE"""),9.700427269E9) -> 9700427269 | G13: =IFERROR(__xludf.DUMMYFUNCTION("""COMPUTED_VALUE"""),450.0) -> 450 | H13: =IFERROR(__xludf.DUMMYFUNCTION("""COMPUTED_VALUE"""),1350.0) -> 1350 | I13: =IFERROR(__xludf.DUMMYFUNCTION("""COMPUTED_VALUE"""),182.38) -> 182.38 | J13: =IFERROR(__xludf.DUMMYFUNCTION("""COMPUTED_VALUE"""),"Delivered") -> Delivered | K13: =IFERROR(__xludf.DUMMYFUNCTION("""COMPUTED_VALUE"""),45893.449965277774) -> 45893.45 | L13: =IFERROR(__xludf.DUMMYFUNCTION("IFS( OR(REGEXMATCH(LOWER(E13), ""sirutar|sundarijal|sitapaila|duwakot|tikathali|bhaktapur|lalitpur|kathmandu|ktm|changunarayan|bageswari|ghalate|tinkune|balkot|tikathali""), REGEXMATCH(LOWER(E13), ""inside valley"")), ""Inside Valley"", REGEXMATCH(LOW"&"ER(E13), ""dharan|pokhara|biratnagar|birgunj|narayanghat|itahari|hetauda|janakpur|madi""), ""Tier 1"", REGEXMATCH(LOWER(E13), ""nepalgunj|butwal|birtamod|dhangadhi|ghorahi|beni|kushma|waling|haldibari|dulegauda|baitadi|bhadrapur|syangja|parbat|myagdi|da"&"ng|nuwakot|jhapa""), ""Tier 2"", TRUE, ""Tier 3"" )"),"Tier 2") -> Tier 2 | M13: Koshi
B14: =IFERROR(__xludf.DUMMYFUNCTION("""COMPUTED_VALUE"""),45890.17833333333) -> 45890.178 | C14: =IFERROR(__xludf.DUMMYFUNCTION("""COMPUTED_VALUE"""),"Casual Adidas shoes 41") -> Casual Adidas shoes 41 | D14: =IFERROR(__xludf.DUMMYFUNCTION("""COMPUTED_VALUE"""),"Asmirt Tamang") -> Asmirt Tamang | E14: =IFERROR(__xludf.DUMMYFUNCTION("""COMPUTED_VALUE"""),"Pokhara") -> Pokhara | F14: =IFERROR(__xludf.DUMMYFUNCTION("""COMPUTED_VALUE"""),9.703252518E9) -> 9703252518 | G14: =IFERROR(__xludf.DUMMYFUNCTION("""COMPUTED_VALUE"""),450.0) -> 450 | H14: =IFERROR(__xludf.DUMMYFUNCTION("""COMPUTED_VALUE"""),1450.0) -> 1450 | I14: =IFERROR(__xludf.DUMMYFUNCTION("""COMPUTED_VALUE"""),162.63) -> 162.63 | J14: =IFERROR(__xludf.DUMMYFUNCTION("""COMPUTED_VALUE"""),"Delivered") -> Delivered | K14: =IFERROR(__xludf.DUMMYFUNCTION("""COMPUTED_VALUE"""),45893.31458333333) -> 45893.315 | L14: =IFERROR(__xludf.DUMMYFUNCTION("IFS( OR(REGEXMATCH(LOWER(E14), ""sirutar|sundarijal|sitapaila|duwakot|tikathali|bhaktapur|lalitpur|kathmandu|ktm|changunarayan|bageswari|ghalate|tinkune|balkot|tikathali""), REGEXMATCH(LOWER(E14), ""inside valley"")), ""Inside Valley"", REGEXMATCH(LOW"&"ER(E14), ""dharan|pokhara|biratnagar|birgunj|narayanghat|itahari|hetauda|janakpur|madi""), ""Tier 1"", REGEXMATCH(LOWER(E14), ""nepalgunj|butwal|birtamod|dhangadhi|ghorahi|beni|kushma|waling|haldibari|dulegauda|baitadi|bhadrapur|syangja|parbat|myagdi|da"&"ng|nuwakot|jhapa""), ""Tier 2"", TRUE, ""Tier 3"" )"),"Tier 1") -> Tier 1 | M14: Gandaki
B15: =IFERROR(__xludf.DUMMYFUNCTION("""COMPUTED_VALUE"""),45890.17673611111) -> 45890.177 | C15: =IFERROR(__xludf.DUMMYFUNCTION("""COMPUTED_VALUE"""),"Martin 2 sole 39 nayabasti") -> Martin 2 sole 39 nayabasti | D15: =IFERROR(__xludf.DUMMYFUNCTION("""COMPUTED_VALUE"""),"Anil Khadgi") -> Anil Khadgi | E15: =IFERROR(__xludf.DUMMYFUNCTION("""COMPUTED_VALUE"""),"Sitapaila mathi ramkot") -> Sitapaila mathi ramkot | F15: =IFERROR(__xludf.DUMMYFUNCTION("""COMPUTED_VALUE"""),9.803874775E9) -> 9803874775 | G15: =IFERROR(__xludf.DUMMYFUNCTION("""COMPUTED_VALUE"""),500.0) -> 500 | H15: =IFERROR(__xludf.DUMMYFUNCTION("""COMPUTED_VALUE"""),1500.0) -> 1500 | I15: =IFERROR(__xludf.DUMMYFUNCTION("""COMPUTED_VALUE"""),102.75) -> 102.75 | J15: =IFERROR(__xludf.DUMMYFUNCTION("""COMPUTED_VALUE"""),"Delivered") -> Delivered | K15: =IFERROR(__xludf.DUMMYFUNCTION("""COMPUTED_VALUE"""),45890.50582175926) -> 45890.506 | L15: =IFERROR(__xludf.DUMMYFUNCTION("IFS( OR(REGEXMATCH(LOWER(E15), ""sirutar|sundarijal|sitapaila|duwakot|tikathali|bhaktapur|lalitpur|kathmandu|ktm|changunarayan|bageswari|ghalate|tinkune|balkot|tikathali""), REGEXMATCH(LOWER(E15), ""inside valley"")), ""Inside Valley"", REGEXMATCH(LOW"&"ER(E15), ""dharan|pokhara|biratnagar|birgunj|narayanghat|itahari|hetauda|janakpur|madi""), ""Tier 1"", REGEXMATCH(LOWER(E15), ""nepalgunj|butwal|birtamod|dhangadhi|ghorahi|beni|kushma|waling|haldibari|dulegauda|baitadi|bhadrapur|syangja|parbat|myagdi|da"&"ng|nuwakot|jhapa""), ""Tier 2"", TRUE, ""Tier 3"" )"),"Inside Valley") -> Inside Valley | M15: Bagmati
B16: =IFERROR(__xludf.DUMMYFUNCTION("""COMPUTED_VALUE"""),45890.17537037037) -> 45890.175 | C16: =IFERROR(__xludf.DUMMYFUNCTION("""COMPUTED_VALUE"""),"Martin 3 sole size 43") -> Martin 3 sole size 43 | D16: =IFERROR(__xludf.DUMMYFUNCTION("""COMPUTED_VALUE"""),"Bikash") -> Bikash | E16: =IFERROR(__xludf.DUMMYFUNCTION("""COMPUTED_VALUE"""),"Rolpa, ghartghau") -> Rolpa, ghartghau | F16: =IFERROR(__xludf.DUMMYFUNCTION("""COMPUTED_VALUE"""),9.765840359E9) -> 9765840359 | G16: =IFERROR(__xludf.DUMMYFUNCTION("""COMPUTED_VALUE"""),650.0) -> 650 | H16: =IFERROR(__xludf.DUMMYFUNCTION("""COMPUTED_VALUE"""),1650.0) -> 1650 | I16: =IFERROR(__xludf.DUMMYFUNCTION("""COMPUTED_VALUE"""),213.13) -> 213.13 | J16: =IFERROR(__xludf.DUMMYFUNCTION("""COMPUTED_VALUE"""),"Delivered") -> Delivered | K16: =IFERROR(__xludf.DUMMYFUNCTION("""COMPUTED_VALUE"""),45895.638506944444) -> 45895.639 | L16: =IFERROR(__xludf.DUMMYFUNCTION("IFS( OR(REGEXMATCH(LOWER(E16), ""sirutar|sundarijal|sitapaila|duwakot|tikathali|bhaktapur|lalitpur|kathmandu|ktm|changunarayan|bageswari|ghalate|tinkune|balkot|tikathali""), REGEXMATCH(LOWER(E16), ""inside valley"")), ""Inside Valley"", REGEXMATCH(LOW"&"ER(E16), ""dharan|pokhara|biratnagar|birgunj|narayanghat|itahari|hetauda|janakpur|madi""), ""Tier 1"", REGEXMATCH(LOWER(E16), ""nepalgunj|butwal|birtamod|dhangadhi|ghorahi|beni|kushma|waling|haldibari|dulegauda|baitadi|bhadrapur|syangja|parbat|myagdi|da"&"ng|nuwakot|jhapa""), ""Tier 2"", TRUE, ""Tier 3"" )"),"Tier 3") -> Tier 3 | M16: Lumbini
B17: =IFERROR(__xludf.DUMMYFUNCTION("""COMPUTED_VALUE"""),45889.17605324074) -> 45889.176 | C17: =IFERROR(__xludf.DUMMYFUNCTION("""COMPUTED_VALUE"""),"Chelsea size 43") -> Chelsea size 43 | D17: =IFERROR(__xludf.DUMMYFUNCTION("""COMPUTED_VALUE"""),"Dipendra Chaudhari") -> Dipendra Chaudhari | E17: =IFERROR(__xludf.DUMMYFUNCTION("""COMPUTED_VALUE"""),"Chitwan, madi") -> Chitwan, madi | F17: =IFERROR(__xludf.DUMMYFUNCTION("""COMPUTED_VALUE"""),9.807289391E9) -> 9807289391 | G17: =IFERROR(__xludf.DUMMYFUNCTION("""COMPUTED_VALUE"""),450.0) -> 450 | H17: =IFERROR(__xludf.DUMMYFUNCTION("""COMPUTED_VALUE"""),1450.0) -> 1450 | I17: =IFERROR(__xludf.DUMMYFUNCTION("""COMPUTED_VALUE"""),162.63) -> 162.63 | J17: =IFERROR(__xludf.DUMMYFUNCTION("""COMPUTED_VALUE"""),"Delivered") -> Delivered | K17: =IFERROR(__xludf.DUMMYFUNCTION("""COMPUTED_VALUE"""),45891.61177083333) -> 45891.612 | L17: =IFERROR(__xludf.DUMMYFUNCTION("IFS( OR(REGEXMATCH(LOWER(E17), ""sirutar|sundarijal|sitapaila|duwakot|tikathali|bhaktapur|lalitpur|kathmandu|ktm|changunarayan|bageswari|ghalate|tinkune|balkot|tikathali""), REGEXMATCH(LOWER(E17), ""inside valley"")), ""Inside Valley"", REGEXMATCH(LOW"&"ER(E17), ""dharan|pokhara|biratnagar|birgunj|narayanghat|itahari|hetauda|janakpur|madi""), ""Tier 1"", REGEXMATCH(LOWER(E17), ""nepalgunj|butwal|birtamod|dhangadhi|ghorahi|beni|kushma|waling|haldibari|dulegauda|baitadi|bhadrapur|syangja|parbat|myagdi|da"&"ng|nuwakot|jhapa""), ""Tier 2"", TRUE, ""Tier 3"" )"),"Tier 1") -> Tier 1 | M17: Bagmati
B18: =IFERROR(__xludf.DUMMYFUNCTION("""COMPUTED_VALUE"""),45889.1749074074) -> 45889.175 | C18: =IFERROR(__xludf.DUMMYFUNCTION("""COMPUTED_VALUE"""),"Martin 3 sole size 41") -> Martin 3 sole size 41 | D18: =IFERROR(__xludf.DUMMYFUNCTION("""COMPUTED_VALUE"""),"Ninam Rai") -> Ninam Rai | E18: =IFERROR(__xludf.DUMMYFUNCTION("""COMPUTED_VALUE"""),"Taplejung") -> Taplejung | F18: =IFERROR(__xludf.DUMMYFUNCTION("""COMPUTED_VALUE"""),9.767381711E9) -> 9767381711 | G18: =IFERROR(__xludf.DUMMYFUNCTION("""COMPUTED_VALUE"""),550.0) -> 550 | H18: =IFERROR(__xludf.DUMMYFUNCTION("""COMPUTED_VALUE"""),1550.0) -> 1550 | I18: =IFERROR(__xludf.DUMMYFUNCTION("""COMPUTED_VALUE"""),212.88) -> 212.88 | J18: =IFERROR(__xludf.DUMMYFUNCTION("""COMPUTED_VALUE"""),"Delivered") -> Delivered | K18: =IFERROR(__xludf.DUMMYFUNCTION("""COMPUTED_VALUE"""),45895.23165509259) -> 45895.232 | L18: =IFERROR(__xludf.DUMMYFUNCTION("IFS( OR(REGEXMATCH(LOWER(E18), ""sirutar|sundarijal|sitapaila|duwakot|tikathali|bhaktapur|lalitpur|kathmandu|ktm|changunarayan|bageswari|ghalate|tinkune|balkot|tikathali""), REGEXMATCH(LOWER(E18), ""inside valley"")), ""Inside Valley"", REGEXMATCH(LOW"&"ER(E18), ""dharan|pokhara|biratnagar|birgunj|narayanghat|itahari|hetauda|janakpur|madi""), ""Tier 1"", REGEXMATCH(LOWER(E18), ""nepalgunj|butwal|birtamod|dhangadhi|ghorahi|beni|kushma|waling|haldibari|dulegauda|baitadi|bhadrapur|syangja|parbat|myagdi|da"&"ng|nuwakot|jhapa""), ""Tier 2"", TRUE, ""Tier 3"" )"),"Tier 3") -> Tier 3 | M18: Koshi
B19: =IFERROR(__xludf.DUMMYFUNCTION("""COMPUTED_VALUE"""),45889.17271990741) -> 45889.173 | C19: =IFERROR(__xludf.DUMMYFUNCTION("""COMPUTED_VALUE"""),"Converse black size 40") -> Converse black size 40 | D19: =IFERROR(__xludf.DUMMYFUNCTION("""COMPUTED_VALUE"""),"Ajeet Khadka") -> Ajeet Khadka | E19: =IFERROR(__xludf.DUMMYFUNCTION("""COMPUTED_VALUE"""),"Bhaktapur, bageswari changunarayan nabarpalika wada no 7") -> Bhaktapur, bageswari changunarayan nabarpalika wada no 7 | F19: =IFERROR(__xludf.DUMMYFUNCTION("""COMPUTED_VALUE"""),9.860944595E9) -> 9860944595 | G19: =IFERROR(__xludf.DUMMYFUNCTION("""COMPUTED_VALUE"""),500.0) -> 500 | H19: =IFERROR(__xludf.DUMMYFUNCTION("""COMPUTED_VALUE"""),1300.0) -> 1300 | I19: =IFERROR(__xludf.DUMMYFUNCTION("""COMPUTED_VALUE"""),182.25) -> 182.25 | J19: =IFERROR(__xludf.DUMMYFUNCTION("""COMPUTED_VALUE"""),"Delivered") -> Delivered | K19: =IFERROR(__xludf.DUMMYFUNCTION("""COMPUTED_VALUE"""),45890.36565972222) -> 45890.366 | L19: =IFERROR(__xludf.DUMMYFUNCTION("IFS( OR(REGEXMATCH(LOWER(E19), ""sirutar|sundarijal|sitapaila|duwakot|tikathali|bhaktapur|lalitpur|kathmandu|ktm|changunarayan|bageswari|ghalate|tinkune|balkot|tikathali""), REGEXMATCH(LOWER(E19), ""inside valley"")), ""Inside Valley"", REGEXMATCH(LOW"&"ER(E19), ""dharan|pokhara|biratnagar|birgunj|narayanghat|itahari|hetauda|janakpur|madi""), ""Tier 1"", REGEXMATCH(LOWER(E19), ""nepalgunj|butwal|birtamod|dhangadhi|ghorahi|beni|kushma|waling|haldibari|dulegauda|baitadi|bhadrapur|syangja|parbat|myagdi|da"&"ng|nuwakot|jhapa""), ""Tier 2"", TRUE, ""Tier 3"" )"),"Inside Valley") -> Inside Valley | M19: Bagmati
B20: =IFERROR(__xludf.DUMMYFUNCTION("""COMPUTED_VALUE"""),45888.17891203704) -> 45888.179 | C20: =IFERROR(__xludf.DUMMYFUNCTION("""COMPUTED_VALUE"""),"Martin single 41 and 42") -> Martin single 41 and 42 | D20: =IFERROR(__xludf.DUMMYFUNCTION("""COMPUTED_VALUE"""),"Sitaram Pun") -> Sitaram Pun | E20: =IFERROR(__xludf.DUMMYFUNCTION("""COMPUTED_VALUE"""),"Pyuthan, sari") -> Pyuthan, sari | F20: =IFERROR(__xludf.DUMMYFUNCTION("""COMPUTED_VALUE"""),9.762095448E9) -> 9762095448 | G20: =IFERROR(__xludf.DUMMYFUNCTION("""COMPUTED_VALUE"""),550.0) -> 550 | H20: =IFERROR(__xludf.DUMMYFUNCTION("""COMPUTED_VALUE"""),2550.0) -> 2550 | I20: =IFERROR(__xludf.DUMMYFUNCTION("""COMPUTED_VALUE"""),185.38) -> 185.38 | J20: =IFERROR(__xludf.DUMMYFUNCTION("""COMPUTED_VALUE"""),"Delivered") -> Delivered | K20: =IFERROR(__xludf.DUMMYFUNCTION("""COMPUTED_VALUE"""),45893.495370370365) -> 45893.495 | L20: =IFERROR(__xludf.DUMMYFUNCTION("IFS( OR(REGEXMATCH(LOWER(E20), ""sirutar|sundarijal|sitapaila|duwakot|tikathali|bhaktapur|lalitpur|kathmandu|ktm|changunarayan|bageswari|ghalate|tinkune|balkot|tikathali""), REGEXMATCH(LOWER(E20), ""inside valley"")), ""Inside Valley"", REGEXMATCH(LOW"&"ER(E20), ""dharan|pokhara|biratnagar|birgunj|narayanghat|itahari|hetauda|janakpur|madi""), ""Tier 1"", REGEXMATCH(LOWER(E20), ""nepalgunj|butwal|birtamod|dhangadhi|ghorahi|beni|kushma|waling|haldibari|dulegauda|baitadi|bhadrapur|syangja|parbat|myagdi|da"&"ng|nuwakot|jhapa""), ""Tier 2"", TRUE, ""Tier 3"" )"),"Tier 3") -> Tier 3 | M20: Lumbini
B21: =IFERROR(__xludf.DUMMYFUNCTION("""COMPUTED_VALUE"""),45888.17722222222) -> 45888.177 | C21: =IFERROR(__xludf.DUMMYFUNCTION("""COMPUTED_VALUE"""),"Martin 3 sole size 39") -> Martin 3 sole size 39 | D21: =IFERROR(__xludf.DUMMYFUNCTION("""COMPUTED_VALUE"""),"Bali Rawat") -> Bali Rawat | E21: =IFERROR(__xludf.DUMMYFUNCTION("""COMPUTED_VALUE"""),"Nepalgunj, muktpur 12, haltpost najik") -> Nepalgunj, muktpur 12, haltpost najik | F21: =IFERROR(__xludf.DUMMYFUNCTION("""COMPUTED_VALUE"""),9.745506225E9) -> 9745506225 | G21: =IFERROR(__xludf.DUMMYFUNCTION("""COMPUTED_VALUE"""),600.0) -> 600 | H21: =IFERROR(__xludf.DUMMYFUNCTION("""COMPUTED_VALUE"""),1600.0) -> 1600 | I21: =IFERROR(__xludf.DUMMYFUNCTION("""COMPUTED_VALUE"""),213.0) -> 213 | J21: =IFERROR(__xludf.DUMMYFUNCTION("""COMPUTED_VALUE"""),"Delivered") -> Delivered | K21: =IFERROR(__xludf.DUMMYFUNCTION("""COMPUTED_VALUE"""),45889.45898148148) -> 45889.459 | L21: =IFERROR(__xludf.DUMMYFUNCTION("IFS( OR(REGEXMATCH(LOWER(E21), ""sirutar|sundarijal|sitapaila|duwakot|tikathali|bhaktapur|lalitpur|kathmandu|ktm|changunarayan|bageswari|ghalate|tinkune|balkot|tikathali""), REGEXMATCH(LOWER(E21), ""inside valley"")), ""Inside Valley"", REGEXMATCH(LOW"&"ER(E21), ""dharan|pokhara|biratnagar|birgunj|narayanghat|itahari|hetauda|janakpur|madi""), ""Tier 1"", REGEXMATCH(LOWER(E21), ""nepalgunj|butwal|birtamod|dhangadhi|ghorahi|beni|kushma|waling|haldibari|dulegauda|baitadi|bhadrapur|syangja|parbat|myagdi|da"&"ng|nuwakot|jhapa""), ""Tier 2"", TRUE, ""Tier 3"" )"),"Tier 2") -> Tier 2 | M21: Lumbini
B22: =IFERROR(__xludf.DUMMYFUNCTION("""COMPUTED_VALUE"""),45888.17445601852) -> 45888.174 | C22: =IFERROR(__xludf.DUMMYFUNCTION("""COMPUTED_VALUE"""),"Martin single 42") -> Martin single 42 | D22: =IFERROR(__xludf.DUMMYFUNCTION("""COMPUTED_VALUE"""),"Shree krishna") -> Shree krishna | E22: =IFERROR(__xludf.DUMMYFUNCTION("""COMPUTED_VALUE"""),"Ghalate, bhaktapur") -> Ghalate, bhaktapur | F22: =IFERROR(__xludf.DUMMYFUNCTION("""COMPUTED_VALUE"""),9.765007077E9) -> 9765007077 | G22: =IFERROR(__xludf.DUMMYFUNCTION("""COMPUTED_VALUE"""),400.0) -> 400 | H22: =IFERROR(__xludf.DUMMYFUNCTION("""COMPUTED_VALUE"""),1300.0) -> 1300 | I22: =IFERROR(__xludf.DUMMYFUNCTION("""COMPUTED_VALUE"""),102.25) -> 102.25 | J22: =IFERROR(__xludf.DUMMYFUNCTION("""COMPUTED_VALUE"""),"Delivered") -> Delivered | K22: =IFERROR(__xludf.DUMMYFUNCTION("""COMPUTED_VALUE"""),45889.2105787037) -> 45889.211 | L22: =IFERROR(__xludf.DUMMYFUNCTION("IFS( OR(REGEXMATCH(LOWER(E22), ""sirutar|sundarijal|sitapaila|duwakot|tikathali|bhaktapur|lalitpur|kathmandu|ktm|changunarayan|bageswari|ghalate|tinkune|balkot|tikathali""), REGEXMATCH(LOWER(E22), ""inside valley"")), ""Inside Valley"", REGEXMATCH(LOW"&"ER(E22), ""dharan|pokhara|biratnagar|birgunj|narayanghat|itahari|hetauda|janakpur|madi""), ""Tier 1"", REGEXMATCH(LOWER(E22), ""nepalgunj|butwal|birtamod|dhangadhi|ghorahi|beni|kushma|waling|haldibari|dulegauda|baitadi|bhadrapur|syangja|parbat|myagdi|da"&"ng|nuwakot|jhapa""), ""Tier 2"", TRUE, ""Tier 3"" )"),"Inside Valley") -> Inside Valley | M22: Bagmati
B23: =IFERROR(__xludf.DUMMYFUNCTION("""COMPUTED_VALUE"""),45887.16681712963) -> 45887.167 | C23: =IFERROR(__xludf.DUMMYFUNCTION("""COMPUTED_VALUE"""),"Martin triple sole size 40") -> Martin triple sole size 40 | D23: =IFERROR(__xludf.DUMMYFUNCTION("""COMPUTED_VALUE"""),"Aashish Gautam") -> Aashish Gautam | E23: =IFERROR(__xludf.DUMMYFUNCTION("""COMPUTED_VALUE"""),"Baitadi, patan, metallic municipality 7, kanda bazzar") -> Baitadi, patan, metallic municipality 7, kanda bazzar | F23: =IFERROR(__xludf.DUMMYFUNCTION("""COMPUTED_VALUE"""),9.768483761E9) -> 9768483761 | G23: =IFERROR(__xludf.DUMMYFUNCTION("""COMPUTED_VALUE"""),650.0) -> 650 | H23: =IFERROR(__xludf.DUMMYFUNCTION("""COMPUTED_VALUE"""),1650.0) -> 1650 | I23: =IFERROR(__xludf.DUMMYFUNCTION("""COMPUTED_VALUE"""),143.13) -> 143.13 | J23: =IFERROR(__xludf.DUMMYFUNCTION("""COMPUTED_VALUE"""),"Delivered") -> Delivered | K23: =IFERROR(__xludf.DUMMYFUNCTION("""COMPUTED_VALUE"""),45891.40899305556) -> 45891.409 | L23: =IFERROR(__xludf.DUMMYFUNCTION("IFS( OR(REGEXMATCH(LOWER(E23), ""sirutar|sundarijal|sitapaila|duwakot|tikathali|bhaktapur|lalitpur|kathmandu|ktm|changunarayan|bageswari|ghalate|tinkune|balkot|tikathali""), REGEXMATCH(LOWER(E23), ""inside valley"")), ""Inside Valley"", REGEXMATCH(LOW"&"ER(E23), ""dharan|pokhara|biratnagar|birgunj|narayanghat|itahari|hetauda|janakpur|madi""), ""Tier 1"", REGEXMATCH(LOWER(E23), ""nepalgunj|butwal|birtamod|dhangadhi|ghorahi|beni|kushma|waling|haldibari|dulegauda|baitadi|bhadrapur|syangja|parbat|myagdi|da"&"ng|nuwakot|jhapa""), ""Tier 2"", TRUE, ""Tier 3"" )"),"Tier 2") -> Tier 2 | M23: Bagmati
B24: =IFERROR(__xludf.DUMMYFUNCTION("""COMPUTED_VALUE"""),45887.16091435185) -> 45887.161 | C24: =IFERROR(__xludf.DUMMYFUNCTION("""COMPUTED_VALUE"""),"Martin 3 sole size 40") -> Martin 3 sole size 40 | D24: =IFERROR(__xludf.DUMMYFUNCTION("""COMPUTED_VALUE"""),"Prince Shrestha") -> Prince Shrestha | E24: =IFERROR(__xludf.DUMMYFUNCTION("""COMPUTED_VALUE"""),"Beni bazzar ") -> Beni bazzar | F24: =IFERROR(__xludf.DUMMYFUNCTION("""COMPUTED_VALUE"""),9.765610848E9) -> 9765610848 | G24: =IFERROR(__xludf.DUMMYFUNCTION("""COMPUTED_VALUE"""),650.0) -> 650 | H24: =IFERROR(__xludf.DUMMYFUNCTION("""COMPUTED_VALUE"""),1650.0) -> 1650 | I24: =IFERROR(__xludf.DUMMYFUNCTION("""COMPUTED_VALUE"""),183.13) -> 183.13 | J24: =IFERROR(__xludf.DUMMYFUNCTION("""COMPUTED_VALUE"""),"Delivered") -> Delivered | K24: =IFERROR(__xludf.DUMMYFUNCTION("""COMPUTED_VALUE"""),45891.24974537037) -> 45891.25 | L24: =IFERROR(__xludf.DUMMYFUNCTION("IFS( OR(REGEXMATCH(LOWER(E24), ""sirutar|sundarijal|sitapaila|duwakot|tikathali|bhaktapur|lalitpur|kathmandu|ktm|changunarayan|bageswari|ghalate|tinkune|balkot|tikathali""), REGEXMATCH(LOWER(E24), ""inside valley"")), ""Inside Valley"", REGEXMATCH(LOW"&"ER(E24), ""dharan|pokhara|biratnagar|birgunj|narayanghat|itahari|hetauda|janakpur|madi""), ""Tier 1"", REGEXMATCH(LOWER(E24), ""nepalgunj|butwal|birtamod|dhangadhi|ghorahi|beni|kushma|waling|haldibari|dulegauda|baitadi|bhadrapur|syangja|parbat|myagdi|da"&"ng|nuwakot|jhapa""), ""Tier 2"", TRUE, ""Tier 3"" )"),"Tier 2") -> Tier 2 | M24: Gandaki
B25: =IFERROR(__xludf.DUMMYFUNCTION("""COMPUTED_VALUE"""),45886.18208333333) -> 45886.182 | C25: =IFERROR(__xludf.DUMMYFUNCTION("""COMPUTED_VALUE"""),"Nike 40 Black white ") -> Nike 40 Black white | D25: =IFERROR(__xludf.DUMMYFUNCTION("""COMPUTED_VALUE"""),"Siddhartha Gautam") -> Siddhartha Gautam | E25: =IFERROR(__xludf.DUMMYFUNCTION("""COMPUTED_VALUE"""),"Kathmandu,Balkot big mart, Brihaspati marga") -> Kathmandu,Balkot big mart, Brihaspati marga | F25: =IFERROR(__xludf.DUMMYFUNCTION("""COMPUTED_VALUE"""),9.862541342E9) -> 9862541342 | G25: =IFERROR(__xludf.DUMMYFUNCTION("""COMPUTED_VALUE"""),300.0) -> 300 | H25: =IFERROR(__xludf.DUMMYFUNCTION("""COMPUTED_VALUE"""),1300.0) -> 1300 | I25: =IFERROR(__xludf.DUMMYFUNCTION("""COMPUTED_VALUE"""),3.25) -> 3.25 | J25: =IFERROR(__xludf.DUMMYFUNCTION("""COMPUTED_VALUE"""),"Delivered") -> Delivered | K25: =IFERROR(__xludf.DUMMYFUNCTION("""COMPUTED_VALUE"""),45886.49072916667) -> 45886.491 | L25: =IFERROR(__xludf.DUMMYFUNCTION("IFS( OR(REGEXMATCH(LOWER(E25), ""sirutar|sundarijal|sitapaila|duwakot|tikathali|bhaktapur|lalitpur|kathmandu|ktm|changunarayan|bageswari|ghalate|tinkune|balkot|tikathali""), REGEXMATCH(LOWER(E25), ""inside valley"")), ""Inside Valley"", REGEXMATCH(LOW"&"ER(E25), ""dharan|pokhara|biratnagar|birgunj|narayanghat|itahari|hetauda|janakpur|madi""), ""Tier 1"", REGEXMATCH(LOWER(E25), ""nepalgunj|butwal|birtamod|dhangadhi|ghorahi|beni|kushma|waling|haldibari|dulegauda|baitadi|bhadrapur|syangja|parbat|myagdi|da"&"ng|nuwakot|jhapa""), ""Tier 2"", TRUE, ""Tier 3"" )"),"Inside Valley") -> Inside Valley | M25: Bagmati
B26: =IFERROR(__xludf.DUMMYFUNCTION("""COMPUTED_VALUE"""),45873.199583333335) -> 45873.2 | C26: =IFERROR(__xludf.DUMMYFUNCTION("""COMPUTED_VALUE"""),"Martin naysbasti 3 sole 41") -> Martin naysbasti 3 sole 41 | D26: =IFERROR(__xludf.DUMMYFUNCTION("""COMPUTED_VALUE"""),"Santosh") -> Santosh | E26: =IFERROR(__xludf.DUMMYFUNCTION("""COMPUTED_VALUE"""),"Dang, ghorahi") -> Dang, ghorahi | F26: =IFERROR(__xludf.DUMMYFUNCTION("""COMPUTED_VALUE"""),9.818118588E9) -> 9818118588 | G26: =IFERROR(__xludf.DUMMYFUNCTION("""COMPUTED_VALUE"""),550.0) -> 550 | H26: =IFERROR(__xludf.DUMMYFUNCTION("""COMPUTED_VALUE"""),1550.0) -> 1550 | I26: =IFERROR(__xludf.DUMMYFUNCTION("""COMPUTED_VALUE"""),182.88) -> 182.88 | J26: =IFERROR(__xludf.DUMMYFUNCTION("""COMPUTED_VALUE"""),"Delivered") -> Delivered | K26: =IFERROR(__xludf.DUMMYFUNCTION("""COMPUTED_VALUE"""),45882.43194444444) -> 45882.432 | L26: =IFERROR(__xludf.DUMMYFUNCTION("IFS( OR(REGEXMATCH(LOWER(E26), ""sirutar|sundarijal|sitapaila|duwakot|tikathali|bhaktapur|lalitpur|kathmandu|ktm|changunarayan|bageswari|ghalate|tinkune|balkot|tikathali""), REGEXMATCH(LOWER(E26), ""inside valley"")), ""Inside Valley"", REGEXMATCH(LOW"&"ER(E26), ""dharan|pokhara|biratnagar|birgunj|narayanghat|itahari|hetauda|janakpur|madi""), ""Tier 1"", REGEXMATCH(LOWER(E26), ""nepalgunj|butwal|birtamod|dhangadhi|ghorahi|beni|kushma|waling|haldibari|dulegauda|baitadi|bhadrapur|syangja|parbat|myagdi|da"&"ng|nuwakot|jhapa""), ""Tier 2"", TRUE, ""Tier 3"" )"),"Tier 2") -> Tier 2 | M26: Lumbini
B27: =IFERROR(__xludf.DUMMYFUNCTION("""COMPUTED_VALUE"""),45873.19865740741) -> 45873.199 | C27: =IFERROR(__xludf.DUMMYFUNCTION("""COMPUTED_VALUE"""),"Martin half 2 sole 39") -> Martin half 2 sole 39 | D27: =IFERROR(__xludf.DUMMYFUNCTION("""COMPUTED_VALUE"""),"Sudip Darnal") -> Sudip Darnal | E27: =IFERROR(__xludf.DUMMYFUNCTION("""COMPUTED_VALUE"""),"Sangwale ward 4, sindhuli") -> Sangwale ward 4, sindhuli | F27: =IFERROR(__xludf.DUMMYFUNCTION("""COMPUTED_VALUE"""),9.766529083E9) -> 9766529083 | G27: =IFERROR(__xludf.DUMMYFUNCTION("""COMPUTED_VALUE"""),350.0) -> 350 | H27: =IFERROR(__xludf.DUMMYFUNCTION("""COMPUTED_VALUE"""),1350.0) -> 1350 | I27: =IFERROR(__xludf.DUMMYFUNCTION("""COMPUTED_VALUE"""),162.38) -> 162.38 | J27: =IFERROR(__xludf.DUMMYFUNCTION("""COMPUTED_VALUE"""),"Delivered") -> Delivered | K27: =IFERROR(__xludf.DUMMYFUNCTION("""COMPUTED_VALUE"""),45877.46166666667) -> 45877.462 | L27: =IFERROR(__xludf.DUMMYFUNCTION("IFS( OR(REGEXMATCH(LOWER(E27), ""sirutar|sundarijal|sitapaila|duwakot|tikathali|bhaktapur|lalitpur|kathmandu|ktm|changunarayan|bageswari|ghalate|tinkune|balkot|tikathali""), REGEXMATCH(LOWER(E27), ""inside valley"")), ""Inside Valley"", REGEXMATCH(LOW"&"ER(E27), ""dharan|pokhara|biratnagar|birgunj|narayanghat|itahari|hetauda|janakpur|madi""), ""Tier 1"", REGEXMATCH(LOWER(E27), ""nepalgunj|butwal|birtamod|dhangadhi|ghorahi|beni|kushma|waling|haldibari|dulegauda|baitadi|bhadrapur|syangja|parbat|myagdi|da"&"ng|nuwakot|jhapa""), ""Tier 2"", TRUE, ""Tier 3"" )"),"Tier 3") -> Tier 3 | M27: Bagmati
B28: =IFERROR(__xludf.DUMMYFUNCTION("""COMPUTED_VALUE"""),45872.17322916667) -> 45872.173 | C28: =IFERROR(__xludf.DUMMYFUNCTION("""COMPUTED_VALUE"""),"Sr smile 41") -> Sr smile 41 | D28: =IFERROR(__xludf.DUMMYFUNCTION("""COMPUTED_VALUE"""),"Bibash Thapa") -> Bibash Thapa | E28: =IFERROR(__xludf.DUMMYFUNCTION("""COMPUTED_VALUE"""),"Gulariya 6, bardiya") -> Gulariya 6, bardiya | F28: =IFERROR(__xludf.DUMMYFUNCTION("""COMPUTED_VALUE"""),9.816523777E9) -> 9816523777 | G28: =IFERROR(__xludf.DUMMYFUNCTION("""COMPUTED_VALUE"""),450.0) -> 450 | H28: =IFERROR(__xludf.DUMMYFUNCTION("""COMPUTED_VALUE"""),1450.0) -> 1450 | I28: =IFERROR(__xludf.DUMMYFUNCTION("""COMPUTED_VALUE"""),182.63) -> 182.63 | J28: =IFERROR(__xludf.DUMMYFUNCTION("""COMPUTED_VALUE"""),"Delivered") -> Delivered | K28: =IFERROR(__xludf.DUMMYFUNCTION("""COMPUTED_VALUE"""),45873.35476851852) -> 45873.355 | L28: =IFERROR(__xludf.DUMMYFUNCTION("IFS( OR(REGEXMATCH(LOWER(E28), ""sirutar|sundarijal|sitapaila|duwakot|tikathali|bhaktapur|lalitpur|kathmandu|ktm|changunarayan|bageswari|ghalate|tinkune|balkot|tikathali""), REGEXMATCH(LOWER(E28), ""inside valley"")), ""Inside Valley"", REGEXMATCH(LOW"&"ER(E28), ""dharan|pokhara|biratnagar|birgunj|narayanghat|itahari|hetauda|janakpur|madi""), ""Tier 1"", REGEXMATCH(LOWER(E28), ""nepalgunj|butwal|birtamod|dhangadhi|ghorahi|beni|kushma|waling|haldibari|dulegauda|baitadi|bhadrapur|syangja|parbat|myagdi|da"&"ng|nuwakot|jhapa""), ""Tier 2"", TRUE, ""Tier 3"" )"),"Tier 3") -> Tier 3 | M28: Lumbini
B29: =IFERROR(__xludf.DUMMYFUNCTION("""COMPUTED_VALUE"""),45872.17152777778) -> 45872.172 | C29: =IFERROR(__xludf.DUMMYFUNCTION("""COMPUTED_VALUE"""),"Martin nayabasti factory 40") -> Martin nayabasti factory 40 | D29: =IFERROR(__xludf.DUMMYFUNCTION("""COMPUTED_VALUE"""),"Nischal Tamang") -> Nischal Tamang | E29: =IFERROR(__xludf.DUMMYFUNCTION("""COMPUTED_VALUE"""),"Dingla, bhojpur") -> Dingla, bhojpur | F29: =IFERROR(__xludf.DUMMYFUNCTION("""COMPUTED_VALUE"""),9.820330404E9) -> 9820330404 | G29: =IFERROR(__xludf.DUMMYFUNCTION("""COMPUTED_VALUE"""),550.0) -> 550 | H29: =IFERROR(__xludf.DUMMYFUNCTION("""COMPUTED_VALUE"""),1550.0) -> 1550 | I29: =IFERROR(__xludf.DUMMYFUNCTION("""COMPUTED_VALUE"""),212.88) -> 212.88 | J29: =IFERROR(__xludf.DUMMYFUNCTION("""COMPUTED_VALUE"""),"Delivered") -> Delivered | K29: =IFERROR(__xludf.DUMMYFUNCTION("""COMPUTED_VALUE"""),45875.59798611111) -> 45875.598 | L29: =IFERROR(__xludf.DUMMYFUNCTION("IFS( OR(REGEXMATCH(LOWER(E29), ""sirutar|sundarijal|sitapaila|duwakot|tikathali|bhaktapur|lalitpur|kathmandu|ktm|changunarayan|bageswari|ghalate|tinkune|balkot|tikathali""), REGEXMATCH(LOWER(E29), ""inside valley"")), ""Inside Valley"", REGEXMATCH(LOW"&"ER(E29), ""dharan|pokhara|biratnagar|birgunj|narayanghat|itahari|hetauda|janakpur|madi""), ""Tier 1"", REGEXMATCH(LOWER(E29), ""nepalgunj|butwal|birtamod|dhangadhi|ghorahi|beni|kushma|waling|haldibari|dulegauda|baitadi|bhadrapur|syangja|parbat|myagdi|da"&"ng|nuwakot|jhapa""), ""Tier 2"", TRUE, ""Tier 3"" )"),"Tier 3") -> Tier 3 | M29: Koshi
B30: =IFERROR(__xludf.DUMMYFUNCTION("""COMPUTED_VALUE"""),45872.17049768519) -> 45872.171 | C30: =IFERROR(__xludf.DUMMYFUNCTION("""COMPUTED_VALUE"""),"Martin single sole 42") -> Martin single sole 42 | D30: =IFERROR(__xludf.DUMMYFUNCTION("""COMPUTED_VALUE"""),"Rohan Bam") -> Rohan Bam | E30: =IFERROR(__xludf.DUMMYFUNCTION("""COMPUTED_VALUE"""),"Bardageriya gaupalika, ward no 2, kumbiya, kailali") -> Bardageriya gaupalika, ward no 2, kumbiya, kailali | F30: =IFERROR(__xludf.DUMMYFUNCTION("""COMPUTED_VALUE"""),9.815663088E9) -> 9815663088 | G30: =IFERROR(__xludf.DUMMYFUNCTION("""COMPUTED_VALUE"""),350.0) -> 350 | H30: =IFERROR(__xludf.DUMMYFUNCTION("""COMPUTED_VALUE"""),1350.0) -> 1350 | I30: =IFERROR(__xludf.DUMMYFUNCTION("""COMPUTED_VALUE"""),182.38) -> 182.38 | J30: =IFERROR(__xludf.DUMMYFUNCTION("""COMPUTED_VALUE"""),"Delivered") -> Delivered | K30: =IFERROR(__xludf.DUMMYFUNCTION("""COMPUTED_VALUE"""),45877.282442129625) -> 45877.282 | L30: =IFERROR(__xludf.DUMMYFUNCTION("IFS( OR(REGEXMATCH(LOWER(E30), ""sirutar|sundarijal|sitapaila|duwakot|tikathali|bhaktapur|lalitpur|kathmandu|ktm|changunarayan|bageswari|ghalate|tinkune|balkot|tikathali""), REGEXMATCH(LOWER(E30), ""inside valley"")), ""Inside Valley"", REGEXMATCH(LOW"&"ER(E30), ""dharan|pokhara|biratnagar|birgunj|narayanghat|itahari|hetauda|janakpur|madi""), ""Tier 1"", REGEXMATCH(LOWER(E30), ""nepalgunj|butwal|birtamod|dhangadhi|ghorahi|beni|kushma|waling|haldibari|dulegauda|baitadi|bhadrapur|syangja|parbat|myagdi|da"&"ng|nuwakot|jhapa""), ""Tier 2"", TRUE, ""Tier 3"" )"),"Tier 3") -> Tier 3 | M30: Sudurpashchim
B31: =IFERROR(__xludf.DUMMYFUNCTION("""COMPUTED_VALUE"""),45869.2041087963) -> 45869.204 | C31: =IFERROR(__xludf.DUMMYFUNCTION("""COMPUTED_VALUE"""),"Martin single sole 41") -> Martin single sole 41 | D31: =IFERROR(__xludf.DUMMYFUNCTION("""COMPUTED_VALUE"""),"Santosh Pariyar") -> Santosh Pariyar | E31: =IFERROR(__xludf.DUMMYFUNCTION("""COMPUTED_VALUE"""),"Gogli chowk, dang") -> Gogli chowk, dang | F31: =IFERROR(__xludf.DUMMYFUNCTION("""COMPUTED_VALUE"""),9.706877325E9) -> 9706877325 | G31: =IFERROR(__xludf.DUMMYFUNCTION("""COMPUTED_VALUE"""),350.0) -> 350 | H31: =IFERROR(__xludf.DUMMYFUNCTION("""COMPUTED_VALUE"""),1350.0) -> 1350 | I31: =IFERROR(__xludf.DUMMYFUNCTION("""COMPUTED_VALUE"""),182.38) -> 182.38 | J31: =IFERROR(__xludf.DUMMYFUNCTION("""COMPUTED_VALUE"""),"Delivered") -> Delivered | K31: =IFERROR(__xludf.DUMMYFUNCTION("""COMPUTED_VALUE"""),45872.361342592594) -> 45872.361 | L31: =IFERROR(__xludf.DUMMYFUNCTION("IFS( OR(REGEXMATCH(LOWER(E31), ""sirutar|sundarijal|sitapaila|duwakot|tikathali|bhaktapur|lalitpur|kathmandu|ktm|changunarayan|bageswari|ghalate|tinkune|balkot|tikathali""), REGEXMATCH(LOWER(E31), ""inside valley"")), ""Inside Valley"", REGEXMATCH(LOW"&"ER(E31), ""dharan|pokhara|biratnagar|birgunj|narayanghat|itahari|hetauda|janakpur|madi""), ""Tier 1"", REGEXMATCH(LOWER(E31), ""nepalgunj|butwal|birtamod|dhangadhi|ghorahi|beni|kushma|waling|haldibari|dulegauda|baitadi|bhadrapur|syangja|parbat|myagdi|da"&"ng|nuwakot|jhapa""), ""Tier 2"", TRUE, ""Tier 3"" )"),"Tier 2") -> Tier 2 | M31: Lumbini
B32: =IFERROR(__xludf.DUMMYFUNCTION("""COMPUTED_VALUE"""),45869.20298611111) -> 45869.203 | C32: =IFERROR(__xludf.DUMMYFUNCTION("""COMPUTED_VALUE"""),"Sr gray 42") -> Sr gray 42 | D32: =IFERROR(__xludf.DUMMYFUNCTION("""COMPUTED_VALUE"""),"Subarth Kunwar") -> Subarth Kunwar | E32: =IFERROR(__xludf.DUMMYFUNCTION("""COMPUTED_VALUE"""),"Baneshwor soa and swimming pool or ananda events and meeting") -> Baneshwor soa and swimming pool or ananda events and meeting | F32: =IFERROR(__xludf.DUMMYFUNCTION("""COMPUTED_VALUE"""),9.763313182E9) -> 9763313182 | G32: =IFERROR(__xludf.DUMMYFUNCTION("""COMPUTED_VALUE"""),400.0) -> 400 | H32: =IFERROR(__xludf.DUMMYFUNCTION("""COMPUTED_VALUE"""),1400.0) -> 1400 | I32: =IFERROR(__xludf.DUMMYFUNCTION("""COMPUTED_VALUE"""),102.5) -> 102.5 | J32: =IFERROR(__xludf.DUMMYFUNCTION("""COMPUTED_VALUE"""),"Delivered") -> Delivered | K32: =IFERROR(__xludf.DUMMYFUNCTION("""COMPUTED_VALUE"""),45869.45903935185) -> 45869.459 | L32: =IFERROR(__xludf.DUMMYFUNCTION("IFS( OR(REGEXMATCH(LOWER(E32), ""sirutar|sundarijal|sitapaila|duwakot|tikathali|bhaktapur|lalitpur|kathmandu|ktm|changunarayan|bageswari|ghalate|tinkune|balkot|tikathali""), REGEXMATCH(LOWER(E32), ""inside valley"")), ""Inside Valley"", REGEXMATCH(LOW"&"ER(E32), ""dharan|pokhara|biratnagar|birgunj|narayanghat|itahari|hetauda|janakpur|madi""), ""Tier 1"", REGEXMATCH(LOWER(E32), ""nepalgunj|butwal|birtamod|dhangadhi|ghorahi|beni|kushma|waling|haldibari|dulegauda|baitadi|bhadrapur|syangja|parbat|myagdi|da"&"ng|nuwakot|jhapa""), ""Tier 2"", TRUE, ""Tier 3"" )"),"Tier 3") -> Tier 3 | M32: Bagmati
B33: =IFERROR(__xludf.DUMMYFUNCTION("""COMPUTED_VALUE"""),45867.21146990741) -> 45867.211 | C33: =IFERROR(__xludf.DUMMYFUNCTION("""COMPUTED_VALUE"""),"Nie 11 red and black") -> Nie 11 red and black | D33: =IFERROR(__xludf.DUMMYFUNCTION("""COMPUTED_VALUE"""),"Raj Thegim Limbu") -> Raj Thegim Limbu | E33: =IFERROR(__xludf.DUMMYFUNCTION("""COMPUTED_VALUE"""),"Jalthal, jhapa") -> Jalthal, jhapa | F33: =IFERROR(__xludf.DUMMYFUNCTION("""COMPUTED_VALUE"""),9.814977789E9) -> 9814977789 | G33: =IFERROR(__xludf.DUMMYFUNCTION("""COMPUTED_VALUE"""),700.0) -> 700 | H33: =IFERROR(__xludf.DUMMYFUNCTION("""COMPUTED_VALUE"""),2500.0) -> 2500 | I33: =IFERROR(__xludf.DUMMYFUNCTION("""COMPUTED_VALUE"""),185.25) -> 185.25 | J33: =IFERROR(__xludf.DUMMYFUNCTION("""COMPUTED_VALUE"""),"Delivered") -> Delivered | K33: =IFERROR(__xludf.DUMMYFUNCTION("""COMPUTED_VALUE"""),45870.19578703704) -> 45870.196 | L33: =IFERROR(__xludf.DUMMYFUNCTION("IFS( OR(REGEXMATCH(LOWER(E33), ""sirutar|sundarijal|sitapaila|duwakot|tikathali|bhaktapur|lalitpur|kathmandu|ktm|changunarayan|bageswari|ghalate|tinkune|balkot|tikathali""), REGEXMATCH(LOWER(E33), ""inside valley"")), ""Inside Valley"", REGEXMATCH(LOW"&"ER(E33), ""dharan|pokhara|biratnagar|birgunj|narayanghat|itahari|hetauda|janakpur|madi""), ""Tier 1"", REGEXMATCH(LOWER(E33), ""nepalgunj|butwal|birtamod|dhangadhi|ghorahi|beni|kushma|waling|haldibari|dulegauda|baitadi|bhadrapur|syangja|parbat|myagdi|da"&"ng|nuwakot|jhapa""), ""Tier 2"", TRUE, ""Tier 3"" )"),"Tier 2") -> Tier 2 | M33: Koshi
B34: =IFERROR(__xludf.DUMMYFUNCTION("""COMPUTED_VALUE"""),45867.20958333333) -> 45867.21 | C34: =IFERROR(__xludf.DUMMYFUNCTION("""COMPUTED_VALUE"""),"White Nike 37") -> White Nike 37 | D34: =IFERROR(__xludf.DUMMYFUNCTION("""COMPUTED_VALUE"""),"Gaurav Jaiswal") -> Gaurav Jaiswal | E34: =IFERROR(__xludf.DUMMYFUNCTION("""COMPUTED_VALUE"""),"Nepalgunj, dhamboji chowk siddhartha Bank najik") -> Nepalgunj, dhamboji chowk siddhartha Bank najik | F34: =IFERROR(__xludf.DUMMYFUNCTION("""COMPUTED_VALUE"""),9.762065388E9) -> 9762065388 | G34: =IFERROR(__xludf.DUMMYFUNCTION("""COMPUTED_VALUE"""),350.0) -> 350 | H34: =IFERROR(__xludf.DUMMYFUNCTION("""COMPUTED_VALUE"""),1350.0) -> 1350 | I34: =IFERROR(__xludf.DUMMYFUNCTION("""COMPUTED_VALUE"""),212.38) -> 212.38 | J34: =IFERROR(__xludf.DUMMYFUNCTION("""COMPUTED_VALUE"""),"Delivered") -> Delivered | K34: =IFERROR(__xludf.DUMMYFUNCTION("""COMPUTED_VALUE"""),45872.44072916667) -> 45872.441 | L34: =IFERROR(__xludf.DUMMYFUNCTION("IFS( OR(REGEXMATCH(LOWER(E34), ""sirutar|sundarijal|sitapaila|duwakot|tikathali|bhaktapur|lalitpur|kathmandu|ktm|changunarayan|bageswari|ghalate|tinkune|balkot|tikathali""), REGEXMATCH(LOWER(E34), ""inside valley"")), ""Inside Valley"", REGEXMATCH(LOW"&"ER(E34), ""dharan|pokhara|biratnagar|birgunj|narayanghat|itahari|hetauda|janakpur|madi""), ""Tier 1"", REGEXMATCH(LOWER(E34), ""nepalgunj|butwal|birtamod|dhangadhi|ghorahi|beni|kushma|waling|haldibari|dulegauda|baitadi|bhadrapur|syangja|parbat|myagdi|da"&"ng|nuwakot|jhapa""), ""Tier 2"", TRUE, ""Tier 3"" )"),"Tier 2") -> Tier 2 | M34: Lumbini
B35: =IFERROR(__xludf.DUMMYFUNCTION("""COMPUTED_VALUE"""),45865.19533564815) -> 45865.195 | C35: =IFERROR(__xludf.DUMMYFUNCTION("""COMPUTED_VALUE"""),"Martin 3 sole size 39") -> Martin 3 sole size 39 | D35: =IFERROR(__xludf.DUMMYFUNCTION("""COMPUTED_VALUE"""),"Manoj") -> Manoj | E35: =IFERROR(__xludf.DUMMYFUNCTION("""COMPUTED_VALUE"""),"Ktm, sundarijal dobato chowk") -> Ktm, sundarijal dobato chowk | F35: =IFERROR(__xludf.DUMMYFUNCTION("""COMPUTED_VALUE"""),9.768966994E9) -> 9768966994 | G35: =IFERROR(__xludf.DUMMYFUNCTION("""COMPUTED_VALUE"""),500.0) -> 500 | H35: =IFERROR(__xludf.DUMMYFUNCTION("""COMPUTED_VALUE"""),1500.0) -> 1500 | I35: =IFERROR(__xludf.DUMMYFUNCTION("""COMPUTED_VALUE"""),102.75) -> 102.75 | J35: =IFERROR(__xludf.DUMMYFUNCTION("""COMPUTED_VALUE"""),"Delivered") -> Delivered | K35: =IFERROR(__xludf.DUMMYFUNCTION("""COMPUTED_VALUE"""),45867.2159837963) -> 45867.216 | L35: =IFERROR(__xludf.DUMMYFUNCTION("IFS( OR(REGEXMATCH(LOWER(E35), ""sirutar|sundarijal|sitapaila|duwakot|tikathali|bhaktapur|lalitpur|kathmandu|ktm|changunarayan|bageswari|ghalate|tinkune|balkot|tikathali""), REGEXMATCH(LOWER(E35), ""inside valley"")), ""Inside Valley"", REGEXMATCH(LOW"&"ER(E35), ""dharan|pokhara|biratnagar|birgunj|narayanghat|itahari|hetauda|janakpur|madi""), ""Tier 1"", REGEXMATCH(LOWER(E35), ""nepalgunj|butwal|birtamod|dhangadhi|ghorahi|beni|kushma|waling|haldibari|dulegauda|baitadi|bhadrapur|syangja|parbat|myagdi|da"&"ng|nuwakot|jhapa""), ""Tier 2"", TRUE, ""Tier 3"" )"),"Inside Valley") -> Inside Valley | M35: Bagmati
B36: =IFERROR(__xludf.DUMMYFUNCTION("""COMPUTED_VALUE"""),45865.183171296296) -> 45865.183 | C36: =IFERROR(__xludf.DUMMYFUNCTION("""COMPUTED_VALUE"""),"Chelsea size 41") -> Chelsea size 41 | D36: =IFERROR(__xludf.DUMMYFUNCTION("""COMPUTED_VALUE"""),"Sudesh Shrestha") -> Sudesh Shrestha | E36: =IFERROR(__xludf.DUMMYFUNCTION("""COMPUTED_VALUE"""),"Sundar haraicha 12, biratchowk Road no 12") -> Sundar haraicha 12, biratchowk Road no 12 | F36: =IFERROR(__xludf.DUMMYFUNCTION("""COMPUTED_VALUE"""),9.862232928E9) -> 9862232928 | G36: =IFERROR(__xludf.DUMMYFUNCTION("""COMPUTED_VALUE"""),450.0) -> 450 | H36: =IFERROR(__xludf.DUMMYFUNCTION("""COMPUTED_VALUE"""),1350.0) -> 1350 | I36: =IFERROR(__xludf.DUMMYFUNCTION("""COMPUTED_VALUE"""),162.38) -> 162.38 | J36: =IFERROR(__xludf.DUMMYFUNCTION("""COMPUTED_VALUE"""),"Delivered") -> Delivered | K36: =IFERROR(__xludf.DUMMYFUNCTION("""COMPUTED_VALUE"""),45867.38013888889) -> 45867.38 | L36: =IFERROR(__xludf.DUMMYFUNCTION("IFS( OR(REGEXMATCH(LOWER(E36), ""sirutar|sundarijal|sitapaila|duwakot|tikathali|bhaktapur|lalitpur|kathmandu|ktm|changunarayan|bageswari|ghalate|tinkune|balkot|tikathali""), REGEXMATCH(LOWER(E36), ""inside valley"")), ""Inside Valley"", REGEXMATCH(LOW"&"ER(E36), ""dharan|pokhara|biratnagar|birgunj|narayanghat|itahari|hetauda|janakpur|madi""), ""Tier 1"", REGEXMATCH(LOWER(E36), ""nepalgunj|butwal|birtamod|dhangadhi|ghorahi|beni|kushma|waling|haldibari|dulegauda|baitadi|bhadrapur|syangja|parbat|myagdi|da"&"ng|nuwakot|jhapa""), ""Tier 2"", TRUE, ""Tier 3"" )"),"Tier 3") -> Tier 3 | M36: Koshi
B37: =IFERROR(__xludf.DUMMYFUNCTION("""COMPUTED_VALUE"""),45865.18116898148) -> 45865.181 | C37: =IFERROR(__xludf.DUMMYFUNCTION("""COMPUTED_VALUE"""),"Sb dunk 41") -> Sb dunk 41 | D37: =IFERROR(__xludf.DUMMYFUNCTION("""COMPUTED_VALUE"""),"Sijan Shrestha") -> Sijan Shrestha | E37: =IFERROR(__xludf.DUMMYFUNCTION("""COMPUTED_VALUE"""),"Beni, myagdi") -> Beni, myagdi | F37: =IFERROR(__xludf.DUMMYFUNCTION("""COMPUTED_VALUE"""),9.84764997E9) -> 9847649970 | G37: =IFERROR(__xludf.DUMMYFUNCTION("""COMPUTED_VALUE"""),400.0) -> 400 | H37: =IFERROR(__xludf.DUMMYFUNCTION("""COMPUTED_VALUE"""),1400.0) -> 1400 | I37: =IFERROR(__xludf.DUMMYFUNCTION("""COMPUTED_VALUE"""),212.5) -> 212.5 | J37: =IFERROR(__xludf.DUMMYFUNCTION("""COMPUTED_VALUE"""),"Delivered") -> Delivered | K37: =IFERROR(__xludf.DUMMYFUNCTION("""COMPUTED_VALUE"""),45867.280752314815) -> 45867.281 | L37: =IFERROR(__xludf.DUMMYFUNCTION("IFS( OR(REGEXMATCH(LOWER(E37), ""sirutar|sundarijal|sitapaila|duwakot|tikathali|bhaktapur|lalitpur|kathmandu|ktm|changunarayan|bageswari|ghalate|tinkune|balkot|tikathali""), REGEXMATCH(LOWER(E37), ""inside valley"")), ""Inside Valley"", REGEXMATCH(LOW"&"ER(E37), ""dharan|pokhara|biratnagar|birgunj|narayanghat|itahari|hetauda|janakpur|madi""), ""Tier 1"", REGEXMATCH(LOWER(E37), ""nepalgunj|butwal|birtamod|dhangadhi|ghorahi|beni|kushma|waling|haldibari|dulegauda|baitadi|bhadrapur|syangja|parbat|myagdi|da"&"ng|nuwakot|jhapa""), ""Tier 2"", TRUE, ""Tier 3"" )"),"Tier 2") -> Tier 2 | M37: Gandaki
B38: =IFERROR(__xludf.DUMMYFUNCTION("""COMPUTED_VALUE"""),45865.17979166667) -> 45865.18 | C38: =IFERROR(__xludf.DUMMYFUNCTION("""COMPUTED_VALUE"""),"Red Nike ") -> Red Nike | D38: =IFERROR(__xludf.DUMMYFUNCTION("""COMPUTED_VALUE"""),"Aayush Panthi") -> Aayush Panthi | E38: =IFERROR(__xludf.DUMMYFUNCTION("""COMPUTED_VALUE"""),"Butwal, bhakwari 7, lec college side") -> Butwal, bhakwari 7, lec college side | F38: =IFERROR(__xludf.DUMMYFUNCTION("""COMPUTED_VALUE"""),9.844755593E9) -> 9844755593 | G38: =IFERROR(__xludf.DUMMYFUNCTION("""COMPUTED_VALUE"""),350.0) -> 350 | H38: =IFERROR(__xludf.DUMMYFUNCTION("""COMPUTED_VALUE"""),1350.0) -> 1350 | I38: =IFERROR(__xludf.DUMMYFUNCTION("""COMPUTED_VALUE"""),182.38) -> 182.38 | J38: =IFERROR(__xludf.DUMMYFUNCTION("""COMPUTED_VALUE"""),"Delivered") -> Delivered | K38: =IFERROR(__xludf.DUMMYFUNCTION("""COMPUTED_VALUE"""),45866.38072916667) -> 45866.381 | L38: =IFERROR(__xludf.DUMMYFUNCTION("IFS( OR(REGEXMATCH(LOWER(E38), ""sirutar|sundarijal|sitapaila|duwakot|tikathali|bhaktapur|lalitpur|kathmandu|ktm|changunarayan|bageswari|ghalate|tinkune|balkot|tikathali""), REGEXMATCH(LOWER(E38), ""inside valley"")), ""Inside Valley"", REGEXMATCH(LOW"&"ER(E38), ""dharan|pokhara|biratnagar|birgunj|narayanghat|itahari|hetauda|janakpur|madi""), ""Tier 1"", REGEXMATCH(LOWER(E38), ""nepalgunj|butwal|birtamod|dhangadhi|ghorahi|beni|kushma|waling|haldibari|dulegauda|baitadi|bhadrapur|syangja|parbat|myagdi|da"&"ng|nuwakot|jhapa""), ""Tier 2"", TRUE, ""Tier 3"" )"),"Tier 2") -> Tier 2 | M38: Lumbini
B39: =IFERROR(__xludf.DUMMYFUNCTION("""COMPUTED_VALUE"""),45865.17822916667) -> 45865.178 | C39: =IFERROR(__xludf.DUMMYFUNCTION("""COMPUTED_VALUE"""),"Dark brown 40") -> Dark brown 40 | D39: =IFERROR(__xludf.DUMMYFUNCTION("""COMPUTED_VALUE"""),"Govinda Khatiwada") -> Govinda Khatiwada | E39: =IFERROR(__xludf.DUMMYFUNCTION("""COMPUTED_VALUE"""),"Salleri bazar, solukhumbu") -> Salleri bazar, solukhumbu | F39: =IFERROR(__xludf.DUMMYFUNCTION("""COMPUTED_VALUE"""),9.869667233E9) -> 9869667233 | G39: =IFERROR(__xludf.DUMMYFUNCTION("""COMPUTED_VALUE"""),320.0) -> 320 | H39: =IFERROR(__xludf.DUMMYFUNCTION("""COMPUTED_VALUE"""),1320.0) -> 1320 | I39: =IFERROR(__xludf.DUMMYFUNCTION("""COMPUTED_VALUE"""),212.3) -> 212.3 | J39: =IFERROR(__xludf.DUMMYFUNCTION("""COMPUTED_VALUE"""),"Delivered") -> Delivered | K39: =IFERROR(__xludf.DUMMYFUNCTION("""COMPUTED_VALUE"""),45867.60194444444) -> 45867.602 | L39: =IFERROR(__xludf.DUMMYFUNCTION("IFS( OR(REGEXMATCH(LOWER(E39), ""sirutar|sundarijal|sitapaila|duwakot|tikathali|bhaktapur|lalitpur|kathmandu|ktm|changunarayan|bageswari|ghalate|tinkune|balkot|tikathali""), REGEXMATCH(LOWER(E39), ""inside valley"")), ""Inside Valley"", REGEXMATCH(LOW"&"ER(E39), ""dharan|pokhara|biratnagar|birgunj|narayanghat|itahari|hetauda|janakpur|madi""), ""Tier 1"", REGEXMATCH(LOWER(E39), ""nepalgunj|butwal|birtamod|dhangadhi|ghorahi|beni|kushma|waling|haldibari|dulegauda|baitadi|bhadrapur|syangja|parbat|myagdi|da"&"ng|nuwakot|jhapa""), ""Tier 2"", TRUE, ""Tier 3"" )"),"Tier 3") -> Tier 3 | M39: Koshi
B40: =IFERROR(__xludf.DUMMYFUNCTION("""COMPUTED_VALUE"""),45864.20482638889) -> 45864.205 | C40: =IFERROR(__xludf.DUMMYFUNCTION("""COMPUTED_VALUE"""),"Size 39 Martin 3 sole") -> Size 39 Martin 3 sole | D40: =IFERROR(__xludf.DUMMYFUNCTION("""COMPUTED_VALUE"""),"Rohan") -> Rohan | E40: =IFERROR(__xludf.DUMMYFUNCTION("""COMPUTED_VALUE"""),"Manakamana suit hotel, gogechaur, banepa") -> Manakamana suit hotel, gogechaur, banepa | F40: =IFERROR(__xludf.DUMMYFUNCTION("""COMPUTED_VALUE"""),9.701538165E9) -> 9701538165 | G40: =IFERROR(__xludf.DUMMYFUNCTION("""COMPUTED_VALUE"""),600.0) -> 600 | H40: =IFERROR(__xludf.DUMMYFUNCTION("""COMPUTED_VALUE"""),1600.0) -> 1600 | I40: =IFERROR(__xludf.DUMMYFUNCTION("""COMPUTED_VALUE"""),163.0) -> 163 | J40: =IFERROR(__xludf.DUMMYFUNCTION("""COMPUTED_VALUE"""),"Delivered") -> Delivered | K40: =IFERROR(__xludf.DUMMYFUNCTION("""COMPUTED_VALUE"""),45865.5271875) -> 45865.527 | L40: =IFERROR(__xludf.DUMMYFUNCTION("IFS( OR(REGEXMATCH(LOWER(E40), ""sirutar|sundarijal|sitapaila|duwakot|tikathali|bhaktapur|lalitpur|kathmandu|ktm|changunarayan|bageswari|ghalate|tinkune|balkot|tikathali""), REGEXMATCH(LOWER(E40), ""inside valley"")), ""Inside Valley"", REGEXMATCH(LOW"&"ER(E40), ""dharan|pokhara|biratnagar|birgunj|narayanghat|itahari|hetauda|janakpur|madi""), ""Tier 1"", REGEXMATCH(LOWER(E40), ""nepalgunj|butwal|birtamod|dhangadhi|ghorahi|beni|kushma|waling|haldibari|dulegauda|baitadi|bhadrapur|syangja|parbat|myagdi|da"&"ng|nuwakot|jhapa""), ""Tier 2"", TRUE, ""Tier 3"" )"),"Tier 3") -> Tier 3 | M40: Bagmati
B41: =IFERROR(__xludf.DUMMYFUNCTION("""COMPUTED_VALUE"""),45864.203668981485) -> 45864.204 | C41: =IFERROR(__xludf.DUMMYFUNCTION("""COMPUTED_VALUE"""),"Single sole Martin 43") -> Single sole Martin 43 | D41: =IFERROR(__xludf.DUMMYFUNCTION("""COMPUTED_VALUE"""),"Ankit Rajbanshi") -> Ankit Rajbanshi | E41: =IFERROR(__xludf.DUMMYFUNCTION("""COMPUTED_VALUE"""),"Mechinagar-10, dhulabari, jhapa") -> Mechinagar-10, dhulabari, jhapa | F41: =IFERROR(__xludf.DUMMYFUNCTION("""COMPUTED_VALUE"""),9.827940827E9) -> 9827940827 | G41: =IFERROR(__xludf.DUMMYFUNCTION("""COMPUTED_VALUE"""),350.0) -> 350 | H41: =IFERROR(__xludf.DUMMYFUNCTION("""COMPUTED_VALUE"""),1350.0) -> 1350 | I41: =IFERROR(__xludf.DUMMYFUNCTION("""COMPUTED_VALUE"""),182.38) -> 182.38 | J41: =IFERROR(__xludf.DUMMYFUNCTION("""COMPUTED_VALUE"""),"Delivered") -> Delivered | K41: =IFERROR(__xludf.DUMMYFUNCTION("""COMPUTED_VALUE"""),45866.45042824074) -> 45866.45 | L41: =IFERROR(__xludf.DUMMYFUNCTION("IFS( OR(REGEXMATCH(LOWER(E41), ""sirutar|sundarijal|sitapaila|duwakot|tikathali|bhaktapur|lalitpur|kathmandu|ktm|changunarayan|bageswari|ghalate|tinkune|balkot|tikathali""), REGEXMATCH(LOWER(E41), ""inside valley"")), ""Inside Valley"", REGEXMATCH(LOW"&"ER(E41), ""dharan|pokhara|biratnagar|birgunj|narayanghat|itahari|hetauda|janakpur|madi""), ""Tier 1"", REGEXMATCH(LOWER(E41), ""nepalgunj|butwal|birtamod|dhangadhi|ghorahi|beni|kushma|waling|haldibari|dulegauda|baitadi|bhadrapur|syangja|parbat|myagdi|da"&"ng|nuwakot|jhapa""), ""Tier 2"", TRUE, ""Tier 3"" )"),"Tier 2") -> Tier 2 | M41: Koshi
B42: =IFERROR(__xludf.DUMMYFUNCTION("""COMPUTED_VALUE"""),45864.191504629634) -> 45864.192 | C42: =IFERROR(__xludf.DUMMYFUNCTION("""COMPUTED_VALUE"""),"Brown 40") -> Brown 40 | D42: =IFERROR(__xludf.DUMMYFUNCTION("""COMPUTED_VALUE"""),"Toshu Sah") -> Toshu Sah | E42: =IFERROR(__xludf.DUMMYFUNCTION("""COMPUTED_VALUE"""),"Chyasal, lalitpur") -> Chyasal, lalitpur | F42: =IFERROR(__xludf.DUMMYFUNCTION("""COMPUTED_VALUE"""),9.700310751E9) -> 9700310751 | G42: =IFERROR(__xludf.DUMMYFUNCTION("""COMPUTED_VALUE"""),300.0) -> 300 | H42: =IFERROR(__xludf.DUMMYFUNCTION("""COMPUTED_VALUE"""),1300.0) -> 1300 | I42: =IFERROR(__xludf.DUMMYFUNCTION("""COMPUTED_VALUE"""),102.25) -> 102.25 | J42: =IFERROR(__xludf.DUMMYFUNCTION("""COMPUTED_VALUE"""),"Delivered") -> Delivered | K42: =IFERROR(__xludf.DUMMYFUNCTION("""COMPUTED_VALUE"""),45865.17994212963) -> 45865.18 | L42: =IFERROR(__xludf.DUMMYFUNCTION("IFS( OR(REGEXMATCH(LOWER(E42), ""sirutar|sundarijal|sitapaila|duwakot|tikathali|bhaktapur|lalitpur|kathmandu|ktm|changunarayan|bageswari|ghalate|tinkune|balkot|tikathali""), REGEXMATCH(LOWER(E42), ""inside valley"")), ""Inside Valley"", REGEXMATCH(LOW"&"ER(E42), ""dharan|pokhara|biratnagar|birgunj|narayanghat|itahari|hetauda|janakpur|madi""), ""Tier 1"", REGEXMATCH(LOWER(E42), ""nepalgunj|butwal|birtamod|dhangadhi|ghorahi|beni|kushma|waling|haldibari|dulegauda|baitadi|bhadrapur|syangja|parbat|myagdi|da"&"ng|nuwakot|jhapa""), ""Tier 2"", TRUE, ""Tier 3"" )"),"Inside Valley") -> Inside Valley | M42: Bagmati
B43: =IFERROR(__xludf.DUMMYFUNCTION("""COMPUTED_VALUE"""),45863.22542824074) -> 45863.225 | C43: =IFERROR(__xludf.DUMMYFUNCTION("""COMPUTED_VALUE"""),"Martin half double sole") -> Martin half double sole | D43: =IFERROR(__xludf.DUMMYFUNCTION("""COMPUTED_VALUE"""),"Abhishek rokaya") -> Abhishek rokaya | E43: =IFERROR(__xludf.DUMMYFUNCTION("""COMPUTED_VALUE"""),"Durbarmarg , yakyeti marg Jane bato") -> Durbarmarg , yakyeti marg Jane bato | F43: =IFERROR(__xludf.DUMMYFUNCTION("""COMPUTED_VALUE"""),9.822767923E9) -> 9822767923 | G43: =IFERROR(__xludf.DUMMYFUNCTION("""COMPUTED_VALUE"""),400.0) -> 400 | H43: =IFERROR(__xludf.DUMMYFUNCTION("""COMPUTED_VALUE"""),1300.0) -> 1300 | I43: =IFERROR(__xludf.DUMMYFUNCTION("""COMPUTED_VALUE"""),102.25) -> 102.25 | J43: =IFERROR(__xludf.DUMMYFUNCTION("""COMPUTED_VALUE"""),"Delivered") -> Delivered | K43: =IFERROR(__xludf.DUMMYFUNCTION("""COMPUTED_VALUE"""),45863.423414351855) -> 45863.423 | L43: =IFERROR(__xludf.DUMMYFUNCTION("IFS( OR(REGEXMATCH(LOWER(E43), ""sirutar|sundarijal|sitapaila|duwakot|tikathali|bhaktapur|lalitpur|kathmandu|ktm|changunarayan|bageswari|ghalate|tinkune|balkot|tikathali""), REGEXMATCH(LOWER(E43), ""inside valley"")), ""Inside Valley"", REGEXMATCH(LOW"&"ER(E43), ""dharan|pokhara|biratnagar|birgunj|narayanghat|itahari|hetauda|janakpur|madi""), ""Tier 1"", REGEXMATCH(LOWER(E43), ""nepalgunj|butwal|birtamod|dhangadhi|ghorahi|beni|kushma|waling|haldibari|dulegauda|baitadi|bhadrapur|syangja|parbat|myagdi|da"&"ng|nuwakot|jhapa""), ""Tier 2"", TRUE, ""Tier 3"" )"),"Tier 3") -> Tier 3 | M43: Bagmati
B44: =IFERROR(__xludf.DUMMYFUNCTION("""COMPUTED_VALUE"""),45863.22326388889) -> 45863.223 | C44: =IFERROR(__xludf.DUMMYFUNCTION("""COMPUTED_VALUE"""),"Sky blue Nike size 42") -> Sky blue Nike size 42 | D44: =IFERROR(__xludf.DUMMYFUNCTION("""COMPUTED_VALUE"""),"Rohan Grg Prajoo") -> Rohan Grg Prajoo | E44: =IFERROR(__xludf.DUMMYFUNCTION("""COMPUTED_VALUE"""),"Tersapatti 3 pokhara") -> Tersapatti 3 pokhara | F44: =IFERROR(__xludf.DUMMYFUNCTION("""COMPUTED_VALUE"""),9.705554376E9) -> 9705554376 | G44: =IFERROR(__xludf.DUMMYFUNCTION("""COMPUTED_VALUE"""),350.0) -> 350 | H44: =IFERROR(__xludf.DUMMYFUNCTION("""COMPUTED_VALUE"""),1350.0) -> 1350 | I44: =IFERROR(__xludf.DUMMYFUNCTION("""COMPUTED_VALUE"""),162.38) -> 162.38 | J44: =IFERROR(__xludf.DUMMYFUNCTION("""COMPUTED_VALUE"""),"Delivered") -> Delivered | K44: =IFERROR(__xludf.DUMMYFUNCTION("""COMPUTED_VALUE"""),45866.33039351852) -> 45866.33 | L44: =IFERROR(__xludf.DUMMYFUNCTION("IFS( OR(REGEXMATCH(LOWER(E44), ""sirutar|sundarijal|sitapaila|duwakot|tikathali|bhaktapur|lalitpur|kathmandu|ktm|changunarayan|bageswari|ghalate|tinkune|balkot|tikathali""), REGEXMATCH(LOWER(E44), ""inside valley"")), ""Inside Valley"", REGEXMATCH(LOW"&"ER(E44), ""dharan|pokhara|biratnagar|birgunj|narayanghat|itahari|hetauda|janakpur|madi""), ""Tier 1"", REGEXMATCH(LOWER(E44), ""nepalgunj|butwal|birtamod|dhangadhi|ghorahi|beni|kushma|waling|haldibari|dulegauda|baitadi|bhadrapur|syangja|parbat|myagdi|da"&"ng|nuwakot|jhapa""), ""Tier 2"", TRUE, ""Tier 3"" )"),"Tier 1") -> Tier 1 | M44: Gandaki
B45: =IFERROR(__xludf.DUMMYFUNCTION("""COMPUTED_VALUE"""),45863.203414351854) -> 45863.203 | C45: =IFERROR(__xludf.DUMMYFUNCTION("""COMPUTED_VALUE"""),"Red Nike 43") -> Red Nike 43 | D45: =IFERROR(__xludf.DUMMYFUNCTION("""COMPUTED_VALUE"""),"Sagar") -> Sagar | E45: =IFERROR(__xludf.DUMMYFUNCTION("""COMPUTED_VALUE"""),"Dhangadhi bhakat chowk, ward no. 9") -> Dhangadhi bhakat chowk, ward no. 9 | F45: =IFERROR(__xludf.DUMMYFUNCTION("""COMPUTED_VALUE"""),9.814660801E9) -> 9814660801 | G45: =IFERROR(__xludf.DUMMYFUNCTION("""COMPUTED_VALUE"""),350.0) -> 350 | H45: =IFERROR(__xludf.DUMMYFUNCTION("""COMPUTED_VALUE"""),1350.0) -> 1350 | I45: =IFERROR(__xludf.DUMMYFUNCTION("""COMPUTED_VALUE"""),182.38) -> 182.38 | J45: =IFERROR(__xludf.DUMMYFUNCTION("""COMPUTED_VALUE"""),"Delivered") -> Delivered | K45: =IFERROR(__xludf.DUMMYFUNCTION("""COMPUTED_VALUE"""),45865.2788425926) -> 45865.279 | L45: =IFERROR(__xludf.DUMMYFUNCTION("IFS( OR(REGEXMATCH(LOWER(E45), ""sirutar|sundarijal|sitapaila|duwakot|tikathali|bhaktapur|lalitpur|kathmandu|ktm|changunarayan|bageswari|ghalate|tinkune|balkot|tikathali""), REGEXMATCH(LOWER(E45), ""inside valley"")), ""Inside Valley"", REGEXMATCH(LOW"&"ER(E45), ""dharan|pokhara|biratnagar|birgunj|narayanghat|itahari|hetauda|janakpur|madi""), ""Tier 1"", REGEXMATCH(LOWER(E45), ""nepalgunj|butwal|birtamod|dhangadhi|ghorahi|beni|kushma|waling|haldibari|dulegauda|baitadi|bhadrapur|syangja|parbat|myagdi|da"&"ng|nuwakot|jhapa""), ""Tier 2"", TRUE, ""Tier 3"" )"),"Tier 2") -> Tier 2 | M45: Sudurpashchim
B46: =IFERROR(__xludf.DUMMYFUNCTION("""COMPUTED_VALUE"""),45863.20244212963) -> 45863.202 | C46: =IFERROR(__xludf.DUMMYFUNCTION("""COMPUTED_VALUE"""),"Nike white and vans 41") -> Nike white and vans 41 | D46: =IFERROR(__xludf.DUMMYFUNCTION("""COMPUTED_VALUE"""),"Manoj Parsai") -> Manoj Parsai | E46: =IFERROR(__xludf.DUMMYFUNCTION("""COMPUTED_VALUE"""),"Nayabazar 10, pokhara, kaski") -> Nayabazar 10, pokhara, kaski | F46: =IFERROR(__xludf.DUMMYFUNCTION("""COMPUTED_VALUE"""),9.816148089E9) -> 9816148089 | G46: =IFERROR(__xludf.DUMMYFUNCTION("""COMPUTED_VALUE"""),950.0) -> 950 | H46: =IFERROR(__xludf.DUMMYFUNCTION("""COMPUTED_VALUE"""),2550.0) -> 2550 | I46: =IFERROR(__xludf.DUMMYFUNCTION("""COMPUTED_VALUE"""),165.38) -> 165.38 | J46: =IFERROR(__xludf.DUMMYFUNCTION("""COMPUTED_VALUE"""),"Delivered") -> Delivered | K46: =IFERROR(__xludf.DUMMYFUNCTION("""COMPUTED_VALUE"""),45864.416226851856) -> 45864.416 | L46: =IFERROR(__xludf.DUMMYFUNCTION("IFS( OR(REGEXMATCH(LOWER(E46), ""sirutar|sundarijal|sitapaila|duwakot|tikathali|bhaktapur|lalitpur|kathmandu|ktm|changunarayan|bageswari|ghalate|tinkune|balkot|tikathali""), REGEXMATCH(LOWER(E46), ""inside valley"")), ""Inside Valley"", REGEXMATCH(LOW"&"ER(E46), ""dharan|pokhara|biratnagar|birgunj|narayanghat|itahari|hetauda|janakpur|madi""), ""Tier 1"", REGEXMATCH(LOWER(E46), ""nepalgunj|butwal|birtamod|dhangadhi|ghorahi|beni|kushma|waling|haldibari|dulegauda|baitadi|bhadrapur|syangja|parbat|myagdi|da"&"ng|nuwakot|jhapa""), ""Tier 2"", TRUE, ""Tier 3"" )"),"Tier 1") -> Tier 1 | M46: Gandaki
B47: =IFERROR(__xludf.DUMMYFUNCTION("""COMPUTED_VALUE"""),45862.1970949074) -> 45862.197 | C47: =IFERROR(__xludf.DUMMYFUNCTION("""COMPUTED_VALUE"""),"Sr sports and vans 42") -> Sr sports and vans 42 | D47: =IFERROR(__xludf.DUMMYFUNCTION("""COMPUTED_VALUE"""),"Abhishek Shrestha") -> Abhishek Shrestha | E47: =IFERROR(__xludf.DUMMYFUNCTION("""COMPUTED_VALUE"""),"Tokha, kathmandu") -> Tokha, kathmandu | F47: =IFERROR(__xludf.DUMMYFUNCTION("""COMPUTED_VALUE"""),9.803226972E9) -> 9803226972 | G47: =IFERROR(__xludf.DUMMYFUNCTION("""COMPUTED_VALUE"""),900.0) -> 900 | H47: =IFERROR(__xludf.DUMMYFUNCTION("""COMPUTED_VALUE"""),2500.0) -> 2500 | I47: =IFERROR(__xludf.DUMMYFUNCTION("""COMPUTED_VALUE"""),105.25) -> 105.25 | J47: =IFERROR(__xludf.DUMMYFUNCTION("""COMPUTED_VALUE"""),"Delivered") -> Delivered | K47: =IFERROR(__xludf.DUMMYFUNCTION("""COMPUTED_VALUE"""),45863.3140625) -> 45863.314 | L47: =IFERROR(__xludf.DUMMYFUNCTION("IFS( OR(REGEXMATCH(LOWER(E47), ""sirutar|sundarijal|sitapaila|duwakot|tikathali|bhaktapur|lalitpur|kathmandu|ktm|changunarayan|bageswari|ghalate|tinkune|balkot|tikathali""), REGEXMATCH(LOWER(E47), ""inside valley"")), ""Inside Valley"", REGEXMATCH(LOW"&"ER(E47), ""dharan|pokhara|biratnagar|birgunj|narayanghat|itahari|hetauda|janakpur|madi""), ""Tier 1"", REGEXMATCH(LOWER(E47), ""nepalgunj|butwal|birtamod|dhangadhi|ghorahi|beni|kushma|waling|haldibari|dulegauda|baitadi|bhadrapur|syangja|parbat|myagdi|da"&"ng|nuwakot|jhapa""), ""Tier 2"", TRUE, ""Tier 3"" )"),"Inside Valley") -> Inside Valley | M47: Bagmati
B48: =IFERROR(__xludf.DUMMYFUNCTION("""COMPUTED_VALUE"""),45862.19537037037) -> 45862.195 | C48: =IFERROR(__xludf.DUMMYFUNCTION("""COMPUTED_VALUE"""),"Dark brown 42") -> Dark brown 42 | D48: =IFERROR(__xludf.DUMMYFUNCTION("""COMPUTED_VALUE"""),"Suraj Gyawali") -> Suraj Gyawali | E48: =IFERROR(__xludf.DUMMYFUNCTION("""COMPUTED_VALUE"""),"Parsyang pokhara") -> Parsyang pokhara | F48: =IFERROR(__xludf.DUMMYFUNCTION("""COMPUTED_VALUE"""),9.84730756E9) -> 9847307560 | G48: =IFERROR(__xludf.DUMMYFUNCTION("""COMPUTED_VALUE"""),350.0) -> 350 | H48: =IFERROR(__xludf.DUMMYFUNCTION("""COMPUTED_VALUE"""),1350.0) -> 1350 | I48: =IFERROR(__xludf.DUMMYFUNCTION("""COMPUTED_VALUE"""),162.38) -> 162.38 | J48: =IFERROR(__xludf.DUMMYFUNCTION("""COMPUTED_VALUE"""),"Delivered") -> Delivered | K48: =IFERROR(__xludf.DUMMYFUNCTION("""COMPUTED_VALUE"""),45863.42010416667) -> 45863.42 | L48: =IFERROR(__xludf.DUMMYFUNCTION("IFS( OR(REGEXMATCH(LOWER(E48), ""sirutar|sundarijal|sitapaila|duwakot|tikathali|bhaktapur|lalitpur|kathmandu|ktm|changunarayan|bageswari|ghalate|tinkune|balkot|tikathali""), REGEXMATCH(LOWER(E48), ""inside valley"")), ""Inside Valley"", REGEXMATCH(LOW"&"ER(E48), ""dharan|pokhara|biratnagar|birgunj|narayanghat|itahari|hetauda|janakpur|madi""), ""Tier 1"", REGEXMATCH(LOWER(E48), ""nepalgunj|butwal|birtamod|dhangadhi|ghorahi|beni|kushma|waling|haldibari|dulegauda|baitadi|bhadrapur|syangja|parbat|myagdi|da"&"ng|nuwakot|jhapa""), ""Tier 2"", TRUE, ""Tier 3"" )"),"Tier 1") -> Tier 1 | M48: Gandaki
B49: =IFERROR(__xludf.DUMMYFUNCTION("""COMPUTED_VALUE"""),45862.188368055555) -> 45862.188 | C49: =IFERROR(__xludf.DUMMYFUNCTION("""COMPUTED_VALUE"""),"Vans 42") -> Vans 42 | D49: =IFERROR(__xludf.DUMMYFUNCTION("""COMPUTED_VALUE"""),"Bhuwan Dev") -> Bhuwan Dev | E49: =IFERROR(__xludf.DUMMYFUNCTION("""COMPUTED_VALUE"""),"Soil management dictorate harihar bhawan, lalitpur ") -> Soil management dictorate harihar bhawan, lalitpur | F49: =IFERROR(__xludf.DUMMYFUNCTION("""COMPUTED_VALUE"""),9.766381427E9) -> 9766381427 | G49: =IFERROR(__xludf.DUMMYFUNCTION("""COMPUTED_VALUE"""),700.0) -> 700 | H49: =IFERROR(__xludf.DUMMYFUNCTION("""COMPUTED_VALUE"""),1300.0) -> 1300 | I49: =IFERROR(__xludf.DUMMYFUNCTION("""COMPUTED_VALUE"""),102.25) -> 102.25 | J49: =IFERROR(__xludf.DUMMYFUNCTION("""COMPUTED_VALUE"""),"Delivered") -> Delivered | K49: =IFERROR(__xludf.DUMMYFUNCTION("""COMPUTED_VALUE"""),45863.28288194444) -> 45863.283 | L49: =IFERROR(__xludf.DUMMYFUNCTION("IFS( OR(REGEXMATCH(LOWER(E49), ""sirutar|sundarijal|sitapaila|duwakot|tikathali|bhaktapur|lalitpur|kathmandu|ktm|changunarayan|bageswari|ghalate|tinkune|balkot|tikathali""), REGEXMATCH(LOWER(E49), ""inside valley"")), ""Inside Valley"", REGEXMATCH(LOW"&"ER(E49), ""dharan|pokhara|biratnagar|birgunj|narayanghat|itahari|hetauda|janakpur|madi""), ""Tier 1"", REGEXMATCH(LOWER(E49), ""nepalgunj|butwal|birtamod|dhangadhi|ghorahi|beni|kushma|waling|haldibari|dulegauda|baitadi|bhadrapur|syangja|parbat|myagdi|da"&"ng|nuwakot|jhapa""), ""Tier 2"", TRUE, ""Tier 3"" )"),"Inside Valley") -> Inside Valley | M49: Bagmati
B50: =IFERROR(__xludf.DUMMYFUNCTION("""COMPUTED_VALUE"""),45861.20143518518) -> 45861.201 | C50: =IFERROR(__xludf.DUMMYFUNCTION("""COMPUTED_VALUE"""),"Dunk Low pro 39") -> Dunk Low pro 39 | D50: =IFERROR(__xludf.DUMMYFUNCTION("""COMPUTED_VALUE"""),"Arpan Neupane") -> Arpan Neupane | E50: =IFERROR(__xludf.DUMMYFUNCTION("""COMPUTED_VALUE"""),"Kharaney path, leknath kaski") -> Kharaney path, leknath kaski | F50: =IFERROR(__xludf.DUMMYFUNCTION("""COMPUTED_VALUE"""),9.846952971E9) -> 9846952971 | G50: =IFERROR(__xludf.DUMMYFUNCTION("""COMPUTED_VALUE"""),350.0) -> 350 | H50: =IFERROR(__xludf.DUMMYFUNCTION("""COMPUTED_VALUE"""),1350.0) -> 1350 | I50: =IFERROR(__xludf.DUMMYFUNCTION("""COMPUTED_VALUE"""),162.38) -> 162.38 | J50: =IFERROR(__xludf.DUMMYFUNCTION("""COMPUTED_VALUE"""),"Delivered") -> Delivered | K50: =IFERROR(__xludf.DUMMYFUNCTION("""COMPUTED_VALUE"""),45862.362337962964) -> 45862.362 | L50: =IFERROR(__xludf.DUMMYFUNCTION("IFS( OR(REGEXMATCH(LOWER(E50), ""sirutar|sundarijal|sitapaila|duwakot|tikathali|bhaktapur|lalitpur|kathmandu|ktm|changunarayan|bageswari|ghalate|tinkune|balkot|tikathali""), REGEXMATCH(LOWER(E50), ""inside valley"")), ""Inside Valley"", REGEXMATCH(LOW"&"ER(E50), ""dharan|pokhara|biratnagar|birgunj|narayanghat|itahari|hetauda|janakpur|madi""), ""Tier 1"", REGEXMATCH(LOWER(E50), ""nepalgunj|butwal|birtamod|dhangadhi|ghorahi|beni|kushma|waling|haldibari|dulegauda|baitadi|bhadrapur|syangja|parbat|myagdi|da"&"ng|nuwakot|jhapa""), ""Tier 2"", TRUE, ""Tier 3"" )"),"Tier 3") -> Tier 3 | M50: Gandaki
B51: =IFERROR(__xludf.DUMMYFUNCTION("""COMPUTED_VALUE"""),45861.199224537035) -> 45861.199 | C51: =IFERROR(__xludf.DUMMYFUNCTION("""COMPUTED_VALUE"""),"Vans 41") -> Vans 41 | D51: =IFERROR(__xludf.DUMMYFUNCTION("""COMPUTED_VALUE"""),"Menal Shrestha") -> Menal Shrestha | E51: =IFERROR(__xludf.DUMMYFUNCTION("""COMPUTED_VALUE"""),"Steel Tower, jawalakhel") -> Steel Tower, jawalakhel | F51: =IFERROR(__xludf.DUMMYFUNCTION("""COMPUTED_VALUE"""),9.818994553E9) -> 9818994553 | G51: =IFERROR(__xludf.DUMMYFUNCTION("""COMPUTED_VALUE"""),700.0) -> 700 | H51: =IFERROR(__xludf.DUMMYFUNCTION("""COMPUTED_VALUE"""),1300.0) -> 1300 | I51: =IFERROR(__xludf.DUMMYFUNCTION("""COMPUTED_VALUE"""),102.25) -> 102.25 | J51: =IFERROR(__xludf.DUMMYFUNCTION("""COMPUTED_VALUE"""),"Delivered") -> Delivered | K51: =IFERROR(__xludf.DUMMYFUNCTION("""COMPUTED_VALUE"""),45861.44431712963) -> 45861.444 | L51: =IFERROR(__xludf.DUMMYFUNCTION("IFS( OR(REGEXMATCH(LOWER(E51), ""sirutar|sundarijal|sitapaila|duwakot|tikathali|bhaktapur|lalitpur|kathmandu|ktm|changunarayan|bageswari|ghalate|tinkune|balkot|tikathali""), REGEXMATCH(LOWER(E51), ""inside valley"")), ""Inside Valley"", REGEXMATCH(LOW"&"ER(E51), ""dharan|pokhara|biratnagar|birgunj|narayanghat|itahari|hetauda|janakpur|madi""), ""Tier 1"", REGEXMATCH(LOWER(E51), ""nepalgunj|butwal|birtamod|dhangadhi|ghorahi|beni|kushma|waling|haldibari|dulegauda|baitadi|bhadrapur|syangja|parbat|myagdi|da"&"ng|nuwakot|jhapa""), ""Tier 2"", TRUE, ""Tier 3"" )"),"Tier 3") -> Tier 3 | M51: Bagmati
B52: =IFERROR(__xludf.DUMMYFUNCTION("""COMPUTED_VALUE"""),45860.51074074074) -> 45860.511 | C52: =IFERROR(__xludf.DUMMYFUNCTION("""COMPUTED_VALUE"""),"Sr delta size 39") -> Sr delta size 39 | D52: =IFERROR(__xludf.DUMMYFUNCTION("""COMPUTED_VALUE"""),"Sanjit Tamang") -> Sanjit Tamang | E52: =IFERROR(__xludf.DUMMYFUNCTION("""COMPUTED_VALUE"""),"Sirutar, bhaktapur") -> Sirutar, bhaktapur | F52: =IFERROR(__xludf.DUMMYFUNCTION("""COMPUTED_VALUE"""),9.826764749E9) -> 9826764749 | G52: =IFERROR(__xludf.DUMMYFUNCTION("""COMPUTED_VALUE"""),300.0) -> 300 | H52: =IFERROR(__xludf.DUMMYFUNCTION("""COMPUTED_VALUE"""),1300.0) -> 1300 | I52: =IFERROR(__xludf.DUMMYFUNCTION("""COMPUTED_VALUE"""),102.25) -> 102.25 | J52: =IFERROR(__xludf.DUMMYFUNCTION("""COMPUTED_VALUE"""),"Delivered") -> Delivered | K52: =IFERROR(__xludf.DUMMYFUNCTION("""COMPUTED_VALUE"""),45862.395266203705) -> 45862.395 | L52: =IFERROR(__xludf.DUMMYFUNCTION("IFS( OR(REGEXMATCH(LOWER(E52), ""sirutar|sundarijal|sitapaila|duwakot|tikathali|bhaktapur|lalitpur|kathmandu|ktm|changunarayan|bageswari|ghalate|tinkune|balkot|tikathali""), REGEXMATCH(LOWER(E52), ""inside valley"")), ""Inside Valley"", REGEXMATCH(LOW"&"ER(E52), ""dharan|pokhara|biratnagar|birgunj|narayanghat|itahari|hetauda|janakpur|madi""), ""Tier 1"", REGEXMATCH(LOWER(E52), ""nepalgunj|butwal|birtamod|dhangadhi|ghorahi|beni|kushma|waling|haldibari|dulegauda|baitadi|bhadrapur|syangja|parbat|myagdi|da"&"ng|nuwakot|jhapa""), ""Tier 2"", TRUE, ""Tier 3"" )"),"Inside Valley") -> Inside Valley | M52: Bagmati
B53: =IFERROR(__xludf.DUMMYFUNCTION("""COMPUTED_VALUE"""),45857.22825231482) -> 45857.228 | C53: =IFERROR(__xludf.DUMMYFUNCTION("""COMPUTED_VALUE"""),"Vans 43") -> Vans 43 | D53: =IFERROR(__xludf.DUMMYFUNCTION("""COMPUTED_VALUE"""),"Newar Shyam") -> Newar Shyam | E53: =IFERROR(__xludf.DUMMYFUNCTION("""COMPUTED_VALUE"""),"Pakhapani, dang") -> Pakhapani, dang | F53: =IFERROR(__xludf.DUMMYFUNCTION("""COMPUTED_VALUE"""),9.843713594E9) -> 9843713594 | G53: =IFERROR(__xludf.DUMMYFUNCTION("""COMPUTED_VALUE"""),750.0) -> 750 | H53: =IFERROR(__xludf.DUMMYFUNCTION("""COMPUTED_VALUE"""),1350.0) -> 1350 | I53: =IFERROR(__xludf.DUMMYFUNCTION("""COMPUTED_VALUE"""),232.38) -> 232.38 | J53: =IFERROR(__xludf.DUMMYFUNCTION("""COMPUTED_VALUE"""),"Delivered") -> Delivered | K53: =IFERROR(__xludf.DUMMYFUNCTION("""COMPUTED_VALUE"""),45860.518425925926) -> 45860.518 | L53: =IFERROR(__xludf.DUMMYFUNCTION("IFS( OR(REGEXMATCH(LOWER(E53), ""sirutar|sundarijal|sitapaila|duwakot|tikathali|bhaktapur|lalitpur|kathmandu|ktm|changunarayan|bageswari|ghalate|tinkune|balkot|tikathali""), REGEXMATCH(LOWER(E53), ""inside valley"")), ""Inside Valley"", REGEXMATCH(LOW"&"ER(E53), ""dharan|pokhara|biratnagar|birgunj|narayanghat|itahari|hetauda|janakpur|madi""), ""Tier 1"", REGEXMATCH(LOWER(E53), ""nepalgunj|butwal|birtamod|dhangadhi|ghorahi|beni|kushma|waling|haldibari|dulegauda|baitadi|bhadrapur|syangja|parbat|myagdi|da"&"ng|nuwakot|jhapa""), ""Tier 2"", TRUE, ""Tier 3"" )"),"Tier 2") -> Tier 2 | M53: Lumbini
B54: =IFERROR(__xludf.DUMMYFUNCTION("""COMPUTED_VALUE"""),45857.20888888889) -> 45857.209 | C54: =IFERROR(__xludf.DUMMYFUNCTION("""COMPUTED_VALUE"""),"Gray 42") -> Gray 42 | D54: =IFERROR(__xludf.DUMMYFUNCTION("""COMPUTED_VALUE"""),"Diwash") -> Diwash | E54: =IFERROR(__xludf.DUMMYFUNCTION("""COMPUTED_VALUE"""),"Morang pathari") -> Morang pathari | F54: =IFERROR(__xludf.DUMMYFUNCTION("""COMPUTED_VALUE"""),9.746898035E9) -> 9746898035 | G54: =IFERROR(__xludf.DUMMYFUNCTION("""COMPUTED_VALUE"""),450.0) -> 450 | H54: =IFERROR(__xludf.DUMMYFUNCTION("""COMPUTED_VALUE"""),1450.0) -> 1450 | I54: =IFERROR(__xludf.DUMMYFUNCTION("""COMPUTED_VALUE"""),232.63) -> 232.63 | J54: =IFERROR(__xludf.DUMMYFUNCTION("""COMPUTED_VALUE"""),"Delivered") -> Delivered | K54: =IFERROR(__xludf.DUMMYFUNCTION("""COMPUTED_VALUE"""),45862.316307870366) -> 45862.316 | L54: =IFERROR(__xludf.DUMMYFUNCTION("IFS( OR(REGEXMATCH(LOWER(E54), ""sirutar|sundarijal|sitapaila|duwakot|tikathali|bhaktapur|lalitpur|kathmandu|ktm|changunarayan|bageswari|ghalate|tinkune|balkot|tikathali""), REGEXMATCH(LOWER(E54), ""inside valley"")), ""Inside Valley"", REGEXMATCH(LOW"&"ER(E54), ""dharan|pokhara|biratnagar|birgunj|narayanghat|itahari|hetauda|janakpur|madi""), ""Tier 1"", REGEXMATCH(LOWER(E54), ""nepalgunj|butwal|birtamod|dhangadhi|ghorahi|beni|kushma|waling|haldibari|dulegauda|baitadi|bhadrapur|syangja|parbat|myagdi|da"&"ng|nuwakot|jhapa""), ""Tier 2"", TRUE, ""Tier 3"" )"),"Tier 3") -> Tier 3 | M54: Koshi
B55: =IFERROR(__xludf.DUMMYFUNCTION("""COMPUTED_VALUE"""),45857.206296296295) -> 45857.206 | C55: =IFERROR(__xludf.DUMMYFUNCTION("""COMPUTED_VALUE"""),"Nike White and gray 43") -> Nike White and gray 43 | D55: =IFERROR(__xludf.DUMMYFUNCTION("""COMPUTED_VALUE"""),"Nishan sigdel") -> Nishan sigdel | E55: =IFERROR(__xludf.DUMMYFUNCTION("""COMPUTED_VALUE"""),"Sunsari, ramdhuni bhasi, lalpur") -> Sunsari, ramdhuni bhasi, lalpur | F55: =IFERROR(__xludf.DUMMYFUNCTION("""COMPUTED_VALUE"""),9.829369398E9) -> 9829369398 | G55: =IFERROR(__xludf.DUMMYFUNCTION("""COMPUTED_VALUE"""),450.0) -> 450 | H55: =IFERROR(__xludf.DUMMYFUNCTION("""COMPUTED_VALUE"""),2450.0) -> 2450 | I55: =IFERROR(__xludf.DUMMYFUNCTION("""COMPUTED_VALUE"""),215.13) -> 215.13 | J55: =IFERROR(__xludf.DUMMYFUNCTION("""COMPUTED_VALUE"""),"Delivered") -> Delivered | K55: =IFERROR(__xludf.DUMMYFUNCTION("""COMPUTED_VALUE"""),45860.3343287037) -> 45860.334 | L55: =IFERROR(__xludf.DUMMYFUNCTION("IFS( OR(REGEXMATCH(LOWER(E55), ""sirutar|sundarijal|sitapaila|duwakot|tikathali|bhaktapur|lalitpur|kathmandu|ktm|changunarayan|bageswari|ghalate|tinkune|balkot|tikathali""), REGEXMATCH(LOWER(E55), ""inside valley"")), ""Inside Valley"", REGEXMATCH(LOW"&"ER(E55), ""dharan|pokhara|biratnagar|birgunj|narayanghat|itahari|hetauda|janakpur|madi""), ""Tier 1"", REGEXMATCH(LOWER(E55), ""nepalgunj|butwal|birtamod|dhangadhi|ghorahi|beni|kushma|waling|haldibari|dulegauda|baitadi|bhadrapur|syangja|parbat|myagdi|da"&"ng|nuwakot|jhapa""), ""Tier 2"", TRUE, ""Tier 3"" )"),"Tier 3") -> Tier 3 | M55: Koshi
B56: =IFERROR(__xludf.DUMMYFUNCTION("""COMPUTED_VALUE"""),45857.19940972222) -> 45857.199 | C56: =IFERROR(__xludf.DUMMYFUNCTION("""COMPUTED_VALUE"""),"Brown 39 nike") -> Brown 39 nike | D56: =IFERROR(__xludf.DUMMYFUNCTION("""COMPUTED_VALUE"""),"Samir Khadka") -> Samir Khadka | E56: =IFERROR(__xludf.DUMMYFUNCTION("""COMPUTED_VALUE"""),"Mullani, manakamana mandir") -> Mullani, manakamana mandir | F56: =IFERROR(__xludf.DUMMYFUNCTION("""COMPUTED_VALUE"""),9.80344133E9) -> 9803441330 | G56: =IFERROR(__xludf.DUMMYFUNCTION("""COMPUTED_VALUE"""),300.0) -> 300 | H56: =IFERROR(__xludf.DUMMYFUNCTION("""COMPUTED_VALUE"""),1300.0) -> 1300 | I56: =IFERROR(__xludf.DUMMYFUNCTION("""COMPUTED_VALUE"""),152.25) -> 152.25 | J56: =IFERROR(__xludf.DUMMYFUNCTION("""COMPUTED_VALUE"""),"Delivered") -> Delivered | K56: =IFERROR(__xludf.DUMMYFUNCTION("""COMPUTED_VALUE"""),45858.38641203704) -> 45858.386 | L56: =IFERROR(__xludf.DUMMYFUNCTION("IFS( OR(REGEXMATCH(LOWER(E56), ""sirutar|sundarijal|sitapaila|duwakot|tikathali|bhaktapur|lalitpur|kathmandu|ktm|changunarayan|bageswari|ghalate|tinkune|balkot|tikathali""), REGEXMATCH(LOWER(E56), ""inside valley"")), ""Inside Valley"", REGEXMATCH(LOW"&"ER(E56), ""dharan|pokhara|biratnagar|birgunj|narayanghat|itahari|hetauda|janakpur|madi""), ""Tier 1"", REGEXMATCH(LOWER(E56), ""nepalgunj|butwal|birtamod|dhangadhi|ghorahi|beni|kushma|waling|haldibari|dulegauda|baitadi|bhadrapur|syangja|parbat|myagdi|da"&"ng|nuwakot|jhapa""), ""Tier 2"", TRUE, ""Tier 3"" )"),"Tier 3") -> Tier 3 | M56: Gandaki
B57: =IFERROR(__xludf.DUMMYFUNCTION("""COMPUTED_VALUE"""),45857.197800925926) -> 45857.198 | C57: =IFERROR(__xludf.DUMMYFUNCTION("""COMPUTED_VALUE"""),"Nike 11 red 44") -> Nike 11 red 44 | D57: =IFERROR(__xludf.DUMMYFUNCTION("""COMPUTED_VALUE"""),"Dipesh Bhusal") -> Dipesh Bhusal | E57: =IFERROR(__xludf.DUMMYFUNCTION("""COMPUTED_VALUE"""),"Accham district, sanfebagar") -> Accham district, sanfebagar | F57: =IFERROR(__xludf.DUMMYFUNCTION("""COMPUTED_VALUE"""),9.86471728E9) -> 9864717280 | G57: =IFERROR(__xludf.DUMMYFUNCTION("""COMPUTED_VALUE"""),650.0) -> 650 | H57: =IFERROR(__xludf.DUMMYFUNCTION("""COMPUTED_VALUE"""),1450.0) -> 1450 | I57: =IFERROR(__xludf.DUMMYFUNCTION("""COMPUTED_VALUE"""),212.63) -> 212.63 | J57: =IFERROR(__xludf.DUMMYFUNCTION("""COMPUTED_VALUE"""),"Delivered") -> Delivered | K57: =IFERROR(__xludf.DUMMYFUNCTION("""COMPUTED_VALUE"""),45860.51934027778) -> 45860.519 | L57: =IFERROR(__xludf.DUMMYFUNCTION("IFS( OR(REGEXMATCH(LOWER(E57), ""sirutar|sundarijal|sitapaila|duwakot|tikathali|bhaktapur|lalitpur|kathmandu|ktm|changunarayan|bageswari|ghalate|tinkune|balkot|tikathali""), REGEXMATCH(LOWER(E57), ""inside valley"")), ""Inside Valley"", REGEXMATCH(LOW"&"ER(E57), ""dharan|pokhara|biratnagar|birgunj|narayanghat|itahari|hetauda|janakpur|madi""), ""Tier 1"", REGEXMATCH(LOWER(E57), ""nepalgunj|butwal|birtamod|dhangadhi|ghorahi|beni|kushma|waling|haldibari|dulegauda|baitadi|bhadrapur|syangja|parbat|myagdi|da"&"ng|nuwakot|jhapa""), ""Tier 2"", TRUE, ""Tier 3"" )"),"Tier 3") -> Tier 3 | M57: Sudurpashchim
B58: =IFERROR(__xludf.DUMMYFUNCTION("""COMPUTED_VALUE"""),45857.19510416666) -> 45857.195 | C58: =IFERROR(__xludf.DUMMYFUNCTION("""COMPUTED_VALUE"""),"Vans 41") -> Vans 41 | D58: =IFERROR(__xludf.DUMMYFUNCTION("""COMPUTED_VALUE"""),"Aashish Aryal") -> Aashish Aryal | E58: =IFERROR(__xludf.DUMMYFUNCTION("""COMPUTED_VALUE"""),"Sunwal 13, badera") -> Sunwal 13, badera | F58: =IFERROR(__xludf.DUMMYFUNCTION("""COMPUTED_VALUE"""),9.762248226E9) -> 9762248226 | G58: =IFERROR(__xludf.DUMMYFUNCTION("""COMPUTED_VALUE"""),700.0) -> 700 | H58: =IFERROR(__xludf.DUMMYFUNCTION("""COMPUTED_VALUE"""),1300.0) -> 1300 | I58: =IFERROR(__xludf.DUMMYFUNCTION("""COMPUTED_VALUE"""),232.25) -> 232.25 | J58: =IFERROR(__xludf.DUMMYFUNCTION("""COMPUTED_VALUE"""),"Delivered") -> Delivered | K58: =IFERROR(__xludf.DUMMYFUNCTION("""COMPUTED_VALUE"""),45860.359872685185) -> 45860.36 | L58: =IFERROR(__xludf.DUMMYFUNCTION("IFS( OR(REGEXMATCH(LOWER(E58), ""sirutar|sundarijal|sitapaila|duwakot|tikathali|bhaktapur|lalitpur|kathmandu|ktm|changunarayan|bageswari|ghalate|tinkune|balkot|tikathali""), REGEXMATCH(LOWER(E58), ""inside valley"")), ""Inside Valley"", REGEXMATCH(LOW"&"ER(E58), ""dharan|pokhara|biratnagar|birgunj|narayanghat|itahari|hetauda|janakpur|madi""), ""Tier 1"", REGEXMATCH(LOWER(E58), ""nepalgunj|butwal|birtamod|dhangadhi|ghorahi|beni|kushma|waling|haldibari|dulegauda|baitadi|bhadrapur|syangja|parbat|myagdi|da"&"ng|nuwakot|jhapa""), ""Tier 2"", TRUE, ""Tier 3"" )"),"Tier 3") -> Tier 3 | M58: Lumbini
